Workbook
Name NewHoldingValue: #REF!
Name NewPortfolioPercent: #REF!
Name PortfolioPercent: 'Copy of Holdings'!$I$3:$I$20
Name HoldingValue: 'Copy of Holdings 1'!$H$3:$H$20
Name TotalValue: 'Copy of Holdings 1'!$H$21
Name StocksValue: 'Copy of Stocks'!$H$5:$H$12
Name NewHoldingValue: #REF!
Name TotalValue: 'Copy of Holdings'!$H$21
Name TotalStockValue: 'Copy of Stocks'!$H$13
Name NewPortfolioPercent: #REF!
Name NewTotalValue: #REF!
Name NewTotalValue: #REF!
Name PortfolioPercent: 'Copy of Holdings 1'!$I$3:$I$20
Name HoldingValue: 'Copy of Holdings'!$H$3:$H$20

Sheet 2018
A1: Payment Schedule 2018
A2: Schedule | B2: Week 1 | C2: Week 2 | D2: REMAINING BALANCE | E2: TOTAL SAVINGS | F2: TOTAL DEBT
A3: Starting Balance | B3: 0 | C3: =B12 | D3: 0 | E3: =D27+B7+C7 -> 0 | F3: =#REF!-B8-C8 -> #REF!
A4: Income #1 | B4: 2500 | C4: 1850
A5: Additional Income | B5: 1900 | C5: 0
A6: EXPENSES | B6: =#REF! -> #REF! | C6: 250
A7: SAVINGS | B7: =B27 | C7: =C27
A8: DEBTS MANAGEMENT | B8: =#REF! -> #REF! | C8: =#REF! -> #REF!
A9: PERSONAL EXPENSES | B9: =B22 -> 610 | C9: =C22 -> 800
A10: BUSINESS EXPENSES | B10: =#REF!-#REF! -> #REF! | C10: =#REF!-#REF! -> #REF!
A11: NON-PROFIT | B11: =#REF! -> #REF! | C11: 50
A12: Net
A14: PERSONAL EXPENSES | B14: WEEK 1 | C14: WEEK 2 | D14: TOTAL | E14: STATUS | F14: SCHEDULE
A15: Groceries | B15: 100 | C15: 100 | E15: ACTIVE
A16: Restaurants & Bars | B16: 200 | C16: 200 | E16: ACTIVE
A17: Services | B17: 10 | C17: 0 | E17: ACTIVE | F17: Spotify, Nomad List
A18: Travel (Hosting, Flights) | B18: 200 | C18: 400 | E18: PAUSED
A19: Clothing | B19: 100 | C19: 100 | E19: PAUSED
A20: Healthcare | B20: 0 | C20: 0 | E20: PAUSED
A21: Misc. | B21: 0 | C21: 0 | E21: PAUSED
A22: TOTAL | B22: =sum(B15:B21) -> 610 | C22: =sum(C15:C21) -> 800
A24: SAVINGS | B24: WEEK 1 | C24: WEEK 2 | D24: TOTAL | E24: STATUS | F24: SCHEDULE
A25: Travel (Simple) | B25: 0 | C25: 0 | D25: 0 | E25: ACTIVE
A26: Rainy Day (Simple) | B26: 100 | C26: 0 | D26: 100 | E26: ACTIVE
A27: TOTAL
A29: INVEST | B29: WEEK 1 | C29: WEEK 2 | D29: TOTAL | E29: STATUS | F29: SCHEDULE
A30: Hashtag Language | B30: 100 | C30: 100 | D30: 1612 | E30: ACTIVE
A31: Roth IRA | B31: 100 | C31: 100 | D31: 300 | E31: ACTIVE
A32: Ethereum | B32: 100 | C32: 0 | D32: 0 | E32: ACTIVE
A33: Bitcoin | B33: 0 | C33: 0 | D33: 0.01843329 | E33: ACTIVE
A34: EOS | B34: 0 | C34: 0 | D34: 0 | E34: PAUSED
A35: XRP | B35: 0 | C35: 0 | D35: 300 | E35: PAUSED
A36: NEO | B36: 0 | C36: 0 | D36: 0 | E36: PAUSED | F36: *Hold for Nancy
A37: DCR | B37: 0 | C37: 0 | D37: 0 | E37: PAUSED
A38: XLM | B38: 0 | C38: 0 | D38: 0 | E38: PAUSED
A39: ETrade | B39: 0 | C39: 0 | D39: 0 | E39: PAUSED | F39: TSLA, AMZN, FB
A41: DEBTS | B41: WEEK 1 | C41: WEEK 2 | D41: TOTAL | E41: STATUS | F41: SCHEDULE
A42: Capital One | B42: 250 | C42: 250 | D42: 500 | E42: ACTIVE | F42: 1st, 15th
A43: Wells Fargo | B43: 200 | C43: 200 | D43: 2800 | E43: ACTIVE | F43: 1st, 15th (15 Payments~12/1/2017)
A44: NuVision | B44: 50 | C44: 50 | D44: 350 | E44: ACTIVE | F44: 1st (7 Payments~12/1/2017)
A45: Braden (Venmo) | B45: 100 | C45: 0 | D45: 3210.37 | E45: ACTIVE | F45: 4% APR (32 Payments~12/1/2017)
A46: Grandma (Venmo) | B46: 100 | C46: 100 | D46: 14000 | E46: ACTIVE | F46: 1st
A47: JCrew | B47: 0 | C47: 0 | D47: 643 | E47: ACTIVE | F47: 15th
A48: Great Lakes | B48: 0 | C48: 100 | D48: 9311 | E48: ACTIVE | F48: TBD
A49: LLC Disolution | B49: 0 | C49: 0 | D49: 400 | E49: PAUSED | F49: TBD
A50: Dad & Mom | B50: 0 | C50: 0 | D50: 4000 | E50: PAUSED | F50: TBD
A51: Paypal | B51: 0 | C51: 0 | D51: 0 | E51: PAID OFF | F51: TBD
A52: Nordstrom | B52: 0 | C52: 0 | D52: 0 | E52: PAID OFF | F52: TBD
A55: PHILANTHOPY | B55: WEEK 1 | C55: WEEK 2 | D55: TOTAL | E55: STATUS | F55: SCHEDULE
A56: Donations | B56: 50 | C56: 0 | E56: PAUSED | F56: Active English

Sheet DASHBOARD
B1: DASHBOARD
B2: =AVERAGE(BUDGET!AM13:AX13) -> 16241.259 | C2: =HOLDINGS!C52 -> 12251244 | D2: 675 | E2: 0.4 | F2: =LIABILITIES!C41 -> 25401.63 | G2: XXXX
B3: Avg. Monthly Net | C3: Net worth | D3: Credit Score | E3: Credit Usage | F3: Debt | G3: xxxx
B22: Goals:
B23: - $350k salary
B24: - Exercise $8k CSI shares
B25: - Pay $50k liabilities | C25: (Upstart, Sapphire priorities, lower spending 50%)
B26: - $30k to invest into seed
B27: - Purchase Jaeger LeCouture
B28: - $20k in ETH, $20k in BTC
B29: - $30k cash savings (75% in high yield) | D29: Amount Needed | E29: Due
B30: - 800 credit score | D30: 82631 | E30: 45778 | F30: Consensys Shares
B31: - $10k in IRA, Stocks | D31: 15000 | F31: Bitcoin
D32: 35000 | F32: Ethereum
D33: 10000 | F33: Stock, IRA
D34: 30000 | F34: Savings
D36: =sum(D30:D34) -> 172631

Sheet BUDGET
A1: Categories | C1: Jan | D1: Feb | E1: Mar | F1: Apr | G1: May | H1: Jun | I1: Jul '19 | J1: Aug '19 | K1: Sept '19 | L1: Oct '19 | M1: Nov '19 | N1: Dec '19 | O1: Jan '20 | P1: Feb '20 | Q1: Mar '20 | R1: Apr '20 | S1: May '20 | T1: Jun '20 | U1: Jul '20 | V1: Aug '20 | W1: Sep '20 | X1: Oct '20 | Y1: Nov '20 | Z1: Dec '20 | AA1: Jan '21 | AB1: Feb'21 | AC1: Mar '21 | AD1: Apr '21 | AE1: May '21 | AF1: Jun '21 | AG1: Jul '21 | AH1: Aug '21 | AI1: Sept '21 | AJ1: Oct '21 | AK1: Nov '21 | AL1: Dec '21 | AM1: Jan '22 | AN1: Feb '22 | AO1: Mar '22 | AP1: Apr '22 | AQ1: May '22 | AR1: Jun '22 | AS1: July '22 | AT1: Aug '22 | AU1: Sept '22 | AV1: Oct '22 | AW1: Nov '22 | AX1: Dec '22 | AY1: Jan '23 | AZ1: Feb '23 | BA1: Mar '23 | BB1: Apr '23 | BC1: May '23 | BD1: Jun '23 | BE1: Jul '23 | BF1: Aug '23 | BG1: Sept '23 | BH1: Oct '23 | BI1: Nov '23 | BJ1: Dec '23 | BK1: FY 2023 | BL1: Jan '24 | BM1: Feb '24 | BN1: Mar '24 | BO1: Apr '24 | BP1: May '24 | BQ1: Jun '24 | BR1: Jul '24 | BS1: Aug '24 | BT1: Sep '24 | BU1: Oct '24 | BV1: Nov '24 | BW1: Dec '24 | BX1: FY 2024 | BY1: Jan '25 | BZ1: Feb '25 | CA1: Mar '25 | CB1: Apr '25 | CC1: May '25 | CD1: Jun '25 | CE1: Jul '25 | CF1: Aug '25 | CG1: Sep '25 | CH1: Oct '25 | CI1: Nov '25 | CJ1: Dec '25 | CK1: FY 2025 | CL1: Jan '26 | CM1: Feb '26 | CN1: Mar '26 | CO1: Apr '26 | CP1: May '26 | CQ1: Jun '26 | CR1: Jul '26 | CS1: Aug '26 | CT1: Sep '26 | CU1: Oct '26 | CV1: Nov '26 | CW1: Dec '26 | CX1: FY 2026 | CY1: Nov '25 | CZ1: Dec '25
A2: Income
A3: Salary
B4: Salary (Pre-Tax of 34%) | C4: 10000 | D4: 10000 | E4: 10000 | F4: 10000 | G4: 10000 | H4: 10000 | I4: 10000 | J4: =120000/12 -> 10000 | K4: =120000/12 -> 10000 | L4: =120000/12 -> 10000 | M4: =120000/12 -> 10000 | N4: =120000/12 -> 10000 | O4: =120000/12 -> 10000 | P4: =120000/12 -> 10000 | Q4: =123000/12 -> 10250 | R4: =123000/12 -> 10250 | S4: =123000/12 -> 10250 | T4: =123000/12 -> 10250 | U4: =123000/12 -> 10250 | V4: =123000/12 -> 10250 | W4: =123000/12 -> 10250 | X4: =123000/12 -> 10250 | Y4: =123000/12 -> 10250 | Z4: =160000/12 -> 13333.333 | AA4: =160000/12 -> 13333.333 | AB4: =160000/12 -> 13333.333 | AC4: =160000/12 -> 13333.333 | AD4: =160000/12 -> 13333.333 | AE4: =160000/12 -> 13333.333 | AF4: =160000/12 -> 13333.333 | AG4: =160000/12 -> 13333.333 | ... AJ4: =160000/12 -> 13333.333 | AK4: =165000/12 -> 13750 | AL4: =210000/12 -> 17500 | AM4: =210000/12 -> 17500 | AN4: =210000/12 -> 17500 | AO4: =210000/12 -> 17500 | AP4: =210000/12 -> 17500 | AQ4: =210000/12 -> 17500 | AR4: =210000/12 -> 17500 | AS4: =210000/12 -> 17500 | ... AZ4: =210000/12 -> 17500 | BA4: =200000/12 -> 16666.667 | BB4: =200000/12 -> 16666.667 | BC4: =200000/12 -> 16666.667 | BD4: =200000/12 -> 16666.667 | BE4: =200000/12 -> 16666.667 | BF4: =220000/12 -> 18333.333 | BG4: =220000/12 -> 18333.333 | BH4: =220000/12 -> 18333.333 | BI4: =220000/12 -> 18333.333 | BJ4: =220000/12 -> 18333.333 | BL4: =220000/12 -> 18333.333 | BM4: =220000/12 -> 18333.333 | BN4: =220000/12 -> 18333.333 | BO4: =220000/12 -> 18333.333 | BP4: =220000/12 -> 18333.333 | BQ4: =220000/12 -> 18333.333 | BR4: =220000/12 -> 18333.333 | BS4: =220000/12 -> 18333.333 | ... BW4: =220000/12 -> 18333.333 | BX4: =sum(BL4:BW4) -> 220000 | BY4: =220000/12 -> 18333.333 | BZ4: =220000/12 -> 18333.333 | CA4: =220000/12 -> 18333.333 | CB4: =220000/12 -> 18333.333 | CC4: =360000/12 -> 30000 | CD4: =360000/12 -> 30000 | CE4: =360000/12 -> 30000 | CF4: =360000/12 -> 30000 | CG4: =360000/12 -> 30000 | CH4: =360000/12 -> 30000 | CI4: =360000/12 -> 30000 | CJ4: =360000/12 -> 30000 | CK4: =sum(BY4:CJ4) -> 313333.33 | CL4: =220000/12 -> 18333.333 | CM4: =220000/12 -> 18333.333 | CN4: =220000/12 -> 18333.333 | CO4: =360000/12 -> 30000 | CP4: =360000/12 -> 30000 | CQ4: =360000/12 -> 30000 | CR4: =360000/12 -> 30000 | CS4: =360000/12 -> 30000 | CT4: =360000/12 -> 30000 | CU4: =360000/12 -> 30000 | CV4: =360000/12 -> 30000 | CW4: =360000/12 -> 30000 | CX4: =sum(CL4:CW4) -> 325000 | CY4: =400000/12 -> 33333.333 | CZ4: =400000/12 -> 33333.333
B5: Freelance (Taxed at 41%) | C5: 0 | D5: 3000 | E5: 0 | F5: 0 | G5: 0 | H5: 0 | I5: 5000 | J5: 5000 | K5: 0 | L5: 0 | M5: 800 | N5: =500 -> 500 | O5: 0 | P5: =5000 -> 5000 | Q5: 0 | R5: 0 | S5: 0 | T5: 0 | U5: 0 | V5: 0 | W5: 0 | X5: 0 | Y5: 0 | Z5: 0 | AA5: 0 | AB5: 0 | AC5: 0 | AD5: 0 | AE5: 0 | AF5: 0 | AG5: 0 | AH5: 0 | AI5: 0 | AJ5: 0 | AK5: 0 | AL5: 0 | AM5: 0 | AN5: 0 | AO5: 0 | AP5: 0 | AQ5: 0 | AR5: 0 | AS5: 0 | AT5: 0 | AU5: 0 | AV5: 0 | AW5: 0 | AX5: 0 | AY5: 0 | AZ5: 0 | BA5: 0 | BB5: 0 | BC5: 0 | BD5: 0 | BE5: 0 | BF5: 0 | BG5: 0 | BH5: 0 | BI5: 0 | BJ5: 0 | BL5: 0 | BM5: 0 | BN5: 0 | BO5: 0 | BP5: 0 | BQ5: 0 | BR5: 0 | BS5: 0 | BT5: 0 | BU5: 0 | BV5: 0 | BW5: 0 | BX5: =sum(BL5:BW5) -> 0 | BY5: 0 | BZ5: 0 | CA5: 0 | CB5: 0 | CC5: 0 | CD5: 0 | CE5: 0 | CF5: 0 | CG5: 0 | CH5: 0 | CI5: 0 | CJ5: 0 | CK5: =sum(BY5:CJ5) -> 0 | CL5: 0 | CM5: 0 | CN5: 0 | CO5: 0 | CP5: 0 | CQ5: 0 | CR5: 0 | CS5: 0 | CT5: 0 | CU5: 0 | CV5: 0 | CW5: 0 | CX5: =sum(CL5:CW5) -> 0 | CY5: 0 | CZ5: 0
A6: Freelance
B7: Secondary Income (Taxed @ 34%) | C7: 0 | D7: 0 | E7: 0 | F7: 0 | G7: 0 | H7: 0 | I7: 0 | J7: 0 | K7: 0 | L7: 0 | M7: 0 | N7: 0 | O7: 0 | P7: 0 | Q7: 0 | R7: 0 | S7: 0 | T7: =S7+S7*0.15 -> 0 | U7: =T7+T7*0.15 -> 0 | V7: =U7+U7*0.15 -> 0 | W7: =V7+V7*0.15 -> 0 | X7: 0 | Y7: 0 | Z7: =Y7+Y7*0.1 -> 0 | AA7: =Z7+Z7*0.1 -> 0 | AB7: =AA7+AA7*0.1 -> 0 | AC7: =AB7+AB7*0.1 -> 0 | AD7: =AC7+AC7*0.1 -> 0 | AE7: =AD7+AD7*0.1 -> 0 | AF7: =AE7+AE7*0.1 -> 0 | AG7: =AF7+AF7*0.1 -> 0 | AH7: =AG7+AG7*0.1 -> 0 | AI7: =AG7+AG7*0.1 -> 0 | AJ7: =AH7+AH7*0.1 -> 0 | AK7: =AJ7+AJ7*0.1 -> 0 | AL7: =AK7+AK7*0.1 -> 0 | AM7: =AL7+AL7*0.1 -> 0 | AN7: =AM7+AM7*0.1 -> 0 | AO7: =AN7+AN7*0.1 -> 0 | AP7: =AO7+AO7*0.1 -> 0 | AQ7: =AP7+AP7*0.1 -> 0 | AR7: =AQ7+AQ7*0.1 -> 0 | ... AT7: =AS7+AS7*0.1 -> 0 | AU7: 0 | AV7: 0 | AW7: 0 | AX7: 0 | AY7: 0 | AZ7: 0 | BA7: 0 | BB7: 0 | BC7: 0 | BD7: 0 | BE7: 0 | BF7: 60000 | BG7: 0 | BH7: 0 | BI7: 0 | BJ7: 0 | BL7: 0 | BM7: 0 | BN7: 0 | BO7: 0 | BP7: 0 | BQ7: 0 | BR7: 0 | BS7: 0 | BT7: 0 | BU7: 0 | BV7: 0 | BW7: 0 | BX7: =sum(BL7:BW7) -> 0 | BY7: 0 | BZ7: 0 | CA7: 0 | CB7: 0 | CC7: 0 | CD7: 0 | CE7: 5000000 | CF7: 5000000 | CG7: 5000000 | CH7: 5000000 | CI7: 0 | CJ7: 0 | CK7: =sum(BY7:CJ7) -> 20000000 | CL7: 0 | CM7: 0 | CN7: 0 | CO7: 0 | CP7: 0 | CQ7: 0 | CR7: 0 | CS7: 0 | CT7: 0 | CU7: 0 | CV7: 0 | CW7: 0 | CX7: =sum(CL7:CW7) -> 0 | CY7: 0 | CZ7: 0
B8: Non-taxed Income | O8: =1000 -> 1000 | P8: =2723 -> 2723 | Q8: 419 | R8: =200 -> 200 | S8: =900+2500 -> 3400 | T8: 0 | U8: 0 | V8: 300 | W8: 0 | X8: 0 | Y8: 5600 | Z8: 0 | AA8: 0 | AB8: 0 | AC8: 700 | AD8: 0 | AE8: 11000 | AF8: 1300 | AG8: =sum(1200,1200) -> 2400 | AH8: =sum(7000,10000) -> 17000 | AI8: 0 | AJ8: 0 | AK8: =2000+7700 -> 9700 | AL8: 0 | AM8: 0 | AN8: 10000 | AO8: 1000 | AP8: 21000 | AQ8: 0 | AR8: 0 | AS8: 0 | AT8: =sum(4751.11) -> 4751.11 | AU8: =36000*0.45 -> 16200 | AV8: 0 | AW8: 0 | AX8: =SUM(1500,1844) -> 3344 | AY8: =sum(1000,1800) -> 2800 | AZ8: 16000 | BA8: 20000 | BB8: 0 | BC8: 2500 | BD8: 0 | BE8: 0 | BF8: =sum(-2000,-3000,-1200) -> -6200 | BG8: =sum(5000,2000) -> 7000 | BH8: =sum(10000,1000) -> 11000 | BI8: 0 | BJ8: 0 | BL8: 30000 | BM8: 10000 | BN8: =sum(25000) -> 25000 | BO8: =sum(24000) -> 24000 | BP8: 2000 | BQ8: =sum(20000) -> 20000 | BR8: =sum(50000) -> 50000 | BS8: =SUM(2800,6000) -> 8800 | BT8: 10000 | BU8: 0 | BV8: 0 | BW8: =sum(10000) -> 10000 | BX8: =sum(BL8:BW8) -> 189800 | BY8: =sum(10000) -> 10000 | BZ8: =sum(10000) -> 10000 | CA8: =sum(85000) -> 85000 | CB8: =sum(7500,11000,75000) -> 93500 | CC8: 0 | CD8: 250000 | CE8: 0 | CF8: 0 | CG8: 0 | CH8: 0 | CI8: 0 | CJ8: 0 | CK8: =sum(BY8:CJ8) -> 448500 | CL8: =sum(10000) -> 10000 | CM8: =sum(10000) -> 10000 | CN8: =sum(7500,11000,10000) -> 28500 | CO8: 200000 | CP8: 0 | CQ8: 0 | CR8: 0 | CS8: 0 | CT8: 0 | CU8: 0 | CV8: 0 | CW8: 0 | CX8: =sum(CL8:CW8) -> 248500 | CY8: 0 | CZ8: 0
A10: Total Income | C10: =sum(C4:C7) -> 10000 | D10: =sum(D4:D7) -> 13000 | E10: =sum(E4:E7) -> 10000 | F10: =sum(F4:F7) -> 10000 | G10: =sum(G4:G7) -> 10000 | H10: =sum(H4:H7) -> 10000 | I10: =sum(I4:I7) -> 15000 | J10: =sum(J4:J7) -> 15000 | ... O10: =sum(O4:O7) -> 10000 | P10: =sum(P4:P8) -> 17723 | Q10: =sum(Q4:Q8) -> 10669 | R10: =sum(R4:R8) -> 10450 | S10: =sum(S4:S8) -> 13650 | T10: =sum(T4:T8) -> 10250 | U10: =sum(U4:U8) -> 10250 | V10: =sum(V4:V8) -> 10550 | W10: =sum(W4:W8) -> 10250 | ... BJ10: =sum(BJ4:BJ8) -> 18333.333 | BL10: =sum(BL4:BL8) -> 48333.333 | BM10: =sum(BM4:BM8) -> 28333.333 | BN10: =sum(BN4:BN8) -> 43333.333 | BO10: =sum(BO4:BO8) -> 42333.333 | BP10: =sum(BP4:BP8) -> 20333.333 | BQ10: =sum(BQ4:BQ8) -> 38333.333 | BR10: =sum(BR4:BR8) -> 68333.333 | BS10: =sum(BS4:BS8) -> 27133.333 | ... BW10: =sum(BW4:BW8) -> 28333.333 | BX10: =sum(BL10:BW10) -> 409800 | BY10: =sum(BY4:BY8) -> 28333.333 | BZ10: =sum(BZ4:BZ8) -> 28333.333 | CA10: =sum(CA4:CA8) -> 103333.33 | CB10: =sum(CB4:CB8) -> 111833.33 | CC10: =sum(CC4:CC8) -> 30000 | CD10: =sum(CD4:CD8) -> 280000 | CE10: =sum(CE4:CE8) -> 5030000 | CF10: =sum(CF4:CF8) -> 5030000 | ... CJ10: =sum(CJ4:CJ8) -> 30000 | CK10: =sum(BY10:CJ10) -> 20761833 | CL10: =sum(CL4:CL8) -> 28333.333 | CM10: =sum(CM4:CM8) -> 28333.333 | CN10: =sum(CN4:CN8) -> 46833.333 | CO10: =sum(CO4:CO8) -> 230000 | CP10: =sum(CP4:CP8) -> 30000 | CQ10: =sum(CQ4:CQ8) -> 30000 | CR10: =sum(CR4:CR8) -> 30000 | CS10: =sum(CS4:CS8) -> 30000 | ... CW10: =sum(CW4:CW8) -> 30000 | CX10: =sum(CL10:CW10) -> 573500 | CY10: =sum(CY4:CY8) -> 33333.333 | CZ10: =sum(CZ4:CZ8) -> 33333.333
A11: Tax + Withholding | C11: =C10*0.38 -> 3800 | D11: =D10*0.34 -> 4420 | E11: =E10*0.34 -> 3400 | F11: =F10*0.34 -> 3400 | G11: =G10*0.34 -> 3400 | H11: =H10*0.34 -> 3400 | I11: =I10*0.34 -> 5100 | J11: =J10*0.34 -> 5100 | K11: =K10*0.34 -> 3400 | L11: =L10*0.34 -> 3400 | M11: =sum(M4:M7)*0.34 -> 3672 | N11: =sum(N4:N7)*0.34 -> 3570 | O11: =sum(O4:O7)*0.34+O5*0.41 -> 3400 | P11: =P4*0.34+P5*0.41+P7*0.34 -> 5450 | Q11: =sum(Q4:Q7)*0.34+Q5*0.41 -> 3485 | R11: =sum(R4:R7)*0.34+R5*0.41 -> 3485 | S11: =sum(S4:S7)*0.34+S5*0.41 -> 3485 | T11: =sum(T4:T7)*0.34+T5*0.41 -> 3485 | U11: =sum(U4:U7)*0.34+U5*0.41 -> 3485 | V11: =sum(V4:V7)*0.34+V5*0.41 -> 3485 | W11: =sum(W4:W7)*0.34+W5*0.41 -> 3485 | X11: =sum(X4:X7)*0.34+X5*0.41 -> 3485 | ... BE11: =sum(BE4:BE7)*0.34+BE5*0.41 -> 5666.6667 | BF11: =sum(BF4:BF7)*0.34+BF5*0.52 -> 26633.333 | BG11: =sum(BG4:BG7)*0.34+BG5*0.41 -> 6233.3333 | BH11: =sum(BH4:BH7)*0.34+BH5*0.41 -> 6233.3333 | BI11: =sum(BI4:BI7)*0.34+BI5*0.41 -> 6233.3333 | BJ11: =sum(BJ4:BJ7)*0.34+BJ5*0.41 -> 6233.3333 | BL11: =sum(BL4:BL7)*0.34+BL5*0.41 -> 6233.3333 | BM11: =sum(BM4:BM7)*0.34+BM5*0.41 -> 6233.3333 | BN11: =sum(BN4:BN7)*0.34+BN5*0.41 -> 6233.3333 | BO11: =sum(BO4:BO7)*0.34+BO5*0.41 -> 6233.3333 | BP11: =sum(BP4:BP7)*0.34+BP5*0.41 -> 6233.3333 | BQ11: =sum(BQ4:BQ7)*0.34+BQ5*0.41 -> 6233.3333 | BR11: =sum(BR4:BR7)*0.34+BR5*0.41 -> 6233.3333 | BS11: =sum(BS4:BS7)*0.34+BS5*0.41 -> 6233.3333 | ... BW11: =sum(BW4:BW7)*0.34+BW5*0.41 -> 6233.3333 | BX11: =sum(BL11:BW11) -> 74800 | BY11: =sum(BY4:BY7)*0.34+BY5*0.41 -> 6233.3333 | BZ11: =sum(BZ4:BZ7)*0.34+BZ5*0.41 -> 6233.3333 | CA11: =sum(CA4:CA7)*0.34+CA5*0.41 -> 6233.3333 | CB11: =sum(CB4:CB7)*0.34+CB5*0.41 -> 6233.3333 | CC11: =sum(CC4:CC7)*0.34+CC5*0.41 -> 10200 | CD11: =sum(CD4:CD7)*0.34+CD5*0.41 -> 10200 | CE11: =sum(CE4:CE7)*0.34+CE5*0.41 -> 1710200 | CF11: =sum(CF4:CF7)*0.34+CF5*0.41 -> 1710200 | ... CJ11: =sum(CJ4:CJ7)*0.34+CJ5*0.41 -> 10200 | CK11: =sum(BY11:CJ11) -> 6906533.3 | CL11: =sum(CL4:CL7)*0.34+CL5*0.41 -> 6233.3333 | CM11: =sum(CM4:CM7)*0.34+CM5*0.41 -> 6233.3333 | CN11: =sum(CN4:CN7)*0.34+CN5*0.41 -> 6233.3333 | CO11: =sum(CO4:CO7)*0.34+CO5*0.41 -> 10200 | CP11: =sum(CP4:CP7)*0.34+CP5*0.41 -> 10200 | CQ11: =sum(CQ4:CQ7)*0.34+CQ5*0.41 -> 10200 | CR11: =sum(CR4:CR7)*0.34+CR5*0.41 -> 10200 | CS11: =sum(CS4:CS7)*0.34+CS5*0.41 -> 10200 | ... CW11: =sum(CW4:CW7)*0.34+CW5*0.41 -> 10200 | CX11: =sum(CL11:CW11) -> 110500 | CY11: =sum(CY4:CY7)*0.34+CY5*0.41 -> 11333.333 | CZ11: =sum(CZ4:CZ7)*0.34+CZ5*0.41 -> 11333.333
A12: 401k Contribution | O12: =O4*0.04 -> 400 | P12: =P4*0.04 -> 400 | Q12: =Q4*0.03 -> 307.5 | R12: =R4*0.03 -> 307.5 | S12: =S4*0.03 -> 307.5 | T12: =T4*0.03 -> 307.5 | U12: =U4*0.03 -> 307.5 | V12: =V4*0.03 -> 307.5 | W12: =W4*0.03 -> 307.5 | X12: =X4*0.03 -> 307.5 | Y12: =Y4*0.03 -> 307.5 | Z12: =Z4*0 -> 0 | AA12: =AA4*0 -> 0 | AB12: 0 | AC12: =AC4*0.025 -> 333.33333 | AD12: =AD4*0.004 -> 53.333333 | AE12: =AE4*0.004 -> 53.333333 | AF12: =AF4*0 -> 0 | AG12: =AG4*0 -> 0 | AH12: =AH4*0 -> 0 | AI12: =AI4*0.025 -> 333.33333 | AJ12: =AJ4*0.025 -> 333.33333 | AK12: =AK4*0 -> 0 | AL12: =AL4*0 -> 0 | AM12: =AM4*0 -> 0 | AN12: =AN4*0 -> 0 | AO12: =AO4*0 -> 0 | AP12: =AP4*0 -> 0 | AQ12: =AQ4*0 -> 0 | AR12: =AR4*0 -> 0 | ... BJ12: =BJ4*0 -> 0 | BL12: =BL4*0 -> 0 | BM12: =BM4*0 -> 0 | BN12: =BN4*0 -> 0 | BO12: =BO4*0 -> 0 | BP12: =BP4*0 -> 0 | BQ12: =BQ4*0 -> 0 | BR12: =BR4*0 -> 0 | BS12: =BS4*0 -> 0 | ... BW12: =BW4*0 -> 0 | BX12: =sum(BL12:BW12) -> 0 | BY12: =BY4*0 -> 0 | BZ12: =BZ4*0 -> 0 | CA12: =CA4*0 -> 0 | CB12: =CB4*0 -> 0 | CC12: =CC4*0 -> 0 | CD12: =CD4*0 -> 0 | CE12: =CE4*0 -> 0 | CF12: =CF4*0 -> 0 | ... CJ12: =CJ4*0 -> 0 | CK12: =sum(BY12:CJ12) -> 0 | CL12: =CL4*0 -> 0 | CM12: =CM4*0 -> 0 | CN12: =CN4*0 -> 0 | CO12: =CO4*0 -> 0 | CP12: =CP4*0 -> 0 | CQ12: =CQ4*0 -> 0 | CR12: =CR4*0 -> 0 | CS12: =CS4*0 -> 0 | ... CW12: =CW4*0 -> 0 | CX12: =sum(CL12:CW12) -> 0 | CY12: =CY4*0 -> 0 | CZ12: =CZ4*0 -> 0
A13: Net Take Home | C13: =C10-C11+C5 -> 6200 | D13: =D10-D11+D5 -> 11580 | E13: =E10-E11+E5 -> 6600 | F13: =F10-F11+F5 -> 6600 | G13: =G10-G11+G5 -> 6600 | H13: =H10-H11+H5 -> 6600 | I13: =I10-I11+I5 -> 14900 | J13: =J10-J11+J5 -> 14900 | ... L13: =L10-L11+L5 -> 6600 | M13: =M10-M11 -> 7128 | N13: =N10-N11 -> 6930 | O13: =O4+O7+O5-O11-O12+O8 -> 7200 | P13: =P10-P11-P12 -> 11873 | Q13: =Q10-Q11-Q12 -> 6876.5 | R13: =R10-R11-R12 -> 6657.5 | S13: =S10-S11-S12 -> 9857.5 | T13: =T10-T11-T12 -> 6457.5 | U13: =U10-U11-U12 -> 6457.5 | V13: =V10-V11-V12 -> 6757.5 | W13: =W10-W11-W12 -> 6457.5 | ... BJ13: =BJ10-BJ11-BJ12 -> 12100 | BL13: =BL10-BL11-BL12 -> 42100 | BM13: =BM10-BM11-BM12 -> 22100 | BN13: =BN10-BN11-BN12 -> 37100 | BO13: =BO10-BO11-BO12 -> 36100 | BP13: =BP10-BP11-BP12 -> 14100 | BQ13: =BQ10-BQ11-BQ12 -> 32100 | BR13: =BR10-BR11-BR12 -> 62100 | BS13: =BS10-BS11-BS12 -> 20900 | ... BW13: =BW10-BW11-BW12 -> 22100 | BX13: =sum(BL13:BW13) -> 335000 | BY13: =BY10-BY11-BY12 -> 22100 | BZ13: =BZ10-BZ11-BZ12 -> 22100 | CA13: =CA10-CA11-CA12 -> 97100 | CB13: =CB10-CB11-CB12 -> 105600 | CC13: =CC10-CC11-CC12 -> 19800 | CD13: =CD10-CD11-CD12 -> 269800 | CE13: =CE10-CE11-CE12 -> 3319800 | CF13: =CF10-CF11-CF12 -> 3319800 | ... CJ13: =CJ10-CJ11-CJ12 -> 19800 | CK13: =sum(BY13:CJ13) -> 13855300 | CL13: =CL10-CL11-CL12 -> 22100 | CM13: =CM10-CM11-CM12 -> 22100 | CN13: =CN10-CN11-CN12 -> 40600 | CO13: =CO10-CO11-CO12 -> 219800 | CP13: =CP10-CP11-CP12 -> 19800 | CQ13: =CQ10-CQ11-CQ12 -> 19800 | CR13: =CR10-CR11-CR12 -> 19800 | CS13: =CS10-CS11-CS12 -> 19800 | ... CW13: =CW10-CW11-CW12 -> 19800 | CX13: =sum(CL13:CW13) -> 463000 | CY13: =CY10-CY11-CY12 -> 22000 | CZ13: =CZ10-CZ11-CZ12 -> 22000
A15: Expenses (60%)
A16: Fixed Costs (40%)
A17: Home | B17: Rent | C17: 1450 | D17: 1450 | E17: 1450 | F17: 1450 | G17: 1450 | H17: =1450+350 -> 1800 | I17: =1853+569 -> 2422 | J17: 0 | K17: 1000 | L17: =3383-1500 -> 1883 | M17: =1954 -> 1954 | N17: 1900 | O17: 1900 | P17: 1900 | Q17: 1900 | R17: 1921 | S17: 1921 | T17: =1921 -> 1921 | U17: 120 | V17: =120+700 -> 820 | W17: =sum(120+700) -> 820 | X17: =sum(336,1740) -> 2076 | Y17: =sum(1740) -> 1740 | Z17: 1571.7 | AA17: =sum(1740) -> 1740 | AB17: =sum(1740) -> 1740 | AC17: =sum(1740) -> 1740 | AD17: =sum(1740) -> 1740 | AE17: =sum(1740) -> 1740 | AF17: =sum(1740) -> 1740 | AG17: =sum(1740) -> 1740 | AH17: =sum(4000,1700) -> 5700 | AI17: =sum(2000) -> 2000 | AJ17: =sum(2700) -> 2700 | AK17: =sum(2700) -> 2700 | AL17: =sum(2700) -> 2700 | AM17: =sum(2700) -> 2700 | AN17: =sum(2700) -> 2700 | AO17: =sum(2700) -> 2700 | AP17: =sum(2700) -> 2700 | AQ17: =sum(2700) -> 2700 | ... AT17: =sum(2700) -> 2700 | AU17: =sum(2800) -> 2800 | AV17: =sum(2800) -> 2800 | AW17: =sum(2800) -> 2800 | AX17: =sum(2800) -> 2800 | AY17: =sum(2800) -> 2800 | AZ17: =sum(2800) -> 2800 | BA17: =-sum(2800) -> -2800 | BB17: =-sum(2800) -> -2800 | BC17: =-sum(2800) -> -2800 | BD17: =-sum(2800) -> -2800 | BE17: =-sum(2800) -> -2800 | BF17: =-sum(2800) -> -2800 | BG17: =-sum(2800) -> -2800 | BH17: =-sum(2800) -> -2800 | ... BJ17: =-sum(2800) -> -2800 | BL17: 2800 | BM17: 2800 | BN17: 2800 | BO17: 2800 | BP17: 2800 | BQ17: 2800 | BR17: =sum(2900) -> 2900 | BS17: =sum(2900,4620*2) -> 12140 | BT17: 4620 | BU17: 4620 | BV17: 4620 | BW17: 4620 | BX17: =sum(BL17:BW17) -> 50320 | BY17: 4620 | BZ17: 4620 | CA17: 4620 | CB17: 4620 | CC17: 4620 | CD17: 4620 | CE17: 4620 | CF17: 4620 | CG17: 4620 | CH17: 4620 | CI17: 4620 | CJ17: 4620 | CK17: =sum(BY17:CJ17) -> 55440 | CL17: 4620 | CM17: 4620 | CN17: 4620 | CO17: 4620 | CP17: 4620 | CQ17: 4620 | CR17: 4620 | CS17: 4620 | CT17: 4620 | CU17: 4620 | CV17: 4620 | CW17: 4620 | CX17: =sum(CL17:CW17) -> 55440 | CY17: 4500 | CZ17: 4500
B18: Utilities | I18: 100 | J18: 35 | K18: 90 | L18: =90 -> 90 | M18: 20 | N18: 90 | O18: 90 | P18: 90 | Q18: 90 | R18: 90 | S18: 90 | T18: 90 | U18: 0 | V18: 0 | W18: 0 | X18: 0 | Y18: 90 | Z18: 90 | AA18: 90 | AB18: 90 | AC18: 90 | AD18: 90 | AE18: 90 | AF18: 90 | AG18: 90 | AH18: 90 | AI18: 90 | AJ18: 90 | AK18: 90 | AL18: 90 | AM18: 90 | AN18: 90 | AO18: 90 | AP18: 90 | AQ18: 90 | AR18: 90 | AS18: 90 | AT18: 90 | AU18: 90 | AV18: 90 | AW18: 90 | AX18: 90 | AY18: 90 | AZ18: 90 | BA18: -90 | BB18: -90 | BC18: -90 | BD18: -90 | BE18: -90 | BF18: -90 | BG18: -90 | BH18: -90 | BI18: -90 | BJ18: -90 | BL18: 90 | BM18: 90 | BN18: 90 | BO18: 90 | BP18: 90 | BQ18: 90 | BR18: 90 | BS18: 90 | BT18: 90 | BU18: 120 | BV18: 120 | BW18: 120 | BX18: =sum(BL18:BW18) -> 1170 | BY18: 120 | BZ18: 120 | CA18: 120 | CB18: 120 | CC18: 120 | CD18: 120 | CE18: 120 | CF18: 120 | CG18: 120 | CH18: 120 | CI18: 120 | CJ18: 120 | CK18: =sum(BY18:CJ18) -> 1440 | CL18: 120 | CM18: 120 | CN18: 120 | CO18: 120 | CP18: 120 | CQ18: 120 | CR18: 120 | CS18: 120 | CT18: 120 | CU18: 120 | CV18: 120 | CW18: 120 | CX18: =sum(CL18:CW18) -> 1440 | CY18: 90 | CZ18: 90
B19: Wifi | C19: =62.95/2 -> 31.475 | D19: =62.95/2 -> 31.475 | E19: =62.95/2 -> 31.475 | F19: =62.95/2 -> 31.475 | G19: =62.95/2 -> 31.475 | H19: =62.95/2 -> 31.475 | I19: =62.95/2 -> 31.475 | J19: =62.95/2 -> 31.475 | ... T19: =62.95/2 -> 31.475 | U19: 0 | V19: 0 | W19: 0 | X19: 0 | Y19: =62.95/2 -> 31.475 | Z19: =91/2 -> 45.5 | AA19: =62.95/2 -> 31.475 | AB19: =62.95/2 -> 31.475 | AC19: =62.95/2 -> 31.475 | AD19: =62.95/2 -> 31.475 | AE19: =62.95/2 -> 31.475 | AF19: =62.95/2 -> 31.475 | AG19: =62.95/2 -> 31.475 | AH19: =0 -> 0 | AI19: =100/2 -> 50 | AJ19: =100/2 -> 50 | AK19: =100/2 -> 50 | AL19: =100/2 -> 50 | AM19: =100/2 -> 50 | AN19: =100/2 -> 50 | AO19: =100/2 -> 50 | AP19: =100/2 -> 50 | ... AZ19: =100/2 -> 50 | BA19: =-100/2 -> -50 | BB19: =-100/2 -> -50 | BC19: =-100/2 -> -50 | BD19: =-100/2 -> -50 | BE19: =-100/2 -> -50 | BF19: =-100/2 -> -50 | BG19: =-100/2 -> -50 | BH19: =-100/2 -> -50 | ... BJ19: =-100/2 -> -50 | BL19: 60 | BM19: 60 | BN19: 60 | BO19: 60 | BP19: 60 | BQ19: 60 | BR19: 60 | BS19: 60 | BT19: 60 | BU19: 120 | BV19: 120 | BW19: 120 | BX19: =sum(BL19:BW19) -> 900 | BY19: 120 | BZ19: 120 | CA19: 120 | CB19: 120 | CC19: 120 | CD19: 120 | CE19: 120 | CF19: 120 | CG19: 120 | CH19: 120 | CI19: 120 | CJ19: 120 | CK19: =sum(BY19:CJ19) -> 1440 | CL19: 120 | CM19: 120 | CN19: 120 | CO19: 120 | CP19: 120 | CQ19: 120 | CR19: 120 | CS19: 120 | CT19: 120 | CU19: 120 | CV19: 120 | CW19: 120 | CX19: =sum(CL19:CW19) -> 1440 | CY19: 60 | CZ19: 60
B20: Groceries | I20: 400 | J20: =75*4 -> 300 | K20: =50*4 -> 200 | L20: =55*4 -> 220 | M20: =55*4 -> 220 | N20: =55*4 -> 220 | O20: =55*4 -> 220 | P20: =60*4 -> 240 | Q20: =200+150+250 -> 600 | R20: =195+200+150 -> 545 | S20: =100*4 -> 400 | T20: =60*4 -> 240 | U20: =60*4 -> 240 | V20: =60*4 -> 240 | W20: =60*4 -> 240 | X20: =60*4 -> 240 | Y20: =60*4 -> 240 | Z20: =60*4 -> 240 | AA20: =60*4 -> 240 | ... AJ20: =60*4 -> 240 | AK20: =100*4 -> 400 | AL20: =100*4 -> 400 | AM20: =100*4 -> 400 | AN20: =100*4 -> 400 | AO20: =100*4 -> 400 | AP20: =100*4 -> 400 | AQ20: =100*4 -> 400 | AR20: =100*4 -> 400 | ... AZ20: =100*4 -> 400 | BA20: =-100*4 -> -400 | BB20: =-100*4 -> -400 | BC20: =-100*4 -> -400 | BD20: =-100*4 -> -400 | BE20: =-100*4 -> -400 | BF20: =-100*4 -> -400 | BG20: =-100*4 -> -400 | BH20: =-100*4 -> -400 | ... BJ20: =-100*4 -> -400 | BL20: 500 | BM20: 500 | BN20: 500 | BO20: 500 | BP20: 500 | BQ20: 500 | BR20: 500 | BS20: 500 | BT20: 500 | BU20: 500 | BV20: 500 | BW20: 500 | BX20: =sum(BL20:BW20) -> 6000 | BY20: 500 | BZ20: 500 | CA20: 500 | CB20: 500 | CC20: 500 | CD20: 500 | CE20: 500 | CF20: 500 | CG20: 500 | CH20: 500 | CI20: 500 | CJ20: 500 | CK20: =sum(BY20:CJ20) -> 6000 | CL20: 500 | CM20: 500 | CN20: 500 | CO20: 500 | CP20: 500 | CQ20: 500 | CR20: 500 | CS20: 500 | CT20: 500 | CU20: 500 | CV20: 500 | CW20: 500 | CX20: =sum(CL20:CW20) -> 6000 | CY20: 500 | CZ20: 500
A21: Phone | B21: Phone Bill | E21: 100 | F21: 128.79 | G21: 120 | H21: =120+500 -> 620 | I21: 120.64 | J21: 120.64 | K21: 120.64 | L21: 150 | M21: 120.64 | N21: 120.64 | O21: 120 | P21: 120 | Q21: 120 | R21: 120 | S21: 120 | T21: 120 | U21: 120 | V21: 120 | W21: 120 | X21: 120 | Y21: 150 | Z21: 185.09 | AA21: 185.09 | AB21: 185.09 | AC21: 185.09 | AD21: 185.09 | AE21: 185.09 | AF21: 185.09 | AG21: 185.09 | AH21: 185.09 | AI21: 185.09 | AJ21: 185.09 | AK21: 0 | AL21: 0 | AM21: 0 | AN21: 0 | AO21: 0 | AP21: 0 | AQ21: 0 | AR21: 0 | AS21: 0 | AT21: 0 | AU21: 0 | AV21: 0 | AW21: 150 | AX21: 150 | AY21: 150 | AZ21: 150 | BA21: -150 | BB21: -150 | BC21: -150 | BD21: -150 | BE21: -150 | BF21: -150 | BG21: -150 | BH21: -150 | BI21: -150 | BJ21: -150 | BL21: 150 | BM21: 150 | BN21: 150 | BO21: 150 | BP21: 150 | BQ21: 150 | BR21: 150 | BS21: 150 | BT21: 150 | BU21: 300 | BV21: 300 | BW21: 300 | BX21: =sum(BL21:BW21) -> 2250 | BY21: 150 | BZ21: 150 | CA21: 150 | CB21: 150 | CC21: 150 | CD21: 150 | CE21: 150 | CF21: 150 | CG21: 150 | CH21: 150 | CI21: 150 | CJ21: 150 | CK21: =sum(BY21:CJ21) -> 1800 | CL21: 150 | CM21: 150 | CN21: 150 | CO21: 150 | CP21: 150 | CQ21: 150 | CR21: 150 | CS21: 150 | CT21: 150 | CU21: 150 | CV21: 150 | CW21: 150 | CX21: =sum(CL21:CW21) -> 1800 | CY21: 0 | CZ21: 0
A22: Car | B22: Car | N22: 0 | O22: 0 | P22: 0 | Q22: 0 | R22: 0 | S22: 0 | T22: 200 | U22: 0 | V22: =sum(116,60,300,300) -> 776 | W22: =sum(343,60,75) -> 478 | X22: =sum(343,180,150) -> 673 | Y22: =sum(343,180,100) -> 623 | Z22: =sum(343,180,100) -> 623 | AA22: =sum(343,180,100) -> 623 | AB22: =sum(343,180,100) -> 623 | AC22: =sum(343,180,100) -> 623 | AD22: =sum(343,180,100) -> 623 | AE22: =sum(343,180,100) -> 623 | AF22: =sum(343,180,100) -> 623 | ... AH22: =sum(343,180,100) -> 623 | AI22: 400 | AJ22: 0 | AK22: 0 | AL22: 175 | AM22: 0 | AN22: 0 | AO22: 0 | AP22: 0 | AQ22: 0 | AR22: 0 | AS22: 0 | AT22: 0 | AU22: 0 | AV22: 0 | AW22: 0 | AX22: 0 | AY22: 0 | AZ22: 0 | BA22: 0 | BB22: 0 | BC22: 0 | BD22: 0 | BE22: 0 | BF22: 0 | BG22: 0 | BH22: 0 | BI22: -150 | BJ22: -300 | BL22: 0 | BM22: 0 | BN22: 0 | BO22: 0 | BP22: 0 | BQ22: 0 | BR22: 0 | BS22: 0 | BT22: 0 | BU22: 0 | BV22: 0 | BW22: 0 | BX22: =sum(BL22:BW22) -> 0 | BY22: 0 | BZ22: 0 | CA22: 0 | CB22: 0 | CC22: 0 | CD22: 0 | CE22: 0 | CF22: 0 | CG22: 0 | CH22: 0 | CI22: 0 | CJ22: 0 | CK22: =sum(BY22:CJ22) -> 0 | CL22: 0 | CM22: 0 | CN22: 0 | CO22: 0 | CP22: 0 | CQ22: 0 | CR22: 0 | CS22: 0 | CT22: 0 | CU22: 0 | CV22: 0 | CW22: 0 | CX22: =sum(CL22:CW22) -> 0 | CY22: 0 | CZ22: 0
A23: Transportation | B23: Ridesharing | J23: =170*4-20 -> 660 | K23: =22*7*4 -> 616 | L23: =22*7*4 -> 616 | M23: =20*4*4 -> 320 | N23: =20*4*4 -> 320 | O23: =15*7*4 -> 420 | P23: =15*30 -> 450 | Q23: =15*5 -> 75 | R23: =10*4 -> 40 | S23: =10*4 -> 40 | T23: =10*20 -> 200 | U23: =10*10 -> 100 | V23: 0 | W23: 0 | X23: 25 | Y23: 25 | Z23: 25 | AA23: 25 | AB23: 25 | AC23: 25 | AD23: 25 | AE23: 25 | AF23: 25 | AG23: 25 | AH23: 100 | AI23: 200 | AJ23: 100 | AK23: 100 | AL23: 100 | AM23: 100 | AN23: 100 | AO23: 100 | AP23: 100 | AQ23: 100 | AR23: 100 | AS23: 100 | AT23: 100 | AU23: 100 | AV23: 100 | AW23: 100 | AX23: 100 | AY23: 100 | AZ23: 100 | BA23: -100 | BB23: -100 | BC23: -100 | BD23: -100 | BE23: -200 | BF23: -200 | BG23: -200 | BH23: -200 | BI23: -200 | BJ23: -200 | BL23: =sum(20*3*4) -> 240 | BM23: =sum(20*3*4) -> 240 | BN23: =sum(20*3*4) -> 240 | BO23: =sum(20*3*4) -> 240 | BP23: =sum(20*3*4) -> 240 | BQ23: =sum(20*3*4) -> 240 | BR23: =sum(20*3*4) -> 240 | BS23: =sum(20*3*4) -> 240 | ... BW23: =sum(20*3*4) -> 240 | BX23: =sum(BL23:BW23) -> 2880 | BY23: =sum(20*3*4) -> 240 | BZ23: =sum(20*3*4) -> 240 | CA23: =sum(20*3*4) -> 240 | CB23: =sum(20*3*4) -> 240 | CC23: =sum(20*3*4) -> 240 | CD23: =sum(20*3*4) -> 240 | CE23: =sum(20*3*4) -> 240 | CF23: =sum(20*3*4) -> 240 | ... CJ23: =sum(20*3*4) -> 240 | CK23: =sum(BY23:CJ23) -> 2880 | CL23: =sum(20*3*4) -> 240 | CM23: =sum(20*3*4) -> 240 | CN23: =sum(20*3*4) -> 240 | CO23: =sum(20*3*4) -> 240 | CP23: =sum(20*3*4) -> 240 | CQ23: =sum(20*3*4) -> 240 | CR23: =sum(20*3*4) -> 240 | CS23: =sum(20*3*4) -> 240 | ... CW23: =sum(20*3*4) -> 240 | CX23: =sum(CL23:CW23) -> 2880 | CY23: =sum(20*3*4) -> 240 | CZ23: =sum(20*3*4) -> 240
B24: Metro | C24: 200 | D24: 200 | E24: 100 | F24: 200 | G24: 200 | H24: 200 | I24: =8*4*4+20*4 -> 208 | J24: =8*7*4 -> 224 | K24: =8*4*4 -> 128 | L24: =8*7*4 -> 224 | M24: =8*4*4 -> 128 | N24: =8*5*4 -> 160 | O24: =8*7*4 -> 224 | P24: =8*5*4 -> 160 | Q24: =40 -> 40 | R24: =0 -> 0 | S24: =0 -> 0 | T24: 0 | U24: 0 | V24: 0 | W24: 0 | X24: 0 | Y24: 0 | Z24: 0 | AA24: 0 | AB24: 0 | AC24: 0 | AD24: 0 | AE24: 0 | AF24: 0 | AG24: 0 | AH24: 50 | AI24: 50 | AJ24: 50 | AK24: 50 | AL24: 50 | AM24: 25 | AN24: 25 | AO24: 25 | AP24: 50 | AQ24: 50 | AR24: 50 | AS24: 50 | AT24: 50 | AU24: 50 | AV24: 50 | AW24: 50 | AX24: 50 | AY24: 50 | AZ24: 50 | BA24: -50 | BB24: -50 | BC24: -50 | BD24: -50 | BE24: -50 | BF24: -50 | BG24: -50 | BH24: -50 | BI24: -50 | BJ24: -50 | BL24: =sum(3*8*4) -> 96 | BM24: =sum(3*8*4) -> 96 | BN24: =sum(3*8*4) -> 96 | BO24: =sum(3*8*4) -> 96 | BP24: =sum(3*8*4) -> 96 | BQ24: =sum(3*8*4) -> 96 | BR24: =sum(3*8*4) -> 96 | BS24: =sum(3*8*4) -> 96 | ... BW24: =sum(3*8*4) -> 96 | BX24: =sum(BL24:BW24) -> 1152 | BY24: =sum(3*8*4) -> 96 | BZ24: =sum(3*8*4) -> 96 | CA24: =sum(3*8*4) -> 96 | CB24: =sum(3*8*4) -> 96 | CC24: =sum(3*8*4) -> 96 | CD24: =sum(3*8*4) -> 96 | CE24: =sum(3*8*4) -> 96 | CF24: =sum(3*8*4) -> 96 | ... CJ24: =sum(3*8*4) -> 96 | CK24: =sum(BY24:CJ24) -> 1152 | CL24: =sum(3*8*4) -> 96 | CM24: =sum(3*8*4) -> 96 | CN24: =sum(3*8*4) -> 96 | CO24: =sum(3*8*4) -> 96 | CP24: =sum(3*8*4) -> 96 | CQ24: =sum(3*8*4) -> 96 | CR24: =sum(3*8*4) -> 96 | CS24: =sum(3*8*4) -> 96 | ... CW24: =sum(3*8*4) -> 96 | CX24: =sum(CL24:CW24) -> 1152 | CY24: =sum(3*8*4) -> 96 | CZ24: =sum(3*8*4) -> 96
P25: =sum(P17:P24)/P13 -> 0.25195612 | Q25: =sum(Q17:Q24)/Q13 -> 0.41539664 | R25: =sum(R17:R24)/R13 -> 0.4126887 | S25: =sum(S17:S24)/S13 -> 0.26400964 | T25: =sum(T17:T24)/T13 -> 0.43398761 | U25: =sum(U17:U24)/U13 -> 0.089818041 | V25: =sum(V17:V24)/V13 -> 0.28945616 | W25: =sum(W17:W24)/W13 -> 0.25675571 | ... AZ25: =sum(AZ17:AZ24)/AZ13 -> 0.13212341
A26: Variable Costs (20%)
A27: Guilt Free | B27: Safe to Spend - Weekdays | C27: 1150 | D27: 1000 | E27: 1000 | F27: 1120 | G27: 1000 | H27: 500 | I27: =160*4 -> 640 | J27: =125*4 -> 500 | K27: =25*7*4 -> 700 | L27: =50*7*4 -> 1400 | M27: =25*7*4 -> 700 | N27: 1500 | O27: =30*5*4 -> 600 | P27: =30*20 -> 600 | Q27: =20*10 -> 200 | R27: =10*20 -> 200 | S27: =5*20 -> 100 | T27: =20*20 -> 400 | U27: =15*20 -> 300 | V27: =15*20 -> 300 | W27: =15*20 -> 300 | X27: =15*20 -> 300 | Y27: =50*20 -> 1000 | Z27: =45*20 -> 900 | AA27: =25*20 -> 500 | AB27: =25*20 -> 500 | AC27: =45*20 -> 900 | AD27: =25*20 -> 500 | AE27: =25*20 -> 500 | AF27: =25*20 -> 500 | AG27: =25*20 -> 500 | AH27: =25*20 -> 500 | AI27: =45*20 -> 900 | AJ27: =45*20 -> 900 | AK27: =45*20 -> 900 | AL27: =75*20 -> 1500 | AM27: =75*20 -> 1500 | AN27: =75*20 -> 1500 | AO27: =75*20 -> 1500 | AP27: =150*20 -> 3000 | AQ27: =75*20 -> 1500 | AR27: =75*20 -> 1500 | AS27: =75*20 -> 1500 | AT27: =75*20 -> 1500 | AU27: =75*20 -> 1500 | AV27: =75*20 -> 1500 | AW27: =75*20 -> 1500 | AX27: =75*20 -> 1500 | ... AZ27: =75*20 -> 1500 | BA27: =-75*20 -> -1500 | BB27: =-75*20 -> -1500 | BC27: =-75*20 -> -1500 | BD27: =-75*20 -> -1500 | BE27: =-75*20 -> -1500 | BF27: =-75*20 -> -1500 | BG27: =-75*20 -> -1500 | BH27: =-75*20 -> -1500 | ... BJ27: =-75*20 -> -1500 | BL27: =125*20 -> 2500 | BM27: =125*20 -> 2500 | BN27: =125*20 -> 2500 | BO27: =125*20 -> 2500 | BP27: =125*20 -> 2500 | BQ27: =125*20 -> 2500 | BR27: =125*20 -> 2500 | BS27: =125*20 -> 2500 | BT27: =125*20 -> 2500 | BU27: =75*20 -> 1500 | BV27: =75*20 -> 1500 | BW27: =125*20 -> 2500 | BX27: =sum(BL27:BW27) -> 28000 | BY27: =125*20 -> 2500 | BZ27: =125*20 -> 2500 | CA27: =125*20 -> 2500 | CB27: =125*20 -> 2500 | CC27: =125*20 -> 2500 | CD27: =125*20 -> 2500 | CE27: =125*20 -> 2500 | CF27: =125*20 -> 2500 | ... CJ27: =125*20 -> 2500 | CK27: =sum(BY27:CJ27) -> 30000 | CL27: =125*20 -> 2500 | CM27: =125*20 -> 2500 | CN27: =125*20 -> 2500 | CO27: =125*20 -> 2500 | CP27: =125*20 -> 2500 | CQ27: =125*20 -> 2500 | CR27: =125*20 -> 2500 | CS27: =125*20 -> 2500 | ... CW27: =125*20 -> 2500 | CX27: =sum(CL27:CW27) -> 30000 | CY27: =125*20 -> 2500 | CZ27: =125*20 -> 2500
B28: Safe to Spend - Weekends | I28: =100*4 -> 400 | J28: =200*4 -> 800 | K28: =50*2*2*4 -> 800 | L28: =50*2*2*4 -> 800 | M28: =40*2*4 -> 320 | N28: =50*2*4 -> 400 | O28: =50*2*4 -> 400 | P28: =100*4 -> 400 | Q28: =45*2 -> 90 | R28: =20*8 -> 160 | S28: =30*8 -> 240 | T28: =45*8 -> 360 | U28: =20*8 -> 160 | V28: =45*8 -> 360 | W28: =40*8 -> 320 | X28: =40*8 -> 320 | Y28: =100*8 -> 800 | Z28: =100*8 -> 800 | AA28: =100*8 -> 800 | AB28: =100*8+300 -> 1100 | AC28: =100*8 -> 800 | AD28: =75*8 -> 600 | AE28: =75*8 -> 600 | AF28: =75*8 -> 600 | AG28: =75*8 -> 600 | AH28: =75*8 -> 600 | AI28: =100*10 -> 1000 | AJ28: =100*8 -> 800 | AK28: =100*8 -> 800 | AL28: =100*8 -> 800 | AM28: =100*8 -> 800 | AN28: =100*8 -> 800 | AO28: =100*8 -> 800 | AP28: =150*8 -> 1200 | AQ28: =100*8 -> 800 | AR28: =100*8 -> 800 | AS28: =100*8 -> 800 | AT28: =100*8 -> 800 | AU28: =100*8 -> 800 | AV28: =100*8 -> 800 | AW28: =100*8 -> 800 | AX28: =100*8 -> 800 | ... AZ28: =100*8 -> 800 | BA28: =-100*8 -> -800 | BB28: =-100*8 -> -800 | BC28: =-100*8 -> -800 | BD28: =-100*8 -> -800 | BE28: =-100*8 -> -800 | BF28: =-100*8 -> -800 | BG28: =-100*8 -> -800 | BH28: =-100*8 -> -800 | ... BJ28: =-100*8 -> -800 | BL28: =200*8 -> 1600 | BM28: =200*8 -> 1600 | BN28: =200*8 -> 1600 | BO28: =200*8 -> 1600 | BP28: =200*8 -> 1600 | BQ28: =200*8 -> 1600 | BR28: =200*8 -> 1600 | BS28: =200*8 -> 1600 | BT28: =200*8 -> 1600 | BU28: =100*8 -> 800 | BV28: =100*8 -> 800 | BW28: =200*8 -> 1600 | BX28: =sum(BL28:BW28) -> 17600 | BY28: =200*8 -> 1600 | BZ28: =200*8 -> 1600 | CA28: =200*8 -> 1600 | CB28: =200*8 -> 1600 | CC28: =200*8 -> 1600 | CD28: =200*8 -> 1600 | CE28: =200*8 -> 1600 | CF28: =200*8 -> 1600 | ... CJ28: =200*8 -> 1600 | CK28: =sum(BY28:CJ28) -> 19200 | CL28: =200*8 -> 1600 | CM28: =200*8 -> 1600 | CN28: =200*8 -> 1600 | CO28: =200*8 -> 1600 | CP28: =200*8 -> 1600 | CQ28: =200*8 -> 1600 | CR28: =200*8 -> 1600 | CS28: =200*8 -> 1600 | ... CW28: =200*8 -> 1600 | CX28: =sum(CL28:CW28) -> 19200 | CY28: =200*8 -> 1600 | CZ28: =200*8 -> 1600
B29: Entertainment | C29: 0 | D29: 0 | E29: 0 | F29: 0 | G29: 0 | H29: 0 | I29: 0 | J29: 0 | K29: 0 | L29: 0 | M29: 0 | N29: 200 | O29: 400 | P29: 0 | Q29: 0 | R29: 0 | S29: 0 | T29: 0 | U29: 0 | V29: 0 | W29: 0 | X29: 0 | Y29: 0 | Z29: 0 | AA29: 0 | AB29: 0 | AC29: 0 | AD29: 0 | AE29: 0 | AF29: 0 | AG29: 0 | AH29: 0 | AI29: 0 | AJ29: 0 | AK29: 0 | AL29: 0 | AM29: 0 | AN29: 0 | AO29: 0 | AP29: 0 | AQ29: 0 | AR29: 0 | AS29: 0 | AT29: 0 | AU29: 0 | AV29: 0 | AW29: 200 | AX29: 200 | AY29: 200 | AZ29: 200 | BA29: -200 | BB29: -200 | BC29: -200 | BD29: -200 | BE29: -200 | BF29: -200 | BG29: -200 | BH29: -200 | BI29: -200 | BJ29: -200 | BL29: 200 | BM29: 200 | BN29: =sum(200,4000) -> 4200 | BO29: 200 | BP29: 200 | BQ29: =sum(200,2000) -> 2200 | BR29: 200 | BS29: 200 | BT29: 200 | BU29: 200 | BV29: 200 | BW29: 200 | BX29: =sum(BL29:BW29) -> 8400 | BY29: 200 | BZ29: 200 | CA29: 200 | CB29: 200 | CC29: 200 | CD29: 200 | CE29: 200 | CF29: 200 | CG29: 200 | CH29: 200 | CI29: 200 | CJ29: 200 | CK29: =sum(BY29:CJ29) -> 2400 | CL29: 200 | CM29: 200 | CN29: 200 | CO29: 200 | CP29: 200 | CQ29: 200 | CR29: 200 | CS29: 200 | CT29: 200 | CU29: 200 | CV29: 200 | CW29: 200 | CX29: =sum(CL29:CW29) -> 2400 | CY29: 200 | CZ29: 200
B30: Subscriptions | C30: 10 | D30: 10 | E30: 10 | F30: 10 | G30: =10+5+20 -> 35 | H30: =10+5+20 -> 35 | I30: =10+20+60 -> 90 | J30: =10+20+30+15 -> 75 | K30: =10+5+20+30 -> 65 | L30: =10+5+20+60 -> 95 | M30: =10+5+20+60 -> 95 | N30: =10+5+20+60 -> 95 | O30: =10+5+20+60 -> 95 | P30: =10+5+20+60+4+4 -> 103 | Q30: =10+5+20+60+35.68 -> 130.68 | R30: =10+5+20+60 -> 95 | S30: =10+13+20+60 -> 103 | T30: =10+13+20+60 -> 103 | U30: =10+13+20+60 -> 103 | V30: =sum(10,13,20,60,4,15,20) -> 142 | W30: =sum(10,13,20,60,4,15,70) -> 192 | X30: =sum(10,13,20,60,4,15,0) -> 122 | Y30: =sum(10,13,20,60,4,15,0) -> 122 | Z30: =sum(10,13,60,4,15,0) -> 102 | AA30: =sum(10,13,60,4,15,0) -> 102 | AB30: =sum(10,13,60,4,15,0) -> 102 | AC30: =sum(10,13,60,4,15,0) -> 102 | AD30: =sum(10,13,60,4,15,0) -> 102 | AE30: =sum(10,13,60,4,15,0) -> 102 | AF30: =sum(10,13,60,4,15,0) -> 102 | AG30: =sum(10,13,60,4,15,0) -> 102 | ... AZ30: =sum(10,13,60,4,15,0) -> 102 | BA30: =-sum(10,13,60,4,15,0) -> -102 | BB30: =-sum(10,13,60,4,15,0) -> -102 | BC30: =-sum(10,13,60,4,15,0) -> -102 | BD30: =-sum(10,13,60,4,15,0) -> -102 | BE30: =-sum(10,13,60,4,15,0) -> -102 | BF30: =-sum(10,13,60,4,15,0) -> -102 | BG30: =-sum(10,13,60,4,15,0) -> -102 | BH30: =-sum(10,13,60,4,15,0) -> -102 | ... BJ30: =-sum(10,13,60,4,15,0) -> -102 | BL30: =sum(10,13,60,4,15,0) -> 102 | BM30: =sum(10,13,60,4,15,0) -> 102 | BN30: =sum(10,13,60,4,15,0) -> 102 | BO30: =sum(10,13,60,4,15,0) -> 102 | BP30: =sum(10,13,60,4,15,0) -> 102 | BQ30: =sum(10,13,60,4,15,0) -> 102 | BR30: =sum(10,13,60,4,15,0) -> 102 | BS30: =sum(10,13,60,4,15,0) -> 102 | ... BW30: =sum(10,13,60,4,15,0) -> 102 | BX30: =sum(BL30:BW30) -> 1224 | BY30: =sum(10,13,60,4,15,0) -> 102 | BZ30: =sum(10,13,60,4,15,0) -> 102 | CA30: =sum(10,13,60,4,15,0) -> 102 | CB30: =sum(10,13,60,4,15,0) -> 102 | CC30: =sum(10,13,60,4,15,0) -> 102 | CD30: =sum(10,13,60,4,15,0) -> 102 | CE30: =sum(10,13,60,4,15,0) -> 102 | CF30: =sum(10,13,60,4,15,0) -> 102 | ... CJ30: =sum(10,13,60,4,15,0) -> 102 | CK30: =sum(BY30:CJ30) -> 1224 | CL30: =sum(10,13,60,4,15,0) -> 102 | CM30: =sum(10,13,60,4,15,0) -> 102 | CN30: =sum(10,13,60,4,15,0) -> 102 | CO30: =sum(10,13,60,4,15,0) -> 102 | CP30: =sum(10,13,60,4,15,0) -> 102 | CQ30: =sum(10,13,60,4,15,0) -> 102 | CR30: =sum(10,13,60,4,15,0) -> 102 | CS30: =sum(10,13,60,4,15,0) -> 102 | ... CW30: =sum(10,13,60,4,15,0) -> 102 | CX30: =sum(CL30:CW30) -> 1224 | CY30: =sum(10,13,60,4,15,0) -> 102 | CZ30: =sum(10,13,60,4,15,0) -> 102
B31: Travel | C31: 0 | D31: 0 | E31: 500 | F31: 500 | G31: 0 | H31: 0 | I31: 0 | J31: 500 | K31: 450 | L31: 300 | M31: 200 | N31: 100 | O31: 0 | P31: =250+179 -> 429 | Q31: 0 | R31: =260*2 -> 520 | S31: 0 | T31: =sum(500/2,185,25,84,257) -> 801 | U31: =sum(270,250) -> 520 | V31: =sum(300,600,240) -> 1140 | W31: =375+74 -> 449 | X31: 0 | Y31: 0 | Z31: =sum(548.5,400,55.1,92.1,169.66,100) -> 1365.36 | AA31: ='Travel Expenses - Tulum'!C32-Z31 -> 2256.425 | AB31: 90 | AC31: 1200 | AD31: 0 | AE31: 500 | AF31: 0 | AG31: 0 | AH31: 0 | AI31: 0 | AJ31: 0 | AK31: 0 | AL31: =1500+600 -> 2100 | AM31: 0 | AN31: 0 | AO31: 0 | AP31: 0 | AQ31: 0 | AR31: 0 | AS31: 0 | AT31: 0 | AU31: 0 | AV31: 0 | AW31: 0 | AX31: 0 | AY31: 0 | AZ31: =sum(650,375,300) -> 1325 | BA31: 0 | BB31: 0 | BC31: =-1700 -> -1700 | BD31: =-sum(3000,4396) -> -7396 | BE31: 0 | BF31: 300 | BG31: 0 | BH31: 0 | BI31: 0 | BJ31: -1000 | BL31: 20000 | BM31: 0 | BN31: =sum(3000,1200) -> 4200 | BO31: 0 | BP31: 0 | BQ31: =sum(4000,600) -> 4600 | BR31: 0 | BS31: =sum(2000,6200,2500) -> 10700 | BT31: =sum(1000) -> 1000 | BU31: 0 | BV31: 0 | BW31: 2000 | BX31: =sum(BL31:BW31) -> 42500 | BY31: 5000 | BZ31: 0 | CA31: 0 | CB31: 0 | CC31: 0 | CD31: 5000 | CE31: 0 | CF31: 0 | CG31: 0 | CH31: 0 | CI31: 0 | CJ31: 0 | CK31: =sum(BY31:CJ31) -> 10000 | CL31: 5000 | CM31: 0 | CN31: 0 | CO31: 0 | CP31: 0 | CQ31: 5000 | CR31: 0 | CS31: 0 | CT31: 0 | CU31: 0 | CV31: 0 | CW31: 0 | CX31: =sum(CL31:CW31) -> 10000 | CY31: 0 | CZ31: 0
A32: Home | B32: Home Goods | I32: 600 | J32: 0 | K32: 0 | L32: 0 | M32: 0 | N32: 0 | O32: 0 | P32: =43+83 -> 126 | Q32: =90+266+80 -> 436 | R32: 0 | S32: 0 | T32: 0 | U32: 0 | V32: 0 | W32: 0 | X32: 1000 | Y32: 0 | Z32: =sum(250,100,250) -> 600 | AA32: 0 | AB32: 0 | AC32: 0 | AD32: 0 | AE32: 0 | AF32: 0 | AG32: 0 | AH32: 2000 | AI32: 0 | AJ32: 0 | AK32: 0 | AL32: 25 | AM32: 0 | AN32: 0 | AO32: 0 | AP32: 0 | AQ32: 0 | AR32: 0 | AS32: 0 | AT32: 0 | AU32: 0 | AV32: 0 | AW32: 50 | AX32: 50 | AY32: 50 | AZ32: 50 | BA32: -50 | BB32: -50 | BC32: -50 | BD32: 0 | BE32: 0 | BF32: -50 | BG32: =sum(-50,-500) -> -550 | BH32: -50 | BI32: -50 | BJ32: -50 | BL32: 500 | BM32: 0 | BN32: 1000 | BO32: 500 | BP32: 500 | BQ32: 500 | BR32: 1000 | BS32: =sum(2500,2000,1000) -> 5500 | BT32: =1200 -> 1200 | BU32: 100 | BV32: 100 | BW32: 100 | BX32: =sum(BL32:BW32) -> 11000 | BY32: 250 | BZ32: 250 | CA32: 250 | CB32: 250 | CC32: 250 | CD32: 250 | CE32: 250 | CF32: 250 | CG32: 250 | CH32: 250 | CI32: 250 | CJ32: 250 | CK32: =sum(BY32:CJ32) -> 3000 | CL32: 250 | CM32: 250 | CN32: 250 | CO32: 250 | CP32: 250 | CQ32: 250 | CR32: 250 | CS32: 250 | CT32: 250 | CU32: 250 | CV32: 250 | CW32: 250 | CX32: =sum(CL32:CW32) -> 3000 | CY32: 250 | CZ32: 250
B33: Books | I33: 10 | J33: 0 | K33: =12*2 -> 24 | L33: 0 | M33: 0 | N33: =12*1 -> 12 | O33: =12*1 -> 12 | P33: =13 -> 13 | Q33: 0 | R33: =12*1 -> 12 | S33: =12*1 -> 12 | T33: =12*1 -> 12 | U33: =12*1 -> 12 | V33: =12*1 -> 12 | W33: =12*1 -> 12 | X33: =12*1 -> 12 | Y33: =12*1 -> 12 | ... AJ33: =12*1 -> 12 | AK33: 0 | AL33: 0 | AM33: =12*1 -> 12 | AN33: =12*1 -> 12 | AO33: =12*1 -> 12 | AP33: =12*1 -> 12 | AQ33: =12*1 -> 12 | AR33: =12*1 -> 12 | AS33: 50 | AT33: =12*1 -> 12 | AU33: =12*1 -> 12 | AV33: =12*1 -> 12 | AW33: =12*1 -> 12 | AX33: =12*1 -> 12 | AY33: =12*1 -> 12 | AZ33: =12*1 -> 12 | BA33: =-20*1 -> -20 | BB33: =-20*1 -> -20 | BC33: =-20*1 -> -20 | BD33: =-20*1 -> -20 | BE33: =-20*1 -> -20 | BF33: =-20*1 -> -20 | BG33: =-20*1 -> -20 | BH33: =-20*1 -> -20 | ... BJ33: =-20*1 -> -20 | BL33: 20 | BM33: 20 | BN33: 20 | BO33: 20 | BP33: 20 | BQ33: 20 | BR33: 20 | BS33: 20 | BT33: 20 | BU33: 20 | BV33: 20 | BW33: 20 | BX33: =sum(BL33:BW33) -> 240 | BY33: 20 | BZ33: 20 | CA33: 20 | CB33: 20 | CC33: 20 | CD33: 20 | CE33: 20 | CF33: 20 | CG33: 20 | CH33: 20 | CI33: 20 | CJ33: 20 | CK33: =sum(BY33:CJ33) -> 240 | CL33: 20 | CM33: 20 | CN33: 20 | CO33: 20 | CP33: 20 | CQ33: 20 | CR33: 20 | CS33: 20 | CT33: 20 | CU33: 20 | CV33: 20 | CW33: 20 | CX33: =sum(CL33:CW33) -> 240 | CY33: 20 | CZ33: 20
B34: Clothing | I34: 100 | J34: 60 | K34: 250 | L34: 0 | M34: 50 | N34: 0 | O34: 100 | P34: 0 | Q34: 0 | R34: 0 | S34: 0 | T34: 300 | U34: 100 | V34: 100 | W34: 100 | X34: 100 | Y34: 100 | Z34: 100 | AA34: 100 | AB34: 100 | AC34: 100 | AD34: 100 | AE34: 100 | AF34: 100 | AG34: 100 | AH34: 100 | AI34: 100 | AJ34: 100 | AK34: 100 | AL34: 300 | AM34: 300 | AN34: 300 | AO34: 300 | AP34: 300 | AQ34: 300 | AR34: 300 | AS34: 300 | AT34: 300 | AU34: 300 | AV34: 300 | AW34: 300 | AX34: 300 | AY34: 300 | AZ34: 300 | BA34: -500 | BB34: -500 | BC34: -500 | BD34: -500 | BE34: -500 | BF34: -200 | BG34: -500 | BH34: -500 | BI34: -500 | BJ34: -500 | BL34: 750 | BM34: 500 | BN34: 1000 | BO34: 700 | BP34: 2000 | BQ34: 500 | BR34: 500 | BS34: 3000 | BT34: 500 | BU34: 100 | BV34: 100 | BW34: 500 | BX34: =sum(BL34:BW34) -> 10150 | BY34: 500 | BZ34: 500 | CA34: 5000 | CB34: 500 | CC34: 500 | CD34: 500 | CE34: 500 | CF34: 500 | CG34: 500 | CH34: 500 | CI34: 500 | CJ34: 500 | CK34: =sum(BY34:CJ34) -> 10500 | CL34: 500 | CM34: 500 | CN34: 500 | CO34: 500 | CP34: 500 | CQ34: 500 | CR34: 500 | CS34: 500 | CT34: 500 | CU34: 500 | CV34: 500 | CW34: 500 | CX34: =sum(CL34:CW34) -> 6000 | CY34: 500 | CZ34: 500
A35: Health | B35: Dental | C35: 0 | D35: 0 | E35: 0 | F35: 0 | G35: 0 | H35: 0 | I35: 25 | J35: 0 | K35: 0 | L35: 0 | M35: 0 | N35: 0 | O35: 0 | P35: 0 | Q35: 0 | R35: 0 | S35: 0 | T35: 0 | U35: 0 | V35: 0 | W35: 0 | X35: 0 | Y35: 0 | Z35: 0 | AA35: 0 | AB35: 0 | AC35: 0 | AD35: 0 | AE35: 0 | AF35: 0 | AG35: 0 | AH35: 0 | AI35: 0 | AJ35: 0 | AK35: 0 | AL35: 0 | AM35: 0 | AN35: 0 | AO35: 0 | AP35: 0 | AQ35: 0 | AR35: 0 | AS35: 0 | AT35: 0 | AU35: 0 | AV35: 0 | AW35: 0 | AX35: 0 | AY35: 0 | AZ35: 0 | BA35: 0 | BB35: 0 | BC35: 0 | BD35: 0 | BE35: 0 | BF35: 0 | BG35: 0 | BH35: 0 | BI35: 0 | BJ35: 0 | BL35: 0 | BM35: 0 | BN35: 1000 | BO35: 2000 | BP35: 0 | BQ35: 0 | BR35: 0 | BS35: 0 | BT35: 0 | BU35: 0 | BV35: 0 | BW35: 0 | BX35: =sum(BL35:BW35) -> 3000 | BY35: 0 | BZ35: 0 | CA35: 200 | CB35: 200 | CC35: 200 | CD35: 200 | CE35: 200 | CF35: 200 | CG35: 200 | CH35: 200 | CI35: 0 | CJ35: 0 | CK35: =sum(BY35:CJ35) -> 1600 | CL35: 0 | CM35: 0 | CN35: 1000 | CO35: 2000 | CP35: 0 | CQ35: 0 | CR35: 0 | CS35: 0 | CT35: 0 | CU35: 0 | CV35: 0 | CW35: 0 | CX35: =sum(CL35:CW35) -> 3000 | CY35: 0 | CZ35: 0
B36: Healthcare | J36: 0 | K36: 0 | L36: 0 | M36: 0 | N36: 0 | O36: 0 | P36: 0 | Q36: 0 | R36: 0 | S36: 0 | T36: 0 | U36: 0 | V36: =490 -> 490 | W36: 0 | X36: 0 | Y36: 0 | Z36: 0 | AA36: 0 | AB36: 0 | AC36: 0 | AD36: 0 | AE36: 0 | AF36: 0 | AG36: 0 | AH36: 0 | AI36: 0 | AJ36: 0 | AK36: 250 | AL36: 0 | AM36: 0 | AN36: 0 | AO36: 0 | AP36: 0 | AQ36: 0 | AR36: 0 | AS36: 0 | AT36: 0 | AU36: 0 | AV36: 0 | AW36: 0 | AX36: 0 | AY36: 0 | AZ36: 0 | BA36: 0 | BB36: 0 | BC36: 0 | BD36: 0 | BE36: 0 | BF36: 0 | BG36: 0 | BH36: 0 | BI36: 0 | BJ36: 0 | BL36: 0 | BM36: 0 | BN36: 0 | BO36: 0 | BP36: 0 | BQ36: 0 | BR36: 0 | BS36: 0 | BT36: 0 | BU36: 0 | BV36: 0 | BW36: 0 | BX36: =sum(BL36:BW36) -> 0 | BY36: 0 | BZ36: 0 | CA36: 0 | CB36: 0 | CC36: 0 | CD36: 0 | CE36: 0 | CF36: 0 | CG36: 0 | CH36: 0 | CI36: 0 | CJ36: 0 | CK36: =sum(BY36:CJ36) -> 0 | CL36: 0 | CM36: 0 | CN36: 0 | CO36: 0 | CP36: 0 | CQ36: 0 | CR36: 0 | CS36: 0 | CT36: 0 | CU36: 0 | CV36: 0 | CW36: 0 | CX36: =sum(CL36:CW36) -> 0 | CY36: 0 | CZ36: 0
B37: Self-Care | I37: 100 | J37: =60+20+350 -> 430 | K37: 50 | L37: 60 | M37: 60 | N37: 95 | O37: 100 | P37: 100 | Q37: 60 | R37: 0 | S37: 0 | T37: 100 | U37: 50 | V37: 100 | W37: 100 | X37: 100 | Y37: 100 | Z37: 100 | AA37: 100 | AB37: 100 | AC37: 100 | AD37: 100 | AE37: 100 | AF37: 100 | AG37: 100 | AH37: 100 | AI37: 100 | AJ37: 100 | AK37: 100 | AL37: 100 | AM37: 100 | AN37: 100 | AO37: 100 | AP37: 100 | AQ37: 100 | AR37: 100 | AS37: 100 | AT37: 100 | AU37: 100 | AV37: 100 | AW37: 100 | AX37: 100 | AY37: 100 | AZ37: 100 | BA37: -100 | BB37: -100 | BC37: -100 | BD37: -100 | BE37: -100 | BF37: -100 | BG37: -100 | BH37: -100 | BI37: -100 | BJ37: -100 | BL37: 200 | BM37: 200 | BN37: 500 | BO37: 500 | BP37: 500 | BQ37: 500 | BR37: 500 | BS37: 500 | BT37: 500 | BU37: =sum(300,300*2) -> 900 | BV37: =sum(300,300*4) -> 1500 | BW37: =sum(300,300*2) -> 900 | BX37: =sum(BL37:BW37) -> 7200 | BY37: =sum(300,400,400,2700) -> 3800 | BZ37: =sum(300,400,400) -> 1100 | CA37: =sum(300,400,400) -> 1100 | CB37: =sum(300,400,400) -> 1100 | CC37: =sum(300,400,400) -> 1100 | CD37: =sum(300,400,400) -> 1100 | CE37: =sum(300,400,400) -> 1100 | CF37: =sum(300,400,400) -> 1100 | CG37: =sum(300,400,400) -> 1100 | ... CJ37: =sum(300,400,400) -> 1100 | CK37: =sum(BY37:CJ37) -> 15900 | CL37: =sum(300,400,400) -> 1100 | CM37: =sum(300,400,400) -> 1100 | CN37: =sum(300,400,400) -> 1100 | CO37: =sum(300,400,400) -> 1100 | CP37: =sum(300,400,400) -> 1100 | CQ37: =sum(300,400,400) -> 1100 | CR37: =sum(300,400,400) -> 1100 | CS37: =sum(300,400,400) -> 1100 | ... CW37: =sum(300,400,400) -> 1100 | CX37: =sum(CL37:CW37) -> 13200 | CY37: 500 | CZ37: 500
B38: Gym | C38: 0 | D38: 0 | E38: 0 | F38: 0 | G38: 0 | H38: 0 | I38: 0 | J38: 0 | K38: 0 | L38: 0 | M38: 0 | N38: 0 | O38: 0 | P38: 0 | Q38: 0 | R38: 0 | S38: 0 | T38: 0 | U38: 0 | V38: 0 | W38: 0 | X38: 0 | Y38: 0 | Z38: 0 | AA38: 0 | AB38: 0 | AC38: 0 | AD38: 0 | AE38: 0 | AF38: 0 | AG38: 0 | AH38: 100 | AI38: 300 | AJ38: 100 | AK38: 175 | AL38: 175 | AM38: 175 | AN38: 175 | AO38: 175 | AP38: 175 | AQ38: 175 | AR38: 175 | AS38: 175 | AT38: 175 | AU38: 175 | AV38: 175 | AW38: 175 | AX38: 175 | AY38: 175 | AZ38: 175 | BA38: -175 | BB38: -175 | BC38: -175 | BD38: -175 | BE38: =sum(-175,-1200) -> -1375 | BF38: =sum(-175) -> -175 | BG38: =sum(-175,-185) -> -360 | BH38: =sum(-175) -> -175 | BI38: =sum(-175) -> -175 | BJ38: =sum(-175,-800/2) -> -575 | BL38: 175 | BM38: =sum(175,1600) -> 1775 | BN38: 175 | BO38: 175 | BP38: 175 | BQ38: =sum(400,600) -> 1000 | BR38: =sum(600,600) -> 1200 | BS38: =sum(600,600) -> 1200 | BT38: =sum(600,600) -> 1200 | BU38: =sum(600,600) -> 1200 | BV38: =sum(600,600) -> 1200 | BW38: =sum(600,300) -> 900 | BX38: =sum(BL38:BW38) -> 10375 | BY38: =sum(600,600) -> 1200 | BZ38: =sum(600,600) -> 1200 | CA38: =sum(600,600) -> 1200 | CB38: =sum(600,600) -> 1200 | CC38: =sum(600,600) -> 1200 | CD38: =sum(600,600) -> 1200 | CE38: =sum(600,600) -> 1200 | CF38: =sum(600,600) -> 1200 | ... CJ38: =sum(600,600) -> 1200 | CK38: =sum(BY38:CJ38) -> 14400 | CL38: =sum(600,600) -> 1200 | CM38: =sum(600,600) -> 1200 | CN38: =sum(600,600) -> 1200 | CO38: =sum(600,600) -> 1200 | CP38: =sum(600,600) -> 1200 | CQ38: =sum(600,600) -> 1200 | CR38: =sum(600,600) -> 1200 | CS38: =sum(600,600) -> 1200 | ... CW38: =sum(600,600) -> 1200 | CX38: =sum(CL38:CW38) -> 14400 | CY38: 175 | CZ38: 175
A39: Misc | B39: Dog Stuff | E39: 50 | F39: 50 | G39: 50 | H39: 50 | I39: 100 | J39: =30+40 -> 70 | K39: 0 | L39: 50 | M39: 50 | N39: 20 | O39: 0 | P39: 50 | Q39: 30 | R39: =15+35 -> 50 | S39: 10 | T39: 40 | U39: 30 | V39: =sum(30,100) -> 130 | W39: 30 | X39: 30 | Y39: 30 | Z39: 10 | AA39: 10 | AB39: 10 | AC39: 10 | AD39: 10 | AE39: 10 | AF39: 10 | AG39: 10 | AH39: 10 | AI39: 10 | AJ39: 10 | AK39: 10 | AL39: 10 | AM39: 10 | AN39: 10 | AO39: 10 | AP39: 10 | AQ39: 10 | AR39: 10 | AS39: 0 | AT39: 10 | AU39: 10 | AV39: 10 | AW39: 30 | AX39: 30 | AY39: 30 | AZ39: 30 | BA39: -30 | BB39: -30 | BC39: -30 | BD39: =sum(-30,-50) -> -80 | BE39: =sum(-30,-50) -> -80 | BF39: =sum(-30,-50) -> -80 | BG39: =sum(-30,-50) -> -80 | BH39: =sum(-30,-50) -> -80 | BI39: =sum(-30,-50) -> -80 | BJ39: =sum(-30,-50) -> -80 | BL39: 100 | BM39: 100 | BN39: 100 | BO39: 100 | BP39: 100 | BQ39: =sum(500,100) -> 600 | BR39: 100 | BS39: 100 | BT39: 100 | BU39: 100 | BV39: 100 | BW39: 100 | BX39: =sum(BL39:BW39) -> 1700 | BY39: 100 | BZ39: 100 | CA39: 100 | CB39: 100 | CC39: 100 | CD39: =sum(500,100) -> 600 | CE39: 100 | CF39: 100 | CG39: 100 | CH39: 100 | CI39: 100 | CJ39: 100 | CK39: =sum(BY39:CJ39) -> 1700 | CL39: 100 | CM39: 100 | CN39: 100 | CO39: 100 | CP39: 100 | CQ39: =sum(500,100) -> 600 | CR39: 100 | CS39: 100 | CT39: 100 | CU39: 100 | CV39: 100 | CW39: 100 | CX39: =sum(CL39:CW39) -> 1700 | CY39: 100 | CZ39: 100
B40: Contractor Services | K40: 0 | L40: 0 | M40: 0 | N40: 250 | O40: 0 | P40: 200 | Q40: 0 | R40: 0 | S40: =0 -> 0 | T40: =840+450 -> 1290 | U40: 0 | V40: 0 | W40: 0 | X40: 0 | Y40: 0 | Z40: 0 | AA40: 0 | AB40: 0 | AC40: 0 | AD40: 0 | AE40: 0 | AF40: 0 | AG40: 0 | AH40: 0 | AI40: 0 | AJ40: 0 | AK40: 0 | AL40: 0 | AM40: 0 | AN40: 0 | AO40: 0 | AP40: 0 | AQ40: 0 | AR40: 0 | AS40: 0 | AT40: 0 | AU40: 0 | AV40: 0 | AW40: 0 | AX40: 0 | AY40: 0 | AZ40: 0 | BA40: 0 | BB40: 0 | BC40: 0 | BD40: 0 | BE40: 0 | BF40: 0 | BG40: 0 | BH40: 0 | BI40: 0 | BJ40: 0 | BL40: 0 | BM40: 0 | BN40: 0 | BO40: 0 | BP40: 0 | BQ40: 0 | BR40: 0 | BS40: 0 | BT40: 0 | BU40: 0 | BV40: 0 | BW40: 0 | BX40: =sum(BL40:BW40) -> 0 | BY40: 0 | BZ40: 0 | CA40: 0 | CB40: 0 | CC40: 0 | CD40: 0 | CE40: 0 | CF40: 0 | CG40: 0 | CH40: 0 | CI40: 0 | CJ40: 0 | CK40: =sum(BY40:CJ40) -> 0 | CL40: 0 | CM40: 0 | CN40: 0 | CO40: 0 | CP40: 0 | CQ40: 0 | CR40: 0 | CS40: 0 | CT40: 0 | CU40: 0 | CV40: 0 | CW40: 0 | CX40: =sum(CL40:CW40) -> 0 | CY40: 0 | CZ40: 0
B41: Tech | X41: =272+375 -> 647 | Y41: 0 | Z41: 0 | AA41: 0 | AB41: 0 | AC41: 0 | AD41: 0 | AE41: 0 | AF41: 0 | AG41: 0 | AH41: 0 | AI41: 0 | AJ41: 0 | AK41: 0 | AL41: 0 | AM41: 0 | AN41: 0 | AO41: 0 | AP41: 0 | AQ41: 0 | AR41: 0 | AS41: 0 | AT41: 0 | AU41: 0 | AV41: 0 | AW41: 0 | AX41: 0 | AY41: 0 | AZ41: 0 | BA41: 0 | BB41: 0 | BC41: 0 | BD41: 0 | BE41: 0 | BF41: 0 | BG41: 0 | BH41: 0 | BI41: 0 | BJ41: 0 | BL41: 0 | BM41: 0 | BN41: 0 | BO41: 0 | BP41: 0 | BQ41: 0 | BR41: 0 | BS41: 0 | BT41: 0 | BU41: 0 | BV41: 0 | BW41: 0 | BX41: =sum(BL41:BW41) -> 0 | BY41: 0 | BZ41: 0 | CA41: 0 | CB41: 0 | CC41: 0 | CD41: 0 | CE41: 0 | CF41: 0 | CG41: 0 | CH41: 0 | CI41: 0 | CJ41: 0 | CK41: =sum(BY41:CJ41) -> 0 | CL41: 0 | CM41: 0 | CN41: 0 | CO41: 0 | CP41: 0 | CQ41: 0 | CR41: 0 | CS41: 0 | CT41: 0 | CU41: 0 | CV41: 0 | CW41: 0 | CX41: =sum(CL41:CW41) -> 0 | CY41: 0 | CZ41: 0
B42: Misc. | T42: 0 | U42: 0 | V42: 0 | W42: 0 | X42: =sum(700/2,50,500) -> 900 | Y42: 0 | Z42: 0 | AA42: 0 | AB42: 0 | AC42: 0 | AD42: 0 | AE42: 0 | AF42: 0 | AG42: 0 | AH42: 0 | AI42: 0 | AJ42: 0 | AK42: 0 | AL42: 1500 | AM42: 0 | AN42: 0 | AO42: 0 | AP42: 0 | AQ42: 0 | AR42: 0 | AS42: 0 | AT42: 0 | AU42: 0 | AV42: 0 | AW42: 0 | AX42: 500 | AY42: 0 | AZ42: 0 | BA42: 0 | BB42: 0 | BC42: 0 | BD42: 0 | BE42: 0 | BF42: 0 | BG42: 0 | BH42: 0 | BI42: 0 | BJ42: -3500 | BL42: 3500 | BM42: 2000 | BN42: =2000 -> 2000 | BO42: 700 | BP42: 0 | BQ42: 0 | BR42: 0 | BS42: =sum(3500,1850,1000,200) -> 6550 | BT42: 0 | BU42: 1000 | BV42: 0 | BW42: 1500 | BX42: =sum(BL42:BW42) -> 17250 | BY42: 0 | BZ42: 0 | CA42: =sum(7500,5000) -> 12500 | CB42: 2500 | CC42: 0 | CD42: =sum(30000,2500) -> 32500 | CE42: 0 | CF42: 0 | CG42: 0 | CH42: 0 | CI42: 0 | CJ42: 0 | CK42: =sum(BY42:CJ42) -> 47500 | CL42: 0 | CM42: 0 | CN42: 0 | CO42: 30000 | CP42: 0 | CQ42: 0 | CR42: 0 | CS42: 0 | CT42: 0 | CU42: 0 | CV42: 0 | CW42: 0 | CX42: =sum(CL42:CW42) -> 30000 | CY42: 0 | CZ42: 0
P43: =sum(P17:P40)/P13 -> 0.42219548 | Q43: =sum(Q27:Q40)/Q13 -> 0.13766887 | R43: =sum(R27:R40)/R13 -> 0.15576418 | S43: =sum(S27:S40)/S13 -> 0.047172204 | T43: =sum(T27:T42)/T13 -> 0.5274487 | U43: =sum(U27:U42)/U13 -> 0.19744483 | V43: =sum(V27:V42)/V13 -> 0.41050684 | W43: =sum(W27:W42)/W13 -> 0.23275261 | X43: =sum(X27:X42)/X13 -> 0.54680604 | Y43: =sum(Y27:Y42)/Y13 -> 0.17947336 | Z43: =sum(Z27:Z42)/Z13 -> 0.45333636 | AA43: =sum(AA27:AA42)/AA13 -> 0.44095739 | ... AZ43: =sum(AZ27:AZ42)/AZ13 -> 0.16675136
A44: Total Expenses | C44: =sum(C17:C39) -> 2841.475 | D44: =sum(D17:D39) -> 2691.475 | E44: =sum(E17:E39) -> 3241.475 | F44: =sum(F17:F39) -> 3490.265 | G44: =sum(G17:G39) -> 2886.475 | H44: =sum(H22:H39) -> 785 | I44: =sum(I22:I39) -> 2273 | J44: =sum(J22:J39) -> 3319 | K44: =sum(K22:K39) -> 3083 | L44: =sum(L22:L39) -> 3545 | M44: =sum(M22:M39) -> 1923 | N44: =sum(N22:N40) -> 3152 | O44: =sum(O22:O40) -> 2351 | P44: =sum(P17:P40) -> 5012.727 | Q44: =sum(Q17:Q40) -> 3803.5704 | R44: =sum(R17:R40) -> 3784.8877 | S44: =sum(S17:S40) -> 3067.739 | T44: =sum(T17:T42) -> 6208.909 | U44: =sum(U17:U42) -> 1855.0898 | V44: =sum(V17:V42) -> 4730.2895 | W44: =sum(W17:W42) -> 3161.2568 | X44: =sum(X17:X42) -> 6665.4853 | Y44: =sum(Y17:Y24,Y27:Y42) -> 5063.475 | Z44: =sum(Z17:Z24,Z27:Z42) -> 6769.65 | AA44: =sum(AA17:AA24,AA27:AA42) -> 6814.99 | AB44: =sum(AB17:AB24,AB27:AB42) -> 4948.565 | AC44: =sum(AC17:AC24,AC27:AC42) -> 6158.565 | AD44: =sum(AD17:AD24,AD27:AD42) -> 4358.565 | AE44: =sum(AE17:AE24,AE27:AE42) -> 4858.565 | AF44: =sum(AF17:AF24,AF27:AF42) -> 4358.565 | ... BJ44: =sum(BJ17:BJ24,BJ27:BJ42) -> -12467 | BL44: =sum(BL17:BL24,BL27:BL42) -> 33583 | BM44: =sum(BM17:BM24,BM27:BM42) -> 12933 | BN44: =sum(BN17:BN24,BN27:BN42) -> 22333 | BO44: =sum(BO17:BO24,BO27:BO42) -> 13033 | BP44: =sum(BP17:BP24,BP27:BP42) -> 11633 | BQ44: =sum(BQ17:BQ24,BQ27:BQ42) -> 18058 | BR44: =sum(BR17:BR24,BR27:BR42) -> 11758 | BS44: =sum(BS17:BS24,BS27:BS42) -> 45248 | ... BW44: =sum(BW17:BW24,BW27:BW42) -> 16418 | BX44: =sum(BL44:BW44) -> 223311 | BY44: =sum(BY17:BY24,BY27:BY42) -> 21118 | BZ44: =sum(BZ17:BZ24,BZ27:BZ42) -> 13418 | CA44: =sum(CA17:CA24,CA27:CA42) -> 30618 | CB44: =sum(CB17:CB24,CB27:CB42) -> 16118 | CC44: =sum(CC17:CC24,CC27:CC42) -> 13618 | CD44: =sum(CD17:CD24,CD27:CD42) -> 51618 | CE44: =sum(CE17:CE24,CE27:CE42) -> 13618 | CF44: =sum(CF17:CF24,CF27:CF42) -> 13618 | ... CJ44: =sum(CJ17:CJ24,CJ27:CJ42) -> 13418 | CK44: =sum(BY44:CJ44) -> 227816 | CL44: =sum(CL17:CL24,CL27:CL42) -> 18418 | CM44: =sum(CM17:CM24,CM27:CM42) -> 13418 | CN44: =sum(CN17:CN24,CN27:CN42) -> 14418 | CO44: =sum(CO17:CO24,CO27:CO42) -> 45418 | CP44: =sum(CP17:CP24,CP27:CP42) -> 13418 | CQ44: =sum(CQ17:CQ24,CQ27:CQ42) -> 18918 | CR44: =sum(CR17:CR24,CR27:CR42) -> 13418 | CS44: =sum(CS17:CS24,CS27:CS42) -> 13418 | ... CW44: =sum(CW17:CW24,CW27:CW42) -> 13418 | CX44: =sum(CL44:CW44) -> 204516 | CY44: =sum(CY17:CY24,CY27:CY42) -> 11433 | CZ44: =sum(CZ17:CZ24,CZ27:CZ42) -> 11433
A46: Financial Health (40%)
A47: Debt Consolidation (10%)
B48: Debt Repayment (10%) | C48: 2500 | D48: 4500 | E48: 2800 | F48: 2800 | G48: 2000 | H48: 3093 | I48: 1600 | J48: ='PAYMENT SCHEDULE'!C13+'PAYMENT SCHEDULE'!C29 -> 3200 | K48: =LIABILITIES!E26 -> 1000 | L48: =LIABILITIES!E26 -> 1000 | M48: ='PAYMENT SCHEDULE'!C33 | N48: =N13*0.25 -> 1732.5 | O48: =O13*0.35 -> 2520 | P48: 5956 | Q48: 2008 | R48: =R13*0.4 -> 2663 | S48: 5600 | T48: =T13*0.25 -> 1614.375 | U48: =U13*0.4 -> 2583 | V48: =3397 -> 3397 | W48: =W13*0.3 -> 1937.25 | X48: =X$13*0.11 -> 710.325 | Y48: =Y$13*0.1 -> 1205.75 | Z48: =Z$13*0.1 -> 880 | AA48: =AA$13*0.33 -> 2904 | AB48: =AB$13*0.2 -> 1760 | AC48: =AC$13*0.2 -> 1833.3333 | AD48: =AD$13*0.25 -> 2186.6667 | AE48: =AE$13*0.7 -> 13822.667 | AF48: =AF$13*0.25 -> 2525 | AG48: =AG$13*0.15 -> 1680 | AH48: =AH$13*0.15 -> 3870 | AI48: =AI$13*0.18 -> 1524 | AJ48: =AJ$13*0.18 -> 1524 | AK48: =AK$13*0.18 -> 3379.5 | AL48: =AL$13*0.05 -> 577.5 | AM48: =AM$13*0.1 -> 1155 | AN48: =AN$13*0.4 -> 8620 | AO48: =AO$13*0.1 -> 1255 | AP48: =17000 -> 17000 | AQ48: =AQ$13*0.1 -> 1155 | AR48: =AR$13*0.3 -> 3465 | AS48: =AS$13*0.3 -> 3465 | AT48: =AT$13*0.5 -> 8150.555 | AU48: =AU$13*0.2 -> 5550 | AV48: =AV$13*0.1 -> 1155 | AW48: =AW$13*0.1+2530 -> 3685 | AX48: =AX$13*0.1+2000 -> 3489.4 | AY48: =AY$13*0.1 -> 1435 | AZ48: 16000 | BA48: -15000 | BB48: -2400 | BC48: -5000 | BD48: -2400 | BE48: -2400 | BF48: -5000 | BG48: =-4500 -> -4500 | BH48: =sum(-2500) -> -2500 | BI48: =sum(-4500) -> -4500 | BJ48: =sum(-8000) -> -8000 | BL48: 0 | BM48: 10000 | BN48: 8000 | BO48: 20000 | BP48: 0 | BQ48: 5000 | BR48: =45000 -> 45000 | BS48: 0 | BT48: 0 | BU48: 0 | BV48: 0 | BW48: 0 | BX48: =sum(BL48:BW48) -> 88000 | BY48: 0 | BZ48: 0 | CA48: 50000 | CB48: 0 | CC48: 0 | CD48: 0 | CE48: 0 | CF48: 0 | CG48: 0 | CH48: 0 | CI48: 0 | CJ48: 0 | CK48: =sum(BY48:CJ48) -> 50000 | CL48: 50000 | CM48: 10000 | CN48: 8000 | CO48: 20000 | CP48: 0 | CQ48: 5000 | CR48: =45000 -> 45000 | CS48: 0 | CT48: 0 | CU48: 25000 | CV48: 0 | CW48: 0 | CX48: =sum(CL48:CW48) -> 163000 | CY48: 0 | CZ48: 0
A49: Savings (19%)
B50: Long-Term High-Yield Savings (10%) | I50: 0 | J50: 0 | K50: =K13*0 -> 0 | L50: =L13*0 -> 0 | M50: 0 | N50: 25 | O50: 25 | P50: 20 | Q50: 25 | R50: 0 | S50: 0 | T50: 0 | U50: 0 | V50: 0 | W50: 0 | X50: =$X$13*0.03 -> 193.725 | Y50: =$X$13*0.03 -> 193.725 | Z50: =$X$13*0.1 -> 645.75 | AA50: =$X$13*0.03 -> 193.725 | AB50: =$X$13*0.03 -> 193.725 | AC50: =$X$13*0.03 -> 193.725 | AD50: =$X$13*0 -> 0 | AE50: =$X$13*0 -> 0 | AF50: =$X$13*0 -> 0 | AG50: =$X$13*0 -> 0 | AH50: =$X$13*0 -> 0 | AI50: =$X$13*0.03 -> 193.725 | AJ50: =$X$13*0.03 -> 193.725 | AK50: =$X$13*0.032 -> 206.64 | AL50: =$X$13*0.032 -> 206.64 | AM50: =$X$13*0.032 -> 206.64 | AN50: =$X$13*0.05 -> 322.875 | AO50: =$X$13*0.05 -> 322.875 | AP50: =$X$13*0.05 -> 322.875 | AQ50: =$X$13*0.05 -> 322.875 | AR50: =$X$13*0.05 -> 322.875 | AS50: =$X$13*0 -> 0 | AT50: =$X$13*0.05 -> 322.875 | AU50: =$X$13*0.05 -> 322.875 | AV50: =$X$13*0.05 -> 322.875 | AW50: 0 | AX50: 0 | AY50: 0 | AZ50: 0 | BA50: 0 | BB50: 0 | BC50: 0 | BD50: 0 | BE50: 0 | BF50: 0 | BG50: 0 | BH50: 0 | BI50: 0 | BJ50: 0 | BL50: 0 | BM50: 0 | BN50: 0 | BO50: 500 | BP50: 500 | BQ50: 0 | BR50: 0 | BS50: 0 | BT50: 0 | BU50: 0 | BV50: 0 | BW50: 0 | BX50: =sum(BL50:BW50) -> 1000 | BY50: 0 | BZ50: 0 | CA50: 0 | CB50: 0 | CC50: 0 | CD50: 500 | CE50: 0 | CF50: 0 | CG50: 0 | CH50: 500 | CI50: 500 | CJ50: 500 | CK50: =sum(BY50:CJ50) -> 2000 | CL50: 500 | CM50: 0 | CN50: 0 | CO50: 500 | CP50: 500 | CQ50: 0 | CR50: 0 | CS50: 0 | CT50: 0 | CU50: 500 | CV50: 500 | CW50: 500 | CX50: =sum(CL50:CW50) -> 3000 | CY50: 500 | CZ50: 500
B51: Short-Term Liquid Traditional Savings (10%) | R51: 0 | S51: 500 | T51: =T13*0.02 -> 129.15 | U51: =U13*0.0387 -> 249.90525 | V51: 200 | W51: 200 | X51: =$X$13*0.04 -> 258.3 | Y51: =$X$13*0.04 -> 258.3 | Z51: =$X$13*0.1 -> 645.75 | AA51: =$X$13*0.047 -> 303.5025 | AB51: =$X$13*0.04 -> 258.3 | AC51: =$X$13*0.04 -> 258.3 | AD51: =$X$13*0.05 -> 322.875 | AE51: =$X$13*0.063 -> 406.8225 | AF51: =$X$13*0.2 -> 1291.5 | AG51: =$X$13*0.2 -> 1291.5 | AH51: =$X$13*0 -> 0 | AI51: =$X$13*0.04 -> 258.3 | AJ51: =$X$13*0.04 -> 258.3 | AK51: =$X$13*0.04 -> 258.3 | AL51: =$X$13*0.04 -> 258.3 | AM51: =$X$13*0.04 -> 258.3 | AN51: =$X$13*0.05 -> 322.875 | AO51: =$X$13*0.05 -> 322.875 | AP51: =$X$13*0.05 -> 322.875 | AQ51: =$X$13*0.05 -> 322.875 | AR51: =$X$13*0.05 -> 322.875 | AS51: =$X$13*0.05 -> 322.875 | AT51: =$X$13*0.05 -> 322.875 | AU51: =$X$13*0.05 -> 322.875 | ... AW51: =$X$13*0.05 -> 322.875 | AX51: =$X$13*0 -> 0 | AY51: =$X$13*0 -> 0 | AZ51: =$X$13*0.05 -> 322.875 | BA51: 0 | BB51: 0 | BC51: -100 | BD51: -100 | BE51: -100 | BF51: -100 | BG51: -100 | BH51: -100 | BI51: -100 | BJ51: -100 | BL51: 0 | BM51: 0 | BN51: 0 | BO51: 2000 | BP51: 500 | BQ51: 5000 | BR51: 2000 | BS51: 0 | BT51: 500 | BU51: 0 | BV51: 0 | BW51: 0 | BX51: =sum(BL51:BW51) -> 10000 | BY51: 0 | BZ51: 0 | CA51: 0 | CB51: 0 | CC51: 0 | CD51: 2000 | CE51: 2000 | CF51: 0 | CG51: 500 | CH51: 500 | CI51: 500 | CJ51: 500 | CK51: =sum(BY51:CJ51) -> 6000 | CL51: 500 | CM51: 0 | CN51: 0 | CO51: 2000 | CP51: 500 | CQ51: 5000 | CR51: 2000 | CS51: 0 | CT51: 500 | CU51: 500 | CV51: 500 | CW51: 500 | CX51: =sum(CL51:CW51) -> 12000 | CY51: 500 | CZ51: 500
B52: Wedding Savings | BU52: 0 | BV52: 0 | BW52: 0 | BX52: =sum(BL52:BW52) -> 0 | BY52: 0 | BZ52: 0 | CA52: 0 | CB52: 0 | CC52: 0 | CD52: 50000 | CE52: 0 | CF52: 0 | CG52: 0 | CH52: 0 | CI52: 0 | CJ52: 0 | CL52: 0 | CM52: 0 | CN52: 0 | CO52: 200000 | CP52: 0 | CQ52: 0 | CR52: 0 | CS52: 0 | CT52: 0 | CU52: 0 | CV52: 0 | CW52: 0
A53: Investment (10%)
B54: Angel investment (1%) | K54: 0 | L54: =150+345 -> 495 | M54: 0 | N54: 0 | O54: =O13*0 -> 0 | P54: 78 | Q54: 0 | R54: 0 | S54: 50 | T54: =$Q13*0 -> 0 | U54: =$Q13*0 -> 0 | V54: =$Q13*0 -> 0 | W54: =$Q13*0 -> 0 | X54: =$X$13*0.01 -> 64.575 | Y54: =$X$13*0.01 -> 64.575 | Z54: =$X$13*0.01 -> 64.575 | AA54: =$X$13*0.01 -> 64.575 | AB54: =$X$13*0 -> 0 | AC54: =$X$13*0 -> 0 | AD54: =$X$13*0 -> 0 | AE54: =$X$13*0 -> 0 | AF54: =$X$13*0 -> 0 | AG54: =sum(2500,1200) -> 3700 | AH54: =sum(2500,500,5000) -> 8000 | AI54: =2000 -> 2000 | AJ54: =$X$13*0 -> 0 | AK54: =$X$13*0 -> 0 | AL54: =7000 -> 7000 | AM54: 3600 | AN54: 3500 | AO54: =$X$13*0 -> 0 | AP54: =6000 -> 6000 | AQ54: =$X$13*0 -> 0 | AR54: =$X$13*1 -> 6457.5 | AS54: =$X$13*0 -> 0 | AT54: =$X$13*0 -> 0 | AU54: 10000 | AV54: 0 | AW54: =$X$13*0 -> 0 | AX54: 1000 | AY54: 900 | AZ54: 900 | BA54: =-sum(3509,1490,500) -> -5499 | BB54: =-800 -> -800 | BC54: =sum(-800,-1200) -> -2000 | BD54: =sum(-800) -> -800 | BE54: =sum(-6200,-800) -> -7000 | BF54: =sum(-400,-7400,-25000) -> -32800 | BG54: =sum(-800,-5000) -> -5800 | BH54: =sum(-400,-400,-12000) -> -12800 | BI54: =sum(0) -> 0 | BJ54: =sum(0) -> 0 | BL54: 0 | BM54: 0 | BN54: 0 | BO54: 0 | BP54: =sum(1500) -> 1500 | BQ54: 0 | BR54: 0 | BS54: 0 | BT54: 0 | BU54: 0 | BV54: 0 | BW54: 0 | BX54: =sum(BL54:BW54) -> 1500 | BY54: 0 | BZ54: 0 | CA54: 0 | CB54: 0 | CC54: 0 | CD54: =sum(30000,15000) -> 45000 | CE54: 1000 | CF54: 1000 | CG54: 1000 | CH54: 1000 | CI54: 1000 | CJ54: 1000 | CK54: =sum(BY54:CJ54) -> 51000 | CL54: 30000 | CM54: 1000 | CN54: 1000 | CO54: 1000 | CP54: 1000 | CQ54: 1000 | CR54: 1000 | CS54: 1000 | CT54: 1000 | CU54: 1000 | CV54: 1000 | CW54: 1000 | CX54: =sum(CL54:CW54) -> 41000 | CY54: 0 | CZ54: 0
B55: Common Stock (5%) | J55: 0 | K55: 0 | L55: 0 | M55: =M13*0 -> 0 | N55: 0 | O55: =O10*0 -> 0 | P55: 0 | Q55: =175+100 -> 275 | R55: =R13*0.0063 -> 41.94225 | S55: 300 | T55: =T13*0.02 -> 129.15 | U55: 120 | V55: 100 | W55: =sum(100,-790) -> -690 | X55: =$X$13*0.02 -> 129.15 | Y55: =$X$13*0.02 -> 129.15 | Z55: =$X$13*0.05 -> 322.875 | AA55: =$X$13*0.02 -> 129.15 | AB55: =$X$13*0.02 -> 129.15 | AC55: =$X$13*0.02 -> 129.15 | AD55: =$X$13*0.02 -> 129.15 | AE55: =$X$13*0.02 -> 129.15 | AF55: =$X$13*0.02 -> 129.15 | AG55: =$X$13*0 -> 0 | AH55: =$X$13*0 -> 0 | AI55: =$X$13*0.02 -> 129.15 | AJ55: =$X$13*0.02 -> 129.15 | AK55: =$X$13*0.02 -> 129.15 | AL55: =$X$13*0.02 -> 129.15 | AM55: =$X$13*0.02 -> 129.15 | AN55: =$X$13*0.02 -> 129.15 | AO55: =$X$13*0.02 -> 129.15 | AP55: =$X$13*0.02 -> 129.15 | ... AR55: =$X$13*0.02 -> 129.15 | AS55: 0 | AT55: =$X$13*0.02 -> 129.15 | AU55: =$X$13*0.02 -> 129.15 | AV55: =$X$13*0.02 -> 129.15 | AW55: =$X$13*0.02 -> 129.15 | AX55: 0 | AY55: 0 | AZ55: =$X$13*0.02 -> 129.15 | BA55: -400 | BB55: -400 | BC55: 0 | BD55: 0 | BE55: 0 | BF55: 0 | BG55: 0 | BH55: 0 | BI55: 0 | BJ55: 0 | BL55: 0 | BM55: 0 | BN55: 0 | BO55: 0 | BP55: 0 | BQ55: 0 | BR55: 0 | BS55: 0 | BT55: 0 | BU55: 0 | BV55: 0 | BW55: 0 | BX55: =sum(BL55:BW55) -> 0 | BY55: 0 | BZ55: 0 | CA55: 0 | CB55: 82631 | CC55: 0 | CD55: 0 | CE55: 1000 | CF55: 1000 | CG55: 1000 | CH55: 1000 | CI55: 1000 | CJ55: 1000 | CK55: =sum(BY55:CJ55) -> 88631 | CL55: 7000 | CM55: 1000 | CN55: 1000 | CO55: 1000 | CP55: 1000 | CQ55: 1000 | CR55: 1000 | CS55: 1000 | CT55: 1000 | CU55: 1000 | CV55: 1000 | CW55: 1000 | CX55: =sum(CL55:CW55) -> 18000 | CY55: 500 | CZ55: 500
B56: Crypto Portfolio (10%) | J56: 0 | K56: 0 | L56: 0 | M56: 0 | N56: 0 | O56: =O13*0 -> 0 | P56: 500 | Q56: =25+100+100+450 -> 675 | R56: =R13*0.065 -> 432.7375 | S56: 225 | T56: =T13*0.02 -> 129.15 | U56: 0 | V56: 200 | W56: 100 | X56: =$X$13*0.06 -> 387.45 | Y56: =$X$13*0.06 -> 387.45 | Z56: =$X$13*0.1 -> 645.75 | AA56: =AA13*0.1 -> 880 | AB56: =$X$13*0.07 -> 452.025 | AC56: =$X$13*0.06 -> 387.45 | AD56: =$X$13*0.08 -> 516.6 | AE56: =$X$13*0.06 -> 387.45 | AF56: =$X$13*0.06 -> 387.45 | AG56: =$X$13*0 -> 0 | AH56: =$X$13*0 -> 0 | AI56: =$X$13*0.078 -> 503.685 | AJ56: =$X$13*0.078 -> 503.685 | AK56: =$X$13*0.078 -> 503.685 | AL56: =$X$13*0.078 -> 503.685 | AM56: =$X$13*0.078 -> 503.685 | AN56: =$X$13*0.078 -> 503.685 | AO56: =$X$13*0.078 -> 503.685 | AP56: =$X$13*0.5 -> 3228.75 | AQ56: =$X$13*0.078 -> 503.685 | AR56: =$X$13*0.078 -> 503.685 | AS56: =$X$13*0.078 -> 503.685 | AT56: =$X$13*0.078 -> 503.685 | AU56: =$X$13*0.078 -> 503.685 | AV56: =$X$13*0.078 -> 503.685 | AW56: =$X$13*0.078 -> 503.685 | AX56: 0 | AY56: 0 | AZ56: =$X$13*0.078 -> 503.685 | BA56: -500 | BB56: -500 | BC56: 0 | BD56: 0 | BE56: 0 | BF56: 0 | BG56: 0 | BH56: 0 | BI56: -500 | BJ56: -500 | BL56: 0 | BM56: 0 | BN56: 500 | BO56: 1500 | BP56: 0 | BQ56: 0 | BR56: 0 | BS56: 0 | BT56: 0 | BU56: 0 | BV56: 0 | BW56: 0 | BX56: =sum(BL56:BW56) -> 2000 | BY56: 0 | BZ56: 0 | CA56: 4000 | CB56: 0 | CC56: 0 | CD56: 25000 | CE56: 0 | CF56: 0 | CG56: 0 | CH56: 1000 | CI56: 1000 | CJ56: 1000 | CK56: =sum(BY56:CJ56) -> 32000 | CL56: 20000 | CM56: 0 | CN56: 500 | CO56: 1500 | CP56: 0 | CQ56: 0 | CR56: 0 | CS56: 0 | CT56: 0 | CU56: 1000 | CV56: 1000 | CW56: 1000 | CX56: =sum(CL56:CW56) -> 25000 | CY56: 1000 | CZ56: 1000
B57: 401K IRA (2.5% Pre-Tax) | M57: =M4*0.03 -> 300 | N57: =N4*0.03 -> 300 | O57: =O12 -> 400 | P57: =P12 -> 400 | Q57: =Q12 -> 307.5 | R57: =R12 -> 307.5 | S57: =S12 -> 307.5 | T57: =T12 -> 307.5 | U57: =U12 -> 307.5 | V57: =V12 -> 307.5 | ... BB57: =BB12 -> 0 | BC57: 0 | BD57: 0 | BE57: 0 | BF57: 0 | BG57: =-0 -> 0 | BH57: =-0 -> 0 | BI57: =0 -> 0 | BJ57: =0 -> 0 | BL57: 0 | BM57: 0 | BN57: 0 | BO57: 500 | BP57: 0 | BQ57: 0 | BR57: 0 | BS57: 0 | BT57: 0 | BU57: 0 | BV57: 0 | BW57: 0 | BX57: =sum(BL57:BW57) -> 500 | BY57: 0 | BZ57: 0 | CA57: 0 | CB57: 0 | CC57: 0 | CD57: 10000 | CE57: 0 | CF57: 0 | CG57: 0 | CH57: 500 | CI57: 500 | CJ57: 500 | CK57: =sum(BY57:CJ57) -> 11500 | CL57: 10000 | CM57: 0 | CN57: 0 | CO57: 500 | CP57: 0 | CQ57: 0 | CR57: 0 | CS57: 0 | CT57: 0 | CU57: 500 | CV57: 500 | CW57: 500 | CX57: =sum(CL57:CW57) -> 12000 | CY57: 500 | CZ57: 500
B58: Real Estate | BH58: 0 | BI58: 0 | BJ58: 0 | BL58: 0 | BM58: 0 | BN58: 0 | BO58: 0 | BP58: 0 | BQ58: 0 | BR58: 0 | BS58: 0 | BT58: 0 | BU58: 0 | BV58: 0 | BW58: 0 | BX58: =sum(BL58:BW58) -> 0 | BY58: 0 | BZ58: 0 | CA58: 0 | CB58: 0 | CC58: 0 | CD58: 0 | CE58: 0 | CF58: 0 | CG58: 0 | CH58: 0 | CI58: 0 | CJ58: 0 | CK58: =sum(BY58:CJ58) -> 0 | CL58: 0 | CM58: 0 | CN58: 0 | CO58: 0 | CP58: 0 | CQ58: 0 | CR58: 0 | CS58: 0 | CT58: 0 | CU58: 0 | CV58: 0 | CW58: 0 | CX58: =sum(CL58:CW58) -> 0 | CY58: 0 | CZ58: 0
A59: Philanthropy (1%)
B60: Non-Profit (1%) | I60: 0 | J60: 0 | K60: =K14*0 -> 0 | L60: =L14*0 -> 0 | M60: 0 | N60: 0 | O60: =O13*0.01 -> 72 | P60: 0 | Q60: =70+20+20 -> 110 | R60: 0 | S60: 0 | T60: 125 | U60: 0 | V60: =V13*0.01 -> 67.575 | W60: =W13*0.01 -> 64.575 | X60: =X13*0.02 -> 129.15 | Y60: =Y13*0.02 -> 241.15 | Z60: =Z13*0.02 -> 176 | AA60: =AA13*0 -> 0 | AB60: =AB13*0.02 -> 176 | AC60: =AC13*0.01 -> 91.666667 | AD60: =AD13*0.01 -> 87.466667 | AE60: =AE13*0.01 -> 197.46667 | AF60: =AF13*0 -> 0 | AG60: =AG13*0 -> 0 | AH60: =AH13*0 -> 0 | AI60: =AI13*0.01 -> 84.666667 | AJ60: =AJ13*0.01 -> 84.666667 | AK60: =AK13*0.01 -> 187.75 | AL60: =AL13*0.01 -> 115.5 | AM60: =AM13*0.01 -> 115.5 | AN60: =AN13*0.01 -> 215.5 | AO60: =AO13*0 -> 0 | AP60: =1000 -> 1000 | AQ60: =AQ13*0.01 -> 115.5 | AR60: =AR13*0.01 -> 115.5 | AS60: 400 | AT60: 0 | AU60: =AU13*0.01 -> 277.5 | AV60: =AV13*0.01 -> 115.5 | AW60: =AW13*0.01 -> 115.5 | AX60: =AX13*0.01 -> 148.94 | AY60: =AY13*0 -> 0 | AZ60: =AZ13*0 -> 0 | BA60: =BA13*0 -> 0 | BB60: =-100 -> -100 | BC60: =-100 -> -100 | BD60: =-100 -> -100 | BE60: =-100 -> -100 | BF60: =-50 -> -50 | BG60: =-50 -> -50 | BH60: =-50 -> -50 | BI60: =-100 -> -100 | BJ60: =-100 -> -100 | BL60: 0 | BM60: 100 | BN60: 100 | BO60: 100 | BP60: 100 | BQ60: 100 | BR60: 50 | BS60: 50 | BT60: 100 | BU60: 0 | BV60: 0 | BW60: =BW13*0.01 -> 221 | BX60: =sum(BL60:BW60) -> 921 | BY60: =BY13*0.005 -> 110.5 | BZ60: =BZ13*0.005 -> 110.5 | CA60: =CA13*0.005 -> 485.5 | CB60: =CB13*0.005 -> 528 | CC60: =CC13*0.005 -> 99 | CD60: =CD13*0.005 -> 1349 | CE60: =CE13*0.005 -> 16599 | CF60: =CF13*0.005 -> 16599 | ... CJ60: =CJ13*0.005 -> 99 | CK60: =sum(BY60:CJ60) -> 69276.5 | CL60: =CL13*0.01 -> 221 | CM60: =CM13*0.01 -> 221 | CN60: =CN13*0.01 -> 406 | CO60: =CO13*0.01 -> 2198 | CP60: =CP13*0.01 -> 198 | CQ60: =CQ13*0.01 -> 198 | CR60: =CR13*0.01 -> 198 | CS60: =CS13*0.01 -> 198 | ... CW60: =CW13*0.01 -> 198 | CX60: =sum(CL60:CW60) -> 4630 | CY60: 100 | CZ60: 100
A61: Total Financial Health | C61: =C13-C44-#REF!-C48+'BUDGET 2018 (Archive)'!O35 -> #REF! | D61: =D13-D44-#REF!-D48+'BUDGET 2018 (Archive)'!P35 -> #REF! | E61: =E13-E44-#REF!-E48+'BUDGET 2018 (Archive)'!Q35 -> #REF! | F61: =F13-F44-#REF!-F48+'BUDGET 2018 (Archive)'!R35 -> #REF! | G61: =G13-G44-#REF!-G48+'BUDGET 2018 (Archive)'!S35 -> #REF! | H61: =H13-H44-#REF!-H48+'BUDGET 2018 (Archive)'!T35 -> #REF! | I61: =H61+I13-I44-#REF!-#REF!-I48 -> #REF! | J61: =sum(J48:J60) -> 3200 | K61: =sum(K48:K60) -> 1000 | L61: =sum(L48:L60) -> 1495 | M61: =sum(M48:M56)+M60 -> 0 | N61: =sum(N48:N56)+N60 -> 1757.5 | O61: =sum(O48:O56)+O60 -> 2617 | P61: =sum(P48:P60) -> 6954 | Q61: =sum(Q48:Q56)+Q60 -> 3093 | R61: =sum(R48:R56)+R60 -> 3137.6797 | S61: =sum(S48:S56)+S60 -> 6675 | T61: =sum(T48:T56)+T60 -> 2126.825 | U61: =sum(U48:U56)+U60 -> 2952.9052 | V61: =sum(V48:V56)+V60 -> 3964.575 | W61: =sum(W48:W56)+W60 -> 1611.825 | X61: =sum(X48:X57) -> 2051.025 | Y61: =sum(Y48:Y57) -> 2546.45 | Z61: =sum(Z48:Z57) -> 3204.7 | AA61: =sum(AA48:AA57) -> 4474.9525 | AB61: =sum(AB48:AB57) -> 2793.2 | AC61: =sum(AC48:AC57) -> 3135.2917 | AD61: =sum(AD48:AD57) -> 3208.625 | AE61: =sum(AE48:AE57) -> 14799.423 | ... AO61: =sum(AO48:AO57) -> 2533.585 | AP61: =sum(AP48:AP60) -> 28003.65 | AQ61: =sum(AQ48:AQ57) -> 2433.585 | AR61: =sum(AR48:AR57) -> 11201.085 | AS61: =sum(AS48:AS57) -> 4291.56 | AT61: =sum(AT48:AT57) -> 9429.14 | AU61: =sum(AU48:AU57) -> 16828.585 | AV61: =sum(AV48:AV57) -> 2433.585 | AW61: =sum(AW48:AW57) -> 4640.71 | AX61: =sum(AX48:AX57) -> 4489.4 | ... AZ61: =sum(AZ48:AZ57) -> 17855.71 | BA61: =sum(BA48:BA60) -> -21399 | BB61: =sum(BB48:BB60) -> -4200 | BC61: =sum(BC48:BC60) -> -7200 | BD61: =sum(BD48:BD60) -> -3400 | BE61: =sum(BE48:BE60) -> -9600 | BF61: =sum(BF48:BF60) -> -37950 | BG61: =sum(BG48:BG60) -> -10450 | BH61: =sum(BH48:BH60) -> -15450 | ... BJ61: =sum(BJ48:BJ60) -> -8700 | BL61: =sum(BL48:BL60) -> 0 | BM61: =sum(BM48:BM60) -> 10100 | BN61: =sum(BN48:BN60) -> 8600 | BO61: =sum(BO48:BO60) -> 24600 | BP61: =sum(BP48:BP60) -> 2600 | BQ61: =sum(BQ48:BQ60) -> 10100 | BR61: =sum(BR48:BR60) -> 47050 | BS61: =sum(BS48:BS60) -> 50 | ... BW61: =sum(BW48:BW60) -> 221 | BX61: =sum(BL61:BW61) -> 103921 | BY61: =sum(BY48:BY60) -> 110.5 | BZ61: =sum(BZ48:BZ60) -> 110.5 | CA61: =sum(CA48:CA60) -> 54485.5 | CB61: =sum(CB48:CB60) -> 83159 | CC61: =sum(CC48:CC60) -> 99 | CD61: =sum(CD48:CD60) -> 133849 | CE61: =sum(CE48:CE60) -> 20599 | CF61: =sum(CF48:CF60) -> 18599 | ... CJ61: =sum(CJ48:CJ60) -> 4599 | CK61: =sum(BY61:CJ61) -> 360407.5 | CL61: =sum(CL48:CL60) -> 118221 | CM61: =sum(CM48:CM60) -> 12221 | CN61: =sum(CN48:CN60) -> 10906 | CO61: =sum(CO48:CO60) -> 228698 | CP61: =sum(CP48:CP60) -> 3198 | CQ61: =sum(CQ48:CQ60) -> 12198 | CR61: =sum(CR48:CR60) -> 49198 | CS61: =sum(CS48:CS60) -> 2198 | ... CW61: =sum(CW48:CW60) -> 4698 | CX61: =sum(CL61:CW61) -> 478630 | CY61: =sum(CY48:CY60) -> 3100 | CZ61: =sum(CZ48:CZ60) -> 3100
A64: Total Remaining | J64: =J13-#REF!-J44-J61 -> #REF! | K64: =K13-#REF!-K44-K61 -> #REF! | L64: =L13-#REF!-L44-L61+K64 -> #REF! | M64: =M13-#REF!-M44-M61+L64 -> #REF! | N64: =N13-N44-N61 -> 2020.5 | O64: =N64+O13-O44-O61 -> 4252.5 | P64: =P13-P44-P61+P57 -> 306.27304 | Q64: =Q13-Q44-Q61+Q57+P64 -> 593.70265 | R64: =R13-R44-R61+R57+Q64 -> 636.13521 | S64: =S13-S44-S61+S57+100 -> 522.26099 | T64: =T13-T44-T61+T57+S64 -> -1048.473 | U64: =U13-U44-U61+U57+T64 -> 908.53193 | V64: =V13-V44-V61+V57+U64 -> -721.33252 | W64: =W13-W44-W61+W57+V64 -> 1270.5857 | X64: =X13-X44-X61+X57 -> -1951.5103 | Y64: =Y13-Y44-Y61+Y57+X64 -> 2803.5647 | Z64: =Z13-Z44-Z61+Z57+Y64 -> 1629.2147 | AA64: =AA13-AA44-AA61+AA57+Z64 -> -860.72783 | AB64: =AB13-AB44-AB61+AB57+AA64 -> 197.50717 | AC64: =AC13-AC44-AC61+AC57+AB64 -> 403.65051 | AD64: =AD13-AD44-AD61+AD57+AC64 -> 1636.4605 | AE64: =AE13-AE44-AE61+AE57+AD64 -> 1778.473 | AF64: =AF13-AF44-AF61+AF57+AE64 -> 3186.808 | ... AH64: =AH13-AH44-AH61+AH57+AG64 -> 6774.653 | AI64: =AI13-AI44-AI61+AI57+AG64 -> 1475.4597 | AJ64: =AJ13-AJ44-AJ61+AJ57 -> 318.71667 | AK64: =AK13-AK44-AK61+AK57 -> 8470.725 | AL64: =AL13-AL44-AL61+AL57+AK64 -> 1168.45 | AM64: =AM13-AM44-AM61+AM57+AL64 -> 501.675 | AN64: =AN13-AN44-AN61+AN57+AM64 -> 2289.09 | AO64: =AO13-AO44-AO61+AO57+AN64 -> 5941.505 | AP64: =AP13-AP44-AP61+AP57+AO64 -> 2198.855 | AQ64: =AQ13-AQ44-AQ61+AQ57+AP64 -> 4926.27 | AR64: =AR13-AR44-AR61+AR57+AQ64 -> -1113.815 | AS64: =AS13-AS44-AS61+AS57+AR64 -> -272.375 | ... AU64: =AU13-AU44-AU61+AU57+AT64 -> 4643.01 | AV64: =0 -> 0 | AW64: =AW13-AW44-AW61+AW57 -> 0.29 | AX64: =AX13-AX44-AX61+AX57 -> 2995.6 | AY64: =AY13-AY44-AY61+AY57 -> 5106 | AZ64: =AZ13-AZ44-AZ61+AZ57+AY64 -> 6566.29 | BA64: =sum(BA13,BA44,BA61) -> 2484 | BB64: =sum(BB13,BB44,BB61,BA64) -> 2167 | BC64: =sum(BC13,BC44,BC61,BB64) -> -350 | BD64: =sum(BD13,BD44,BD61,BC64) -> -7263 | BE64: =sum(BE13,BE44,BE61,BD64) -> -14280 | BF64: =sum(BF13,BF44,BF61) -> 883 | BG64: =sum(BG13,BG44,BG61,BF64) -> 1581 | BH64: =sum(BH13,BH44,BH61,BG64) -> 1964 | BI64: =sum(BI13,BI44,BI61,BH64) -> 1447 | BJ64: =sum(BJ13,BJ44,BJ61,BI64) -> -7620 | BL64: =BL13-BL44-BL61 -> 8517 | BM64: =BM13-BM44-BM61 -> -933 | BN64: =BM64+BN13-BN44-BN61 -> 5234 | BO64: =BN64+BO13-BO44-BO61 -> 3701 | BP64: =BO64+BP13-BP44-BP61 -> 3568 | BQ64: =BP64+BQ13-BQ44-BQ61 -> 7510 | BR64: =BQ64+BR13-BR44-BR61 -> 10802 | BS64: =BR64+BS13-BS44-BS61 -> -13596 | BT64: =BS64+BT13-BT44-BT61 -> -6774 | BU64: =BT64+BU13-BU44-BU61 -> -6692 | ... BW64: =BV64+BW13-BW44-BW61 -> -749 | BX64: =BW64 -> -749 | BY64: =sum(BX64,BY13,-BY44,-BY61) -> 122.5 | BZ64: =sum(BY64,BZ13,-BZ44,-BZ61) -> 8694 | CA64: =sum(BZ64,CA13,-CA44,-CA61) -> 20690.5 | CB64: =sum(CA64,CB13,-CB44,-CB61) -> 27013.5 | CC64: =sum(CB64,CC13,-CC44,-CC61) -> 33096.5 | CD64: =sum(CC64,CD13,-CD44,-CD61) -> 117429.5 | CE64: =sum(CD64,CE13,-CE44,-CE61) -> 3403012.5 | CF64: =sum(CE64,CF13,-CF44,-CF61) -> 6690595.5 | ... CJ64: =sum(CI64,CJ13,-CJ44,-CJ61) -> 13266328 | CK64: =CJ64 -> 13266328 | CL64: =sum(CK64,CL13,-CL44,-CL61) -> 13151788 | CM64: =sum(CL64,CM13,-CM44,-CM61) -> 13148250 | CN64: =sum(CM64,CN13,-CN44,-CN61) -> 13163526 | CO64: =sum(CN64,CO13,-CO44,-CO61) -> 13109210 | CP64: =sum(CO64,CP13,-CP44,-CP61) -> 13112394 | CQ64: =sum(CP64,CQ13,-CQ44,-CQ61) -> 13101078 | CR64: =sum(CQ64,CR13,-CR44,-CR61) -> 13058262 | CS64: =sum(CR64,CS13,-CS44,-CS61) -> 13062446 | ... CW64: =sum(CV64,CW13,-CW44,-CW61) -> 13046182 | CX64: =CW64 -> 13046182 | CY64: =CJ64+CY13-CY44-CY61 -> 13273794 | CZ64: =CK64+CZ13-CZ44-CZ61 -> 13273794

Sheet PRO FORMA
A1: Matt Wright
A2: Pro-Forma FY '23-'25
I3: 2023 | J3: 2024 | K3: 2025 | L3: Projected
B4: 2024 | C4: 2025 | D4: 2026 | E4: 2027 | F4: 2028 | G4: 2029 | H4: 2030 | I4: PROJECTED | J4: PROJECTED | K4: PROJECTED | L4: Total 2022
A5: OPERATING REVENUE
A6: Salary - Consensys | B6: =212000/2 -> 106000 | C6: =220000/2 -> 110000 | D6: =sum(500000/12*6) -> 250000 | E6: =sum(500000/12*6) -> 250000 | F6: =sum(500000/12*6) -> 250000 | G6: =sum(500000/12*6) -> 250000 | I6: =sum(C6*2) -> 220000 | J6: =sum(D6:E6) -> 500000 | K6: =sum(F6:G6) -> 500000 | L6: =#REF!+I6 -> #REF!
A7: Salary - EVM Capital | B7: 0 | C7: =sum(500000/12*6) -> 250000 | D7: =sum(500000/12*6) -> 250000 | E7: =sum(500000/12*6) -> 250000 | F7: =sum(500000/12*6) -> 250000 | G7: =sum(500000/12*6) -> 250000 | I7: =sum(C7*2) -> 500000 | J7: =sum(D7:E7) -> 500000 | K7: =sum(F7:G7) -> 500000
A8: Consulting | B8: 0 | C8: 0 | D8: =sum(250000/12*6) -> 125000 | E8: =sum(250000/12*6*3) -> 375000 | F8: =sum(250000/12*6*3) -> 375000 | G8: =sum(250000/12*6*3) -> 375000 | I8: =sum(C8*2) -> 0 | J8: =sum(D8:E8) -> 500000 | K8: =sum(F8:G8) -> 750000
B9: 0 | C9: 0 | D9: =sum(20000*6) -> 120000 | E9: =sum(20000*6) -> 120000 | F9: =sum(20000*6) -> 120000 | G9: =sum(20000*6) -> 120000 | I9: =sum(C9*2) -> 0 | J9: =sum(D9:E9) -> 240000 | K9: =sum(F9:G9) -> 240000
A11: Total Revenue | B11: =sum(B6:B10) -> 106000 | C11: =sum(C6:C10) -> 360000 | D11: =sum(D6:D10) -> 745000 | E11: =sum(E6:E10) -> 995000 | F11: =sum(F6:F10) -> 995000 | G11: =sum(G6:G10) -> 995000 | I11: =sum(I6:I10) -> 720000 | J11: =sum(J6:J10) -> 1740000 | K11: =sum(K6:K10) -> 1990000
A13: OPERATING EXPENSES
A14: FTE Payroll | B14: =sum('BUDGET FY''23'!B16:G16) -> #REF! | C14: =sum('BUDGET FY''23'!H16:M16) -> #REF! | D14: =sum(-200000/2,-200000/2,-165000/2) -> -282500 | E14: =sum(-200000/2,-200000/2,-165000/2) -> -282500 | F14: =sum(-200000/2,-200000/2,-165000/2) -> -282500 | G14: =sum(-200000/2,-200000/2,-165000/2) -> -282500 | I14: =sum(C14*2) -> #REF! | J14: =sum(D14:E14) -> -565000 | K14: =sum(F14:G14) -> -565000
A15: Contractors | B15: =sum('BUDGET FY''23'!B17:G17) -> #REF! | C15: =sum('BUDGET FY''23'!H17:M17) -> #REF! | D15: =sum(-10000*2,-5000*2) -> -30000 | E15: =sum(-10000*2,-5000*2) -> -30000 | F15: =sum(-10000*2,-5000*2) -> -30000 | G15: =sum(-10000*2,-5000*2) -> -30000 | I15: =sum(C15*2) -> #REF! | J15: =sum(D15:E15) -> -60000 | K15: =sum(F15:G15) -> -60000
A16: Legal, Accounting | B16: =sum('BUDGET FY''23'!B18:G18) -> #REF! | C16: =sum('BUDGET FY''23'!H18:M18) -> #REF! | D16: =-50000 -> -50000 | E16: =-50000 -> -50000 | F16: =-50000 -> -50000 | G16: =-50000 -> -50000 | I16: =sum(C16*2) -> #REF! | J16: =sum(D16:E16) -> -100000 | K16: =sum(F16:G16) -> -100000 | L16: =#REF!+I16 -> #REF!
A17: Office | B17: =sum('BUDGET FY''23'!B19:G19) -> #REF! | C17: =sum('BUDGET FY''23'!H19:M19) -> #REF! | D17: 0 | E17: 0 | F17: 0 | G17: 0 | I17: =sum(C17*2) -> #REF! | J17: =sum(D17:E17) -> 0 | K17: =sum(F17:G17) -> 0 | L17: =#REF!+I17 -> #REF!
A18: Rent | B18: =sum('BUDGET FY''23'!B20:G20) -> #REF! | C18: =sum('BUDGET FY''23'!H20:M20) -> #REF! | D18: =sum(-1400*6) -> -8400 | E18: =sum(-1400*6) -> -8400 | F18: =sum(-1400*6) -> -8400 | G18: =sum(-1400*6) -> -8400 | I18: =sum(C18*2) -> #REF! | J18: =sum(D18:E18) -> -16800 | K18: =sum(F18:G18) -> -16800 | L18: =#REF!+I18 -> #REF!
A19: Utilities | B19: =sum('BUDGET FY''23'!B21:G21) -> #REF! | C19: =sum('BUDGET FY''23'!H21:M21) -> #REF! | D19: =sum(-1000*6) -> -6000 | E19: =sum(-1000*6) -> -6000 | F19: =sum(-1000*6) -> -6000 | G19: =sum(-1000*6) -> -6000 | I19: =sum(C19*2) -> #REF! | J19: =sum(D19:E19) -> -12000 | K19: =sum(F19:G19) -> -12000 | L19: =#REF!+I19 -> #REF!
A20: Software & Apps | B20: =sum('BUDGET FY''23'!B22:G22) -> #REF! | C20: =sum('BUDGET FY''23'!H22:M22) -> #REF! | D20: =sum(-500*6) -> -3000 | E20: =sum(-500*6) -> -3000 | F20: =sum(-500*6) -> -3000 | G20: =sum(-500*6) -> -3000 | I20: =sum(C20*2) -> #REF! | J20: =sum(D20:E20) -> -6000 | K20: =sum(F20:G20) -> -6000 | L20: =#REF!+I20 -> #REF!
A21: Travel | B21: =sum('BUDGET FY''23'!B23:G23) -> #REF! | C21: =sum('BUDGET FY''23'!H23:M23) -> #REF! | D21: =sum(-5000*6) -> -30000 | E21: =sum(-5000*6) -> -30000 | F21: =sum(-5000*6) -> -30000 | G21: =sum(-5000*6) -> -30000 | I21: =sum(C21*2) -> #REF! | J21: =sum(D21:E21) -> -60000 | K21: =sum(F21:G21) -> -60000 | L21: =#REF!+I21 -> #REF!
A22: Business Development | B22: =sum('BUDGET FY''23'!B24:G24) -> #REF! | C22: =sum('BUDGET FY''23'!H24:M24) -> #REF! | D22: =sum(-5000*6) -> -30000 | E22: =sum(-5000*6) -> -30000 | F22: =sum(-5000*6) -> -30000 | G22: =sum(-5000*6) -> -30000 | I22: =sum(C22*2) -> #REF! | J22: =sum(D22:E22) -> -60000 | K22: =sum(F22:G22) -> -60000 | L22: =#REF!+I22 -> #REF!
A23: Marketing, Events | B23: =sum('BUDGET FY''23'!B25:G25) -> #REF! | C23: =sum('BUDGET FY''23'!H25:M25) -> #REF! | D23: =sum(-10000*6) -> -60000 | E23: =sum(-10000*6) -> -60000 | F23: =sum(-10000*6) -> -60000 | G23: =sum(-10000*6) -> -60000 | I23: =sum(C23*2) -> #REF! | J23: =sum(D23:E23) -> -120000 | K23: =sum(F23:G23) -> -120000 | L23: =#REF!+I23 -> #REF!
A24: Platform (EVM Labs) | B24: =sum('BUDGET FY''23'!B26:G26) -> #REF! | C24: =sum('BUDGET FY''23'!H26:M26) -> #REF! | D24: 0 | E24: 0 | F24: 0 | G24: 0 | I24: =sum(C24*2) -> #REF! | J24: =sum(D24:E24) -> 0 | K24: =sum(F24:G24) -> 0 | L24: =#REF!+I24 -> #REF!
A25: Bank Fees / Credit Interest | B25: =sum('BUDGET FY''23'!B27:G27) -> #REF! | C25: =sum('BUDGET FY''23'!H27:M27) -> #REF! | D25: 0 | E25: 0 | F25: 0 | G25: 0 | I25: =sum(C25*2) -> #REF! | J25: =sum(D25:E25) -> 0 | K25: =sum(F25:G25) -> 0 | L25: =#REF!+I25 -> #REF!
A26: Interest Expense | B26: =sum('BUDGET FY''23'!B28:G28) -> #REF! | C26: =sum('BUDGET FY''23'!H28:M28) -> #REF! | D26: 0 | E26: 0 | F26: 0 | G26: 0 | I26: =sum(C26*2) -> #REF! | J26: =sum(D26:E26) -> 0 | K26: =sum(F26:G26) -> 0 | L26: =#REF!+I26 -> #REF!
A28: Total Expenses | B28: =sum(B14:B27) -> #REF! | C28: =sum(C14:C27) -> #REF! | D28: =sum(D14:D27) -> -499900 | E28: =sum(E14:E27) -> -499900 | F28: =sum(F14:F27) -> -499900 | G28: =sum(G14:G27) -> -499900 | I28: =sum(C28:G28) -> #REF! | J28: =sum(D28:H28) -> -1999600 | K28: =sum(E28:I28) -> #REF! | L28: =sum(L16:L27) -> #REF!
A30: NET OPERATING INCOME (LOSS) | B30: =B11+B28 -> #REF! | C30: =C11+C28 -> #REF! | D30: =D11+D28 -> 245100 | E30: =E11+E28 -> 495100 | F30: =F11+F28 -> 495100 | G30: =G11+G28 -> 495100 | I30: =sum(C30:G30) -> #REF! | J30: =sum(D30:H30) -> 1730400 | K30: =sum(E30:I30) -> #REF!
A32: CASH INCR (DECR) SHORT TERM
A33: Accounts Payable Increase (Decr) | B33: =sum(0) -> 0 | C33: =sum(0) -> 0 | D33: =sum(0) -> 0 | E33: =sum(0) -> 0 | F33: =sum(0) -> 0 | G33: =sum(0) -> 0 | I33: =sum(C33:G33) -> 0 | J33: =sum(D33:H33) -> 0 | K33: =sum(E33:I33) -> 0 | L33: =#REF!+I33 -> #REF!
A34: Credit Card Increase (Decrease) | B34: =sum(-3400*6) -> -20400 | C34: =sum(-3400*6) -> -20400 | D34: 0 | E34: 0 | F34: 0 | G34: 0 | I34: =sum(C34:G34) -> -20400 | J34: =sum(D34:H34) -> 0 | K34: =sum(E34:I34) -> -20400 | L34: =#REF!+I34 -> #REF!
A36: Net Cash Incr (Decr) - Short Term | B36: =sum(B33:B35) -> -20400 | C36: =sum(C33:C35) -> -20400 | D36: =sum(D33:D35) -> 0 | E36: =sum(E33:E35) -> 0 | F36: =sum(F33:F35) -> 0 | G36: =sum(G33:G35) -> 0 | I36: =sum(I32:I35) -> -20400 | J36: =sum(J32:J35) -> 0 | K36: =sum(K32:K35) -> -20400 | L36: =sum(L28:L35) -> #REF!
A38: CASH INCR (DECR) LONG TERM
A39: Seed Investment | B39: 0 | C39: =3500000 -> 3500000 | D39: 0 | E39: 0 | F39: 0 | G39: 0 | I39: =sum(C39:G39) -> 3500000 | J39: =sum(D39:H39) -> 0 | K39: =sum(E39:I39) -> 3500000
A40: Refinancing | B40: 0 | C40: =sum(-350000) -> -350000 | D40: 0 | E40: 0 | F40: 0 | G40: 0 | I40: =sum(C40:G40) -> -350000 | J40: =sum(D40:H40) -> 0 | K40: =sum(E40:I40) -> -350000
A41: Investment - Fund I | B41: 0 | C41: -250000 | D41: 0 | E41: 0 | F41: 0 | G41: 0 | I41: =sum(C41:G41) -> -250000 | J41: =sum(D41:H41) -> 0 | K41: =sum(E41:I41) -> -250000
A42: Investment - Fund II | B42: 0 | C42: 0 | D42: -250000 | E42: 0 | F42: 0 | G42: 0 | I42: =sum(C42:G42) -> -250000 | J42: =sum(D42:H42) -> -250000 | K42: =sum(E42:I42) -> -250000
A43: Prop Capital | B43: 0 | C43: =-2500000 -> -2500000 | D43: 0 | E43: 0 | F43: 0 | G43: 0 | I43: =sum(C43:G43) -> -2500000 | J43: =sum(D43:H43) -> 0 | K43: =sum(E43:I43) -> -2500000
A44: Founder - Personal Investment | B44: 0 | C44: =sum(-'CAPITAL ACCOUNT'!AL10/2) -> #REF! | D44: =sum(-'CAPITAL ACCOUNT'!AL10/2) -> #REF! | E44: 0 | F44: =sum(-'CAPITAL ACCOUNT'!AO10/2) -> #REF! | G44: 0 | I44: =sum(C44:G44) -> #REF! | J44: =sum(D44:H44) -> #REF! | K44: =sum(E44:I44) -> #REF!
A45: Net Cash Incr (Decr) - Long Term | B45: =sum(B39:B44) -> 0 | C45: =sum(C39:C44) -> #REF! | D45: =sum(D39:D44) -> #REF! | E45: =sum(E39:E44) -> 0 | F45: =sum(F39:F44) -> #REF! | G45: =sum(G39:G44) -> 0 | I45: =sum(C45:G45) -> #REF! | J45: =sum(D45:H45) -> #REF! | K45: =sum(E45:I45) -> #REF! | L45: =sum(L38:L42) -> 0
A47: NET CASH INCRE (DECR) | B47: =B36+B45 -> -20400 | C47: =C36+C45 -> #REF! | D47: =D36+D45 -> #REF! | E47: =E36+E45 -> 0 | F47: =F36+F45 -> #REF! | G47: =G36+G45 -> 0 | I47: =I36+I45 -> #REF! | J47: =J36+J45 -> #REF! | K47: =K36+K45 -> #REF! | L47: =L36+L45 -> #REF!
A49: PROJECTED ENDING CASH | B49: =sum(B11,B28,B36,B45) -> #REF! | C49: =sum(C11,C28,C36,C45) -> #REF! | D49: =sum(D11,D28,D36,D45,C49) -> #REF! | E49: =sum(E11,E28,E36,E45,D49) -> #REF! | F49: =sum(F11,F28,F36,F45,E49) -> #REF! | G49: =sum(G11,G28,G36,G45,F49) -> #REF!

Sheet LIABILITIES
B1: Debt Consolidation | E1: Goal: $0 bad debt, $5m Net Worth by July 2024
B4: List all of your debts. Enter the balance you owe, annual interest rate, and required monthly payment for each.
B5: Update spreadsheet as you pay off your debts. Add more rows if needed.
B7: Creditor | C7: Balance | D7: Interest Rate | E7: Monthly Payment | F7: % of Total | G7: Payment Scheduled
B8: Nelnet | C8: 4763 | D8: 0.044 | E8: 0 | F8: =IF(C8>0,C8/SUM($C$8:$C$25), "") -> 0.18750765 | G8: Yes
B9: Parents | C9: =16584.63-1500-1500-1200 -> 12384.63 | D9: 0 | E9: 1000 | F9: =IF(C9>0,C9/SUM($C$8:$C$25), "") -> 0.48755257 | G9: Yes
B10: Amex - Business | C10: 4500
B11: Chase - Business | C11: 3754
B12: Nuvision | F12: =IF(C12>0,C12/SUM($C$8:$C$25), "")
B13: Chase Saphire | F13: =IF(C13>0,C13/SUM($C$8:$C$25), "")
B14: SoFi Loan
B15: Upstart
B16: Capital One - Platinum
B17: Chase Slate
B18: Amazon
B19: Capital One - Quicksilver
B20: Chase United
B21: Wells Fargo
B22: Discover
B23: Chase Freedom
B24: Nordstrom
B25: JCrew | F25: =IF(C25>0,C25/SUM($C$8:$C$25), "")
B26: Total | C26: =SUBTOTAL(109,LIABILITIES!$C$8:$C$25) -> 25401.63 | D26: =SUMPRODUCT(LIABILITIES!$C$8:$C$25,LIABILITIES!$D$8:$D$25)/SUM(LIABILITIES!$C$8:$C$25) -> 0.0082503367 | E26: =SUBTOTAL(109,LIABILITIES!$E$8:$E$25) -> 1000 | F26: =SUBTOTAL(109,LIABILITIES!$F$8:$F$24) -> 0.67506022
B28: Budgeted Amount
B29: Enter the amount you have available in your budget each month for debt repayment.
B30: This amount needs to be at greater or equal to the total required monthly payments above.
C32: Amount
B33: Repayment Budget | C33: 1800
B34: Payment Goal Q2 2021 | C34: =sum(C18,C19,C17,C21,C23,C15) -> 0
F35: =IF(C39>0, C39/SUM($C$8:$C$39), "")
B36: Totals & Summary
B37: A calculated summary of your total debts and what you have available to pay them back.
B38: If your extra repayments are negative, you're not making your minimum payments and need to re-budget!
C40: Amount
B41: Total Debt: | C41: =LIABILITIES!$C$26 -> 25401.63
B42: Total Credit Debt: | C42: =sum(C13,C18,C21) -> 0
B43: Total Personal Debt: | C43: =sum(0) -> 0 | E43: Expenses - Wgmi
B44: Total Loan Debt: | C44: =sum(C12,C8) -> 4763 | E44: Expenses - 0xMateo, EVM Labs
B45: Average Interest Rate: | C45: =LIABILITIES!$D$26 -> 0.0082503367 | E45: Expenses - EVM Fund
B46: Average Monthly Interest: | C46: =C41*C45/12 -> 17.464333
B48: Total Monthly Payments: | C48: =LIABILITIES!$E$26 -> 1000
B49: Amount Available: | C49: =LIABILITIES!$C$33 -> 1800
B51: Extra Repayments: | C51: =C49-C48 -> 800
B55: Repayment Strategies
B56: Pick your debt to repay. Either pay off the debt with the highest interest rate, or the one with the smallest balance.
B58: Highest Interest Rate First:
B60: Creditor | C60: Balance | D60: Interest Rate | E60: Monthly Payment | F60: New Payment
B61: {=INDEX(LIABILITIES!$B$8:$E$25, MATCH(MAX(LIABILITIES!$D$8:$D$25),LIABILITIES!$D$8:$D$25, 0), 1)} -> Nelnet | C61: {=INDEX(LIABILITIES!$B$8:$E$25, MATCH(MAX(LIABILITIES!$D$8:$D$25),LIABILITIES!$D$8:$D$25, 0), 2)} -> 4763 | D61: {=INDEX(LIABILITIES!$B$8:$E$25, MATCH(MAX(LIABILITIES!$D$8:$D$25),LIABILITIES!$D$8:$D$25, 0), 3)} -> 0.044 | E61: {=INDEX(LIABILITIES!$B$8:$E$25, MATCH(MAX(LIABILITIES!$D$8:$D$25),LIABILITIES!$D$8:$D$25, 0), 4)} -> 0 | F61: {=INDEX(LIABILITIES!$B$8:$E$25,MATCH(MAX(LIABILITIES!$D$8:$D$25),LIABILITIES!$D$8:$D$25,0),4)+$C$51} -> 800
B63: Lowest Balance First:
B65: Creditor | C65: Balance | D65: Interest Rate | E65: Monthly Payment | F65: New Payment
B66: {=INDEX(LIABILITIES!$B$8:$E$25, MATCH(MAX(LIABILITIES!$C$8:$C$25),LIABILITIES!$C$8:$C$25, 0), 1)} -> Parents | C66: {=INDEX(LIABILITIES!$B$8:$E$25, MATCH(MAX(LIABILITIES!$C$8:$C$25),LIABILITIES!$C$8:$C$25, 0), 2)} -> 12384.63 | D66: {=INDEX(LIABILITIES!$B$8:$E$25, MATCH(MAX(LIABILITIES!$C$8:$C$25),LIABILITIES!$C$8:$C$25, 0), 3)} -> 0 | E66: {=INDEX(LIABILITIES!$B$8:$E$25, MATCH(MAX(LIABILITIES!$C$8:$C$25),LIABILITIES!$C$8:$C$25, 0), 4)} -> 1000 | F66: {=INDEX(LIABILITIES!$B$8:$E$25, MATCH(MAX(LIABILITIES!$C$8:$C$25),LIABILITIES!$C$8:$C$25, 0), 4) + $C$51} -> 1800

Sheet PAYMENT SCHEDULE
A1: Payment Schedule
A2: Investments | B2: Status | C2: Monthly Payment | D2: Amount Owed | E2: Type | F2: Category | G2: Schedule | H2: Details
A3: PP1 (December 1st)
A4: Rent | B4: Paid | C4: 4700 | D4: N/A | E4: Automated | F4: Bill | G4: Week 1-2 | H4: 1st
A5: Utilities | B5: Scheduled | C5: 150 | D5: N/A | E5: Automated | F5: Bill | G5: Week 1-2 | H5: 1st
A6: Chase - Savings | B6: Paused | C6: 200 | D6: Paid in Full | E6: Automated | F6: Savings | G6: Week 1-2 | H6: 1st
A7: Chase Saphire | B7: Paid | C7: 3000 | D7: Paid in Full | E7: Manual | F7: Credit Card | G7: Week 1-2 | H7: 1st
A8: Amazon | B8: Scheduled | C8: 200 | D8: Paid in Full | E8: Manual | F8: Credit Card | G8: Week 1-2 | H8: 1st
A9: Nuvision | B9: Scheduled | C9: =200 -> 200 | D9: Paid in Full | E9: Manual | F9: Loan | G9: Week 1-2 | H9: 1st
A10: Great Lakes | B10: Scheduled | C10: =200 -> 200 | D10: Paid in Full | E10: Manual | F10: Loan | G10: Week 1-2 | H10: 1st
A11: SoFi Loan | B11: Paid | C11: =900 -> 900 | D11: Paid in Full | E11: Manual | F11: Loan | G11: Week 1-2 | H11: 1st
A12: Upstart | B12: Paid | C12: =500 -> 500 | D12: Paid in Full | E12: Manual | F12: Loan | G12: Week 1-2 | H12: 1st
A13: Credit Card | C13: =sumif($F$4:$F$12,"Credit Card",$C$4:$C$12) -> 3200
A14: Bills | C14: =sumif($F$4:$F$12,"Bill",$C$4:$C$12) -> 4850
A15: Investments | C15: =sumif($F$4:$F$12,"Investment",$C$4:$C$12) -> 0
A16: Loan | C16: =sumif($F$4:$F$12,"Loan",$C$4:$C$12) -> 1800
A17: Budget | C17: =sum(5500) -> 5500
A18: Total | C18: =sum(C4:C12) -> 10050
A19: Buffer | C19: =BUDGET!BU13-C18 -> 2050
A21: PP1 (Oct 15th)
A22: Upstart | B22: Scheduled | C22: =370 -> 370 | D22: =LIABILITIES!C15 | E22: Manual | F22: Loan | G22: Week 2-4 | H22: 15th
A23: Chase - Savings | B23: Scheduled | C23: 0 | E23: Automated | F23: Savings | G23: Week 1-2 | H23: 1st
A24: Chase Sapphire | B24: Scheduled | C24: 1500 | D24: =LIABILITIES!C13 | E24: Manual | F24: Credit Card | G24: Week 2-4 | H24: 15th
A25: SoFi Loan | B25: Scheduled | C25: 960 | D25: =LIABILITIES!C14 | E25: Manual | F25: Loan | G25: Week 1-2 | H25: 1st
A26: Credit Card Debt | C26: =sum(C24) -> 1500
A27: Bills
A28: Investments
A29: Gross Debt | C29: 0
A30: Total | C30: =sum(C22:C25) -> 2830
A31: Income | C31: =BUDGET!BR13/2 -> 31050
A32: Remainder | C32: =C31-C30 -> 28220
A38: Investment
A39: Mike Caroll | B39: Paused | C39: 5000 | D39: > Move to Mulstisig - Degen
A40: David Wright | B40: Paused | C40: =sum(16584,15000) -> 31584 | D40: > Move to EVM Cap Top Co
A41: Greg Ruggles | B41: Paused | C41: =sum(2500,2000) -> 4500 | D41: > Move to Mulstisig - Degen, or return 100% ROI
A42: Luis Valdivia | B42: Paused | C42: 13576 | D42: > Move to EVM Cap Top Co
A43: Faith | B43: Paused | C43: 7789 | D43: > Move to EVM Cap Top Co via Marcos? Or return capital on 200% return
A44: Ian Lee | B44: Paused | C44: 20000 | D44: > Move to EVM Cap Top Co
A46: Total | C46: =sum(C39:C45) -> 82449
A47: Buffer | C47: =100000-C46 -> 17551
E50: Payments this Month
E51: 4000 | F51: Soho House
E52: 5000 | F52: Nancy retainer
E56: =sum(E51:E52) -> 9000
D57: 16000 | E57: =D57-E56 -> 7000

Sheet HOLDINGS
A1: HOLDINGS
A2: Account | B2: Category | C2: Account | D2: Entity | E2: Quantity | F2: Principal ($) | G2: Current Value ($) | H2: % Portfolio | I2: 2025 Goal ($G) | J2: 2025 Goal (%G) | K2: % Return | L2: Memo
A3: Cash, Savings
A4: Premier Checking | C4: Chase Saphire Checking | D4: Personal | E4: N/A | F4: 0 | G4: 50 | H4: =IF(G4>0,G4/SUM($G$4:$G$6), "") -> 0.038461538 | I4: 10000
A5: Traditional Savings | C5: Chase Premier | D5: Personal | E5: N/A | F5: 0 | G5: 50 | H5: =IF(G5>0,G5/SUM($G$4:$G$6), "") -> 0.038461538 | I5: 30000
A6: High Yield Savings | C6: American Express | D6: Personal | E6: N/A | F6: 1200 | G6: =F6 -> 1200 | H6: =IF(G6>0,G6/SUM($G$4:$G$6), "") -> 0.92307692 | I6: 20000
F7: =SUM(F4:F6) -> 1200 | G7: =SUM(G4:G6) -> 1300 | H7: =SUBTOTAL(109,H$4:H$6) -> 1 | I7: =sum(I4:I6 ) -> 60000
A8: Private Equity
A9: EVM Capital | B9: Private | C9: - | D9: Matt Wright | E9: 0 | F9: =sum(50000,65000,10000,6000,70000,100000) -> 301000 | G9: =35000000*0.34 -> 11900000 | H9: =if(G9>0,G9/sum($G$9:$G$17),"") -> 0.97206291 | I9: =G9 -> 11900000
A10: Consensys | B10: Private | C10: - | D10: Matt Wright | E10: 10000 | F10: =E10*34 -> 340000 | G10: =F10 -> 340000 | H10: =if(G10>0,G10/sum($G$9:$G$17),"") -> 0.027773226 | I10: =G10 -> 340000
A11: Wgmi DAO | B11: Private | C11: - | D11: EVM Systems | E11: 34 | F11: =E11*100 -> 3400 | G11: 1 | H11: =if(G11>0,G11/sum($G$9:$G$17),"") -> 8.1685959e-08 | I11: 50000
A12: MetalithsDAO | B12: OTC | C12: - | D12: EVM Systems | E12: 0 | F12: 2000 | G12: 1 | H12: =if(G12>0,G12/sum($G$9:$G$17),"") -> 8.1685959e-08 | I12: 100000
A13: Jpegfund.eth | B13: Private | C13: - | D13: EVM Systems | E13: 0 | F13: =sum(10000,10000,5000,500) -> 25500 | G13: 2000 | H13: =if(G13>0,G13/sum($G$9:$G$17),"") -> 0.00016337192 | I13: 100000
A14: Relayer | B14: Private | C14: - | D14: Matt Trust | E14: 0 | F14: 10000 | G14: 1 | H14: =if(G14>0,G14/sum($G$9:$G$17),"") -> 8.1685959e-08 | I14: =F14*2.5 -> 25000
A15: Epoch | B15: Private | C15: - | D15: Matt Trust | E15: 0 | F15: 5000 | G15: 1 | H15: =if(G15>0,G15/sum($G$9:$G$17),"") -> 8.1685959e-08 | I15: =F15*2.5 -> 12500
A16: PADO | B16: Private | C16: - | D16: Matt Trust | E16: 0 | F16: 5000 | G16: 1 | H16: =if(G16>0,G16/sum($G$9:$G$17),"") -> 8.1685959e-08 | I16: =F16*2.5 -> 12500
A17: Noves | B17: Private | C17: - | D17: Matt Trust | E17: 0 | F17: 10000 | G17: 1 | H17: =if(G17>0,G17/sum($G$9:$G$17),"") -> 8.1685959e-08 | I17: =F17*2.5 -> 25000
F18: =sum(F9:F17 ) -> 701900 | G18: =sum(G9:G17 ) -> 12242006 | H18: =sum(H9:H17 ) -> 1 | I18: =sum(I9:I17 ) -> 12565000
A19: Crypto Assets (10%) | I19: =G19
A20: Gaia | G20: 1 | H20: =if(G20>0,G20/sum($G$20:$G$25),"") -> 0.16666667 | I20: 10000000
A21: BTC | G21: 1 | H21: =if(G21>0,G21/sum($G$20:$G$25),"") -> 0.16666667 | I21: 5000000
A22: Ethereum | G22: 1 | H22: =if(G22>0,G22/sum($G$20:$G$25),"") -> 0.16666667 | I22: 5000000
A23: DeFi | G23: 1 | H23: =if(G23>0,G23/sum($G$20:$G$25),"") -> 0.16666667 | I23: 500000
A24: Stabletokens | G24: 1 | H24: =if(G24>0,G24/sum($G$20:$G$25),"") -> 0.16666667 | I24: 500000
A25: Solana | G25: 1 | H25: =if(G25>0,G25/sum($G$20:$G$25),"") -> 0.16666667 | I25: 1000000
F26: 0 | G26: 0 | H26: =sum(H19:H25 ) -> 1 | I26: =sum(I20:I25 ) -> 22000000
A27: Stocks, Bonds, ETFS, CDs
A28: Etrade | I28: 10000
A29: Vanguard | I29: 10000
F30: =sum(F28:F29 ) -> 0 | G30: =sum(G28:G29 ) -> 0 | H30: =SUBTOTAL(109,H$28:H$29) -> 0 | I30: =sum(I28:I29 ) -> 20000
A31: Retirement Accts (5%)
A32: 401K | B32: IRA | C32: Vanguard | E32: 0 | F32: 1200 | G32: 1200 | H32: =IF(G32>0,G32/SUM($G$32:$G$33), "") -> 1 | I32: 20000
A33: Roth IRA | B33: IRA | C33: Vanguard | E33: 0 | F33: 0 | G33: 0 | H33: =IF(G33>0,G33/SUM($G$32:$G$33), "") | I33: 0
F34: =sum(F32:F33 ) -> 1200 | G34: =sum(G32:G33 ) -> 1200 | H34: =SUBTOTAL(109,H$32:H$33) -> 1 | I34: =sum(I32:I33 ) -> 20000
A35: Real Estate
A36: Home 01 | F36: 0 | G36: =F36 -> 0 | H36: =IF(G36>0,G36/SUM($G$4:$G$6), "") | I36: 2000000
F37: =sum(F35:F36 ) -> 0 | G37: =sum(G35:G36 ) -> 0 | H37: =SUBTOTAL(109,H$32:H$33) -> 1 | I37: =sum(I36 ) -> 2000000
A38: Loans Distributed
A39: Jean Lucas | C39: Transferwise | E39: N/A | F39: 1300 | G39: =1500-200 -> 1300 | H39: =if(G39>0,G39/sum($G$39:$G$41),"") -> 0.19302153 | I39: 0
A40: Mario Salazar | C40: Coinbase Wallet | F40: =sum(1025,2400,1500,6515,1500,2095)-10300 -> 4735 | G40: 4735 | H40: =if(G40>0,G40/sum($G$39:$G$41),"") -> 0.7030438 | I40: 0
A41: Ken Luster | F41: 700 | G41: =F41 -> 700 | H41: =if(G41>0,G41/sum($G$39:$G$41),"") -> 0.10393467 | I41: 0
F42: =sum(F39:F41 ) -> 6735 | G42: =sum(G39:G41 ) -> 6735 | H42: =SUBTOTAL(109,H39:H41) -> 1 | I42: =sum(I39:I41 ) -> 0
A44: Type | C44: Total Portfolio | D44: Total Principal | E44: Total Goal 2025 | F44: % of Portfolio
A45: =A3 -> Cash, Savings | C45: =G7 -> 1300 | D45: =F7 -> 1200 | E45: =I7 -> 60000 | F45: =IF(C45>0,C45/SUM($C$45:$C$51), "") -> 0.00010611167
A46: =A31 -> Retirement Accts (5%) | C46: =G34 -> 1200 | D46: =F34 -> 1200 | E46: =I34 -> 20000 | F46: =IF(C46>0,C46/SUM($C$45:$C$51), "") -> 9.7949237e-05
A47: =A19 -> Crypto Assets (10%) | C47: 1 | D47: 1 | E47: =I26 -> 22000000 | F47: =IF(C47>0,C47/SUM($C$45:$C$51), "") -> 8.1624364e-08
A48: =A27 -> Stocks, Bonds, ETFS, CDs | C48: 1 | D48: 1 | E48: =I30 -> 20000 | F48: =IF(C48>0,C48/SUM($C$45:$C$51), "") -> 8.1624364e-08
A49: =A35 -> Real Estate | C49: 1 | D49: 1 | E49: =I37 -> 2000000 | F49: =IF(C49>0,C49/SUM($C$45:$C$51), "") -> 8.1624364e-08
A50: =A8 -> Private Equity | C50: =G18 -> 12242006 | D50: =F18 -> 701900 | E50: =I18 -> 12565000 | F50: =IF(C50>0,C50/SUM($C$45:$C$51), "") -> 0.99924595
A51: =A38 -> Loans Distributed | C51: =G42 -> 6735 | D51: =F42 -> 6735 | E51: =I42 -> 0 | F51: =IF(C51>0,C51/SUM($C$45:$C$51), "") -> 0.00054974009
A52: Total | C52: =sum(C45:C51 ) -> 12251244 | D52: =sum(D45:D51 ) -> 711038 | E52: =sum(E45:E51 ) -> 36665000 | F52: =sum(F45:F51 ) -> 1

Sheet Copy of HOLDINGS
A1: HOLDINGS
A2: Account | B2: Category | C2: Account | D2: Quantity | E2: Principal ($) | F2: Current Value ($) | G2: % Portfolio | H2: % Return | I2: 2022 Goal ($ Growth) | J2: 2022 Goal (% Growth) | K2: Memo
A3: Cash, Savings
A4: Premier Checking | C4: Chase Saphire Checking | D4: N/A | E4: 5000 | F4: =E4 -> 5000 | G4: =IF(F4>0,F4/SUM($F$4:$F$6), "") -> 0.57110223
A5: Traditional | C5: Chase Premier | D5: N/A | E5: 2000 | F5: =E5 -> 2000 | G5: =IF(F5>0,F5/SUM($F$4:$F$6), "") -> 0.22844089
A6: High Yield | C6: American Express | D6: N/A | E6: 1755 | F6: =E6 -> 1755 | G6: =IF(F6>0,F6/SUM($F$4:$F$6), "") -> 0.20045688
E7: =SUM(E4:E6) -> 8755 | F7: =SUM(F4:F6) -> 8755 | G7: =SUBTOTAL(109,G$4:G$6) -> 1
A9: Crypto Assets (10%)
A10: BTC | B10: Token | C10: bc1qhy52h6z6fxqajt2zdh6tswg4k4safyfsaq3qlx | D10: 0.008 | E10: =D10*17000 -> 136 | F10: =D10*55000 -> 440 | G10: =IF(F10>0,F10/SUM($F$10:$F$54), "") -> 0.012285176 | I10: 0.1 | J10: =I10*1000000 -> 100000
A11: ETH | B11: Token | C11: 0x54CC0802aa8bAB73b21b897f96b37AfF16239EeA | D11: 3.714 | E11: =D11*1900 -> 7056.6 | F11: =D11*1975 -> 7335.15 | G11: =IF(F11>0,F11/SUM($F$10:$F$54), "") -> 0.20480366 | I11: 50 | J11: =I11*5000 -> 250000
A12: WETH | B12: Token | C12: 0x54CC0802aa8bAB73b21b897f96b37AfF16239EeA | D12: 0.011 | E12: 0 | F12: =D12*1800 -> 19.8 | G12: =IF(F12>0,F12/SUM($F$10:$F$54), "") -> 0.00055283292 | I12: 20 | J12: =I12*5000 -> 100000
A13: DAI | B13: Token | C13: 0x54CC0802aa8bAB73b21b897f96b37AfF16239EeA | D13: 11 | E13: 0 | F13: =D13*1 -> 11 | G13: =IF(F13>0,F13/SUM($F$10:$F$54), "") -> 0.0003071294 | I13: 1000 | J13: =I13*1 -> 1000
A14: 1Inch | B14: Token | C14: 0x54CC0802aa8bAB73b21b897f96b37AfF16239EeA | D14: 150 | E14: 0 | F14: =D14*5.04 -> 756 | G14: =IF(F14>0,F14/SUM($F$10:$F$54), "") -> 0.021108166 | I14: 150 | J14: =I14*10 -> 1500
A15: POOL | B15: Token | C15: 0x54CC0802aa8bAB73b21b897f96b37AfF16239EeA | D15: 126.2 | E15: =D15*19 -> 2397.8 | F15: =D15*22 -> 2776.4 | G15: =IF(F15>0,F15/SUM($F$10:$F$54), "") -> 0.07751946 | I15: 126 | J15: =I15*30 -> 3780
A16: UNI | B16: Token | C16: 0x54CC0802aa8bAB73b21b897f96b37AfF16239EeA | D16: 10 | E16: =D16*19.78 -> 197.8 | F16: =D16*40 -> 400 | G16: =IF(F16>0,F16/SUM($F$10:$F$54), "") -> 0.011168342 | I16: 500 | J16: =I16*50 -> 25000
A17: Sushi | B17: Token | C17: 0x54CC0802aa8bAB73b21b897f96b37AfF16239EeA | D17: 39.96 | E17: 300 | F17: =D17*13.52 -> 540.2592 | G17: =IF(F17>0,F17/SUM($F$10:$F$54), "") -> 0.015084498 | I17: 100 | J17: =I17*20 -> 2000
A18: DPI | B18: Token | C18: 0x54CC0802aa8bAB73b21b897f96b37AfF16239EeA | D18: 9.32 | E18: =D18*450 -> 4194 | F18: =D18*510 -> 4753.2 | G18: =IF(F18>0,F18/SUM($F$10:$F$54), "") -> 0.13271341 | I18: 10 | J18: =I18*800 -> 8000
A19: YFI | B19: Reward Token | C19: 0x54CC0802aa8bAB73b21b897f96b37AfF16239EeA | D19: 0.0022640416 | E19: 80 | F19: =D19*40936 -> 92.680805 | G19: =IF(F19>0,F19/SUM($F$10:$F$54), "") -> 0.0025877273 | I19: 3
A20: SNX | B20: Reward Token | C20: 0x54CC0802aa8bAB73b21b897f96b37AfF16239EeA | D20: 16 | E20: 80 | F20: =D20*26 -> 416 | G20: =IF(F20>0,F20/SUM($F$10:$F$54), "") -> 0.011615075 | I20: 50 | J20: =I20*30 -> 1500
A21: FARM | B21: Reward Token | C21: 0x54CC0802aa8bAB73b21b897f96b37AfF16239EeA | D21: 1.106 | E21: 300 | F21: =D21*150 -> 165.9 | G21: =IF(F21>0,F21/SUM($F$10:$F$54), "") -> 0.0046320698 | I21: 10 | J21: =I21*300 -> 3000
A22: COMP | B22: Reward Token | C22: 0x54CC0802aa8bAB73b21b897f96b37AfF16239EeA | D22: 0 | E22: 0.008 | F22: =E22*743 -> 5.944 | G22: =IF(F22>0,F22/SUM($F$10:$F$54), "") -> 0.00016596156 | I22: 5
A23: Cream | B23: Reward Token | C23: 0x54CC0802aa8bAB73b21b897f96b37AfF16239EeA | D23: 0.79503945 | E23: 145 | F23: =D23*211 -> 167.75332 | G23: =IF(F23>0,F23/SUM($F$10:$F$54), "") -> 0.0046838162 | I23: 5
A24: GHST | B24: Token | C24: 0x54CC0802aa8bAB73b21b897f96b37AfF16239EeA | D24: 108 | E24: 44.85 | F24: =D24*0.69 -> 74.52 | G24: =IF(F24>0,F24/SUM($F$10:$F$54), "") -> 0.0020806621 | I24: 0
A25: STAKE | B25: Token | C25: 0x54CC0802aa8bAB73b21b897f96b37AfF16239EeA | D25: 2 | E25: =43.62 -> 43.62 | F25: 0 | G25: =IF(F25>0,F25/SUM($F$10:$F$54), "") | I25: 0
A26: YAM | B26: Token | C26: 0x54CC0802aa8bAB73b21b897f96b37AfF16239EeA | D26: 4.976 | E26: 20 | F26: =D26*5.77 -> 28.71152 | G26: =IF(F26>0,F26/SUM($F$10:$F$54), "") -> 0.00080165017 | I26: 0
A27: InstaDApp | B27: Token | C27: 0x54CC0802aa8bAB73b21b897f96b37AfF16239EeA | D27: N/A | E27: 50 | F27: 0 | G27: =IF(F27>0,F27/SUM($F$10:$F$54), "") | I27: 0
A28: Uniswap UNI/ETH Pool | B28: Liquidity Pool | C28: 0x54CC0802aa8bAB73b21b897f96b37AfF16239EeA | D28: 0.718 | E28: 100 | F28: =D28*759 -> 544.962 | G28: =IF(F28>0,F28/SUM($F$10:$F$54), "") -> 0.015215805 | I28: 2 | J28: =I28*1559 -> 3118
A29: Sushi WBTC/WETH Pool | B29: Liquidity Pool | C29: 0x54CC0802aa8bAB73b21b897f96b37AfF16239EeA | D29: 5.8e-09 | E29: 175 | F29: =D29*44054474896.37 -> 255.51595 | G29: =IF(F29>0,F29/SUM($F$10:$F$54), "") -> 0.0071342238 | I29: 2 | J29: =0.0000000058*44054474896.37 -> 255.51595
A30: UNIv2 | B30: Liquidity Pool | C30: 0x54CC0802aa8bAB73b21b897f96b37AfF16239EeA | D30: 0 | E30: =358 -> 358 | F30: 0 | G30: =IF(F30>0,F30/SUM($F$10:$F$54), "") | I30: 2
A31: pDAI | B31: Lending | C31: 0x54CC0802aa8bAB73b21b897f96b37AfF16239EeA | D31: 17 | E31: 17 | F31: 17 | G31: =IF(F31>0,F31/SUM($F$10:$F$54), "") -> 0.00047465453 | I31: 17
A32: sUSD | B32: Lending | C32: 0x54CC0802aa8bAB73b21b897f96b37AfF16239EeA | D32: 12.6 | E32: 10 | F32: =D32*1.01 -> 12.726 | G32: =IF(F32>0,F32/SUM($F$10:$F$54), "") -> 0.00035532079 | I32: 200 | J32: =I32*1 -> 200
A33: aDAI | B33: Lending | C33: 0x54CC0802aa8bAB73b21b897f96b37AfF16239EeA | D33: 1 | E33: 100 | F33: 102 | G33: =IF(F33>0,F33/SUM($F$10:$F$54), "") -> 0.0028479272 | I33: 2000 | J33: =I33*1 -> 2000
A34: cDAI | B34: Lending | C34: 0x54CC0802aa8bAB73b21b897f96b37AfF16239EeA | D34: 1766 | E34: 36.94 | F34: 0 | G34: =IF(F34>0,F34/SUM($F$10:$F$54), "") | I34: 1000 | J34: =I34*1 -> 1000
A35: dYdX | B35: Synthetics | C35: 0x54CC0802aa8bAB73b21b897f96b37AfF16239EeA | D35: N/A | E35: 116 | F35: 0 | G35: =IF(F35>0,F35/SUM($F$10:$F$54), "") | I35: 500
A36: Wgmi | B36: DAO | G36: =IF(F36>0,F36/SUM($F$10:$F$54), "")
A37: Bankless | B37: DAO | G37: =IF(F37>0,F37/SUM($F$10:$F$54), "")
A38: Forefront | B38: DAO | G38: =IF(F38>0,F38/SUM($F$10:$F$54), "")
A39: Seed Club | B39: DAO | G39: =IF(F39>0,F39/SUM($F$10:$F$54), "")
A40: FWB | B40: DAO | G40: =IF(F40>0,F40/SUM($F$10:$F$54), "")
A41: Metacartel | B41: DAO | G41: =IF(F41>0,F41/SUM($F$10:$F$54), "")
A42: ConsenSys DAO | B42: DAO | G42: =IF(F42>0,F42/SUM($F$10:$F$54), "")
A43: Jpegfund.eth | B43: DAO | E43: =sum(5000,500) -> 5500 | G43: =IF(F43>0,F43/SUM($F$10:$F$54), "")
A44: Decentraland | B44: Metaverse | G44: =IF(F44>0,F44/SUM($F$10:$F$54), "")
A45: Decentraland | B45: Metaverse | G45: =IF(F45>0,F45/SUM($F$10:$F$54), "")
A46: CoolCats | B46: NFT | D46: 0 | E46: 0 | F46: 0 | G46: =IF(F46>0,F46/SUM($F$10:$F$54), "")
A47: Art Blocks | B47: NFT | D47: 2 | E47: 3000 | F47: =E47*2 -> 6000 | G47: =IF(F47>0,F47/SUM($F$10:$F$54), "") -> 0.16752513
A48: Mooncat Rescue | B48: NFT | D48: 2 | E48: 1000 | F48: =E48 -> 1000 | G48: =IF(F48>0,F48/SUM($F$10:$F$54), "") -> 0.027920854
A49: Pixel Portraits | B49: NFT | D49: 2 | E49: 1200 | F49: =E49 -> 1200 | G49: =IF(F49>0,F49/SUM($F$10:$F$54), "") -> 0.033505025
A50: Metaliths | B50: NFT | D50: 3 | E50: =8000 -> 8000 | F50: =E50 -> 8000 | G50: =IF(F50>0,F50/SUM($F$10:$F$54), "") -> 0.22336684
A51: Bored Apes | B51: NFT | D51: 0 | E51: 0 | F51: 0 | G51: =IF(F51>0,F51/SUM($F$10:$F$54), "")
A52: CryptoPunks | B52: NFT | D52: 0 | E52: 0 | F52: 0 | G52: =IF(F52>0,F52/SUM($F$10:$F$54), "")
A53: Unfamiliar Faces | B53: NFT | D53: 1 | E53: 300 | F53: =E53 -> 300 | G53: =IF(F53>0,F53/SUM($F$10:$F$54), "") -> 0.0083762563
A54: Strawberry.wtf | B54: NFT | D54: 1 | E54: 400 | F54: =E54 -> 400 | G54: =IF(F54>0,F54/SUM($F$10:$F$54), "") -> 0.011168342
E55: 0 | F55: 0 | G55: =sum(G10:G54 ) -> 1 | I55: =sum(I10:I54 ) -> 5752.1 | J55: =sum(J10:J54 ) -> 502353.52
A57: Stocks, Bonds
A58: Airbnb | B58: Equity | C58: ETrade | D58: 1 | E58: =9*D58 -> 9 | F58: =D58*97.67 -> 97.67 | G58: =if(F58>0,F58/sum($F$58:$F$73),"") -> 0.52358743
A59: Uber (UBER) | B59: Equity | C59: ETrade | D59: 1 | E59: 0 | F59: =D59*28.5 -> 28.5 | G59: =if(F59>0,F59/sum($F$58:$F$73),"") -> 0.15278225
A60: UpWork (UPWK) | B60: Equity | C60: ETrade | D60: 3 | E60: =9*D60 -> 27 | F60: =D60*11.79 -> 35.37 | G60: =if(F60>0,F60/sum($F$58:$F$73),"") -> 0.18961081
A61: Coinbase (Coin) | B61: Equity | C61: ETrade | D61: 0 | E61: =D61*330 -> 0 | F61: =D61*196 -> 0 | G61: =if(F61>0,F61/sum($F$58:$F$73),"")
A62: Slack (WORK) | B62: Equity | C62: ETrade | D62: 0 | E62: 0 | F62: =D62*43.69 -> 0 | G62: =if(F62>0,F62/sum($F$58:$F$73),"")
A63: Blackberry (BB) | B63: Equity | C63: ETrade | D63: 0 | E63: =D63*13.04 -> 0 | F63: =$D$63*13.04 -> 0 | G63: =if(F63>0,F63/sum($F$58:$F$73),"")
A64: Roku (ROKU) | B64: Equity | C64: ETrade | D64: 0 | E64: 0 | F64: =D64*469.5 -> 0 | G64: =if(F64>0,F64/sum($F$58:$F$73),"")
A65: Square (SQ) | B65: Equity | C65: ETrade | D65: 0 | E65: 0 | F65: =D65*272.97 -> 0 | G65: =if(F65>0,F65/sum($F$58:$F$73),"")
A66: Paypal (PYPL) | B66: Equity | C66: ETrade | D66: 0 | E66: 0 | F66: 25 | G66: =if(F66>0,F66/sum($F$58:$F$73),"") -> 0.13401951
A67: AMC (AMC) | B67: Equity | C67: ETrade | D67: 0 | E67: 80 | F67: =D67 -> 0 | G67: =if(F67>0,F67/sum($F$58:$F$73),"")
A68: Nokia (NOK) | B68: Equity | C68: ETrade | D68: 0 | E68: 20 | F68: =D68*4.18 -> 0 | G68: =if(F68>0,F68/sum($F$58:$F$73),"")
A69: Tesla (TSL) | B69: Equity | C69: ETrade | D69: 0 | E69: 0 | F69: 0 | G69: =if(F69>0,F69/sum($F$58:$F$73),"")
A70: Zoom (ZM) | B70: Equity | C70: ETrade | D70: 0 | E70: 0 | F70: 0 | G70: =if(F70>0,F70/sum($F$58:$F$73),"")
A71: Twitter (TWTR) | B71: Equity | C71: ETrade | D71: 0 | E71: 0 | F71: 0 | G71: =if(F71>0,F71/sum($F$58:$F$73),"")
A72: TMobile (TMUS) | B72: Equity | C72: ETrade | D72: 0 | E72: 0 | F72: 0 | G72: =if(F72>0,F72/sum($F$58:$F$73),"")
A73: $Cash | B73: Equity | C73: Etrade | D73: 0 | E73: 0 | F73: 0 | G73: =if(F73>0,F73/sum($F$58:$F$73),"")
A74: 3M (MMM) | C74: ETrade | D74: 0 | E74: 0 | F74: 0 | G74: =IF(F74>0,F74/SUM($F$60:$F$80), "") | I74: 0 | J74: =I74*2 -> 0
A75: Mongo DB (MDB) | C75: ETrade | D75: 0 | E75: 0 | F75: 0 | G75: =IF(F75>0,F75/SUM($F$60:$F$80), "") | I75: 0 | J75: =I75*2 -> 0
A76: Pfizer (PFE) | C76: ETrade | D76: 0 | E76: 0 | F76: 0 | G76: =IF(F76>0,F76/SUM($F$60:$F$80), "") | I76: 0 | J76: =I76*2 -> 0
A77: Coca Cola (KO) | C77: ETrade | D77: 0 | E77: 0 | F77: 0 | G77: =IF(F77>0,F77/SUM($F$60:$F$80), "") | I77: 0 | J77: =I77*2 -> 0
A78: Apple (APPL) | C78: ETrade | D78: 0 | E78: 0 | F78: 0 | G78: =IF(F78>0,F78/SUM($F$60:$F$80), "") | I78: 0 | J78: =I78*2 -> 0
A79: Splunk (SPLK) | C79: ETrade | D79: 0 | E79: 0 | F79: 0 | G79: =IF(F79>0,F79/SUM($F$60:$F$80), "") | I79: 0 | J79: =I79*2 -> 0
A80: United Healthcare (UNH) | C80: ETrade | D80: 0 | E80: 0 | F80: 0 | G80: =IF(F80>0,F80/SUM($F$60:$F$80), "") | I80: 0 | J80: =I80*2 -> 0
E81: =sum(E58:E73 ) -> 136 | F81: =sum(F58:F73 ) -> 186.54 | G81: =SUBTOTAL(109,G$58:G$80) -> 1
A83: Bonds, ETFs, CDs
F84: 0 | G84: =IF(F84>0,F84/SUM($F$84), "")
E85: =sum(E84 ) -> 0 | F85: =sum(F84 ) -> 0 | G85: =SUBTOTAL(109,G$84) -> 0
A87: Precious Metals
A88: Gold | C88: Vault | F88: 0 | G88: =IF(F88>0,F88/SUM($F$89), "")
A89: Silver | C89: Vault | F89: 0 | G89: =IF(F89>0,F89/SUM($F$89), "")
E90: =sum(E88:E89 ) -> 0 | F90: =sum(F88:F89 ) -> 0 | G90: =SUBTOTAL(109,G$88:G$89) -> 0
A92: Private Equity
A93: EVM Fund (EVM Cap Mgmt) | C93: Private | D93: N/A | E93: =sum(50000,65000,10000,6000,70000,100000) -> 301000 | F93: =E93 -> 301000 | G93: =if(F93>0,F93/sum($F$93:$F$99),"") -> 0.44825152
A94: 0xCapitalMgmt | C94: Private | D94: N/A
A95: ConsenSys | C95: Private | D95: 10000 | E95: =D95*34 -> 340000 | F95: =E95 -> 340000 | G95: =if(F95>0,F95/sum($F$93:$F$99),"") -> 0.50633062
A96: DoceLabs (EVM Labs) | C96: Private | D96: 1000000 | E96: 1598 | F96: =E96 -> 1598 | G96: =if(F96>0,F96/sum($F$93:$F$99),"") -> 0.0023797539
A97: Wgmi DAO | C97: Private | D97: 34 | E97: =D97*100 -> 3400 | F97: =E97 -> 3400 | G97: =if(F97>0,F97/sum($F$93:$F$99),"") -> 0.0050633062
A98: MetalithsDAO | C98: OTC | G98: =IF(F98>0,F98/SUM($F$10:$F$54), "")
A99: Jpegfund.eth | C99: Private | D99: N/A | E99: =sum(10000,10000,5000,500) -> 25500 | F99: =E99 -> 25500 | G99: =if(F99>0,F99/sum($F$93:$F$99),"") -> 0.037974797
A100: JokeDAO | C100: Private | E100: 1000
A101: Venture Club | C101: Private | E101: 1000
E102: =sum(E93:E101 ) -> 673498 | F102: =sum(F93:F101 ) -> 671498 | G102: =SUBTOTAL(109,G93:G99) -> 1
A104: Retirement Accts (5%)
A105: 401K | B105: IRA | C105: Vanguard | D105: 0 | E105: 1200 | F105: 1200 | G105: =IF(F105>0,F105/SUM($F$105:$F$106), "") -> 1 | I105: 10000 | J105: =I105*2 -> 20000
A106: Roth IRA | B106: IRA | C106: Vanguard | D106: 0 | E106: 0 | F106: 0 | G106: =IF(F106>0,F106/SUM($F$105:$F$106), "") | I106: 5000 | J106: 0
...

Sheet Uniquity BUDGET-2023
A1: Categories | C1: Jan | D1: Feb | E1: Mar | F1: Apr | G1: May | H1: Jun | I1: Jul '19 | J1: Aug '19 | K1: Sept '19 | L1: Oct '19 | M1: Nov '19 | N1: Dec '19 | O1: Jan '20 | P1: Feb '20 | Q1: Mar '20 | R1: Apr '20 | S1: May '20 | T1: Jun '20 | U1: Jul '20 | V1: Aug '20 | W1: Sep '20 | X1: Oct '20 | Y1: Nov '20 | Z1: Dec '20 | AA1: Jan '21 | AB1: Feb'21 | AC1: Mar '21 | AD1: Apr '21 | AE1: May '21 | AF1: Jun '21 | AG1: Jul '21 | AH1: Aug '21 | AI1: Sept '21 | AJ1: Oct '21 | AK1: Nov '21 | AL1: Dec '21 | AM1: Jan '22 | AN1: Feb '22 | AO1: Mar '22 | AP1: Apr '22 | AQ1: May '22 | AR1: Jun '22 | AS1: July '22 | AT1: Aug '22 | AU1: Sept '22 | AV1: Oct '22 | AW1: Nov '22 | AX1: Dec '22 | AY1: Jan '23 | AZ1: Feb '23 | BA1: Mar '23 | BB1: Apr '23 | BC1: May '23 | BD1: Jun '23 | BE1: Jul '23 | BF1: Aug '23 | BG1: Sept '23 | BH1: Oct '23 | BI1: Nov '23 | BJ1: Dec '23 | BK1: FY 2023 | BL1: Jan '24 | BM1: Feb '24 | BN1: Mar '24 | BO1: Apr '24 | BP1: May '24 | BQ1: Jun '24 | BR1: Jul '24 | BS1: Aug '24 | BT1: Sep '24 | BU1: Oct '24 | BV1: Nov '24 | BW1: Dec '24
A2: Income
A3: Salary
B4: Salary (Pre-Tax of 34%) | C4: 10000 | D4: 10000 | E4: 10000 | F4: 10000 | G4: 10000 | H4: 10000 | I4: 10000 | J4: =120000/12 -> 10000 | K4: =120000/12 -> 10000 | L4: =120000/12 -> 10000 | M4: =120000/12 -> 10000 | N4: =120000/12 -> 10000 | O4: =120000/12 -> 10000 | P4: =120000/12 -> 10000 | Q4: =123000/12 -> 10250 | R4: =123000/12 -> 10250 | S4: =123000/12 -> 10250 | T4: =123000/12 -> 10250 | U4: =123000/12 -> 10250 | V4: =123000/12 -> 10250 | W4: =123000/12 -> 10250 | X4: =123000/12 -> 10250 | Y4: =123000/12 -> 10250 | Z4: =160000/12 -> 13333.333 | AA4: =160000/12 -> 13333.333 | AB4: =160000/12 -> 13333.333 | AC4: =160000/12 -> 13333.333 | AD4: =160000/12 -> 13333.333 | AE4: =160000/12 -> 13333.333 | AF4: =160000/12 -> 13333.333 | AG4: =160000/12 -> 13333.333 | ... AJ4: =160000/12 -> 13333.333 | AK4: =165000/12 -> 13750 | AL4: =210000/12 -> 17500 | AM4: =210000/12 -> 17500 | AN4: =210000/12 -> 17500 | AO4: =210000/12 -> 17500 | AP4: =210000/12 -> 17500 | AQ4: =210000/12 -> 17500 | AR4: =210000/12 -> 17500 | AS4: =210000/12 -> 17500 | ... AZ4: =210000/12 -> 17500 | BA4: =200000/12 -> 16666.667 | BB4: =200000/12 -> 16666.667 | BC4: =200000/12 -> 16666.667 | BD4: =200000/12 -> 16666.667 | BE4: =200000/12 -> 16666.667 | BF4: =220000/12 -> 18333.333 | BG4: =220000/12 -> 18333.333 | BH4: =220000/12 -> 18333.333 | BI4: =220000/12 -> 18333.333 | BJ4: =220000/12 -> 18333.333 | BL4: =220000/12 -> 18333.333 | BM4: =220000/12 -> 18333.333 | BN4: =220000/12 -> 18333.333 | BO4: =220000/12 -> 18333.333 | BP4: =200000/12 -> 16666.667 | BQ4: =220000/12 -> 18333.333 | BR4: =220000/12 -> 18333.333 | BS4: =220000/12 -> 18333.333 | BT4: =220000/12 -> 18333.333 | BU4: =220000/12 -> 18333.333 | BV4: =220000/12 -> 18333.333 | BW4: =220000/12 -> 18333.333
B5: Freelance (Taxed at 41%) | C5: 0 | D5: 3000 | E5: 0 | F5: 0 | G5: 0 | H5: 0 | I5: 5000 | J5: 5000 | K5: 0 | L5: 0 | M5: 800 | N5: =500 -> 500 | O5: 0 | P5: =5000 -> 5000 | Q5: 0 | R5: 0 | S5: 0 | T5: 0 | U5: 0 | V5: 0 | W5: 0 | X5: 0 | Y5: 0 | Z5: 0 | AA5: 0 | AB5: 0 | AC5: 0 | AD5: 0 | AE5: 0 | AF5: 0 | AG5: 0 | AH5: 0 | AI5: 0 | AJ5: 0 | AK5: 0 | AL5: 0 | AM5: 0 | AN5: 0 | AO5: 0 | AP5: 0 | AQ5: 0 | AR5: 0 | AS5: 0 | AT5: 0 | AU5: 0 | AV5: 0 | AW5: 0 | AX5: 0 | AY5: 0 | AZ5: 0 | BA5: 0 | BB5: 0 | BC5: 0 | BD5: 0 | BE5: 0 | BF5: 0 | BG5: 0 | BH5: 0 | BI5: 0 | BJ5: 0 | BL5: 0 | BM5: 0 | BN5: 12000 | BO5: 12000 | BP5: 12000 | BQ5: 12000 | BR5: 12000 | BS5: 12000 | BT5: 10000 | BU5: 10000 | BV5: 10000 | BW5: 10000
A6: Freelance
B7: Secondary Income (Taxed @ 34%) | C7: 0 | D7: 0 | E7: 0 | F7: 0 | G7: 0 | H7: 0 | I7: 0 | J7: 0 | K7: 0 | L7: 0 | M7: 0 | N7: 0 | O7: 0 | P7: 0 | Q7: 0 | R7: 0 | S7: 0 | T7: =S7+S7*0.15 -> 0 | U7: =T7+T7*0.15 -> 0 | V7: =U7+U7*0.15 -> 0 | W7: =V7+V7*0.15 -> 0 | X7: 0 | Y7: 0 | Z7: =Y7+Y7*0.1 -> 0 | AA7: =Z7+Z7*0.1 -> 0 | AB7: =AA7+AA7*0.1 -> 0 | AC7: =AB7+AB7*0.1 -> 0 | AD7: =AC7+AC7*0.1 -> 0 | AE7: =AD7+AD7*0.1 -> 0 | AF7: =AE7+AE7*0.1 -> 0 | AG7: =AF7+AF7*0.1 -> 0 | AH7: =AG7+AG7*0.1 -> 0 | AI7: =AG7+AG7*0.1 -> 0 | AJ7: =AH7+AH7*0.1 -> 0 | AK7: =AJ7+AJ7*0.1 -> 0 | AL7: =AK7+AK7*0.1 -> 0 | AM7: =AL7+AL7*0.1 -> 0 | AN7: =AM7+AM7*0.1 -> 0 | AO7: =AN7+AN7*0.1 -> 0 | AP7: =AO7+AO7*0.1 -> 0 | AQ7: =AP7+AP7*0.1 -> 0 | AR7: =AQ7+AQ7*0.1 -> 0 | ... AT7: =AS7+AS7*0.1 -> 0 | AU7: 0 | AV7: 0 | AW7: 0 | AX7: 0 | AY7: 0 | AZ7: 0 | BA7: 0 | BB7: 0 | BC7: 0 | BD7: 0 | BE7: 0 | BF7: 60000 | BG7: 0 | BH7: 0 | BI7: 0 | BJ7: 0 | BL7: 0 | BM7: 0 | BN7: 0 | BO7: 0 | BP7: 0 | BQ7: 0 | BR7: 0 | BS7: 0 | BT7: 0 | BU7: 0 | BV7: 0 | BW7: 0
B8: Non-taxed Income | O8: =1000 -> 1000 | P8: =2723 -> 2723 | Q8: 419 | R8: =200 -> 200 | S8: =900+2500 -> 3400 | T8: 0 | U8: 0 | V8: 300 | W8: 0 | X8: 0 | Y8: 5600 | Z8: 0 | AA8: 0 | AB8: 0 | AC8: 700 | AD8: 0 | AE8: 11000 | AF8: 1300 | AG8: =sum(1200,1200) -> 2400 | AH8: =sum(7000,10000) -> 17000 | AI8: 0 | AJ8: 0 | AK8: =2000+7700 -> 9700 | AL8: 0 | AM8: 0 | AN8: 10000 | AO8: 1000 | AP8: 21000 | AQ8: 0 | AR8: 0 | AS8: 0 | AT8: =sum(4751.11) -> 4751.11 | AU8: =36000*0.45 -> 16200 | AV8: 0 | AW8: 0 | AX8: =SUM(1500,1844) -> 3344 | AY8: =sum(1000,1800) -> 2800 | AZ8: 16000 | BA8: 20000 | BB8: 0 | BC8: 2500 | BD8: 0 | BE8: 0 | BF8: =sum(-2000,-3000,-1200) -> -6200 | BG8: =sum(5000,2000) -> 7000 | BH8: =sum(12000,10000,1000) -> 23000 | BI8: =sum(250000) -> 250000 | BJ8: 0 | BL8: 0 | BM8: 0 | BN8: 0 | BO8: 0 | BP8: 0 | BQ8: 0 | BR8: 0 | BS8: 0 | BT8: 0 | BU8: 0 | BV8: 0 | BW8: 0
A10: Total Income | C10: =sum(C4:C7) -> 10000 | D10: =sum(D4:D7) -> 13000 | E10: =sum(E4:E7) -> 10000 | F10: =sum(F4:F7) -> 10000 | G10: =sum(G4:G7) -> 10000 | H10: =sum(H4:H7) -> 10000 | I10: =sum(I4:I7) -> 15000 | J10: =sum(J4:J7) -> 15000 | ... O10: =sum(O4:O7) -> 10000 | P10: =sum(P4:P8) -> 17723 | Q10: =sum(Q4:Q8) -> 10669 | R10: =sum(R4:R8) -> 10450 | S10: =sum(S4:S8) -> 13650 | T10: =sum(T4:T8) -> 10250 | U10: =sum(U4:U8) -> 10250 | V10: =sum(V4:V8) -> 10550 | W10: =sum(W4:W8) -> 10250 | ... BJ10: =sum(BJ4:BJ8) -> 18333.333 | BL10: =sum(BL4:BL8) -> 18333.333 | BM10: =sum(BM4:BM8) -> 18333.333 | BN10: =sum(BN4:BN8) -> 30333.333 | BO10: =sum(BO4:BO8) -> 30333.333 | BP10: =sum(BP4:BP8) -> 28666.667 | BQ10: =sum(BQ4:BQ8) -> 30333.333 | BR10: =sum(BR4:BR8) -> 30333.333 | BS10: =sum(BS4:BS8) -> 30333.333 | ... BW10: =sum(BW4:BW8) -> 28333.333
A11: Tax + Withholding | C11: =C10*0.38 -> 3800 | D11: =D10*0.34 -> 4420 | E11: =E10*0.34 -> 3400 | F11: =F10*0.34 -> 3400 | G11: =G10*0.34 -> 3400 | H11: =H10*0.34 -> 3400 | I11: =I10*0.34 -> 5100 | J11: =J10*0.34 -> 5100 | K11: =K10*0.34 -> 3400 | L11: =L10*0.34 -> 3400 | M11: =sum(M4:M7)*0.34 -> 3672 | N11: =sum(N4:N7)*0.34 -> 3570 | O11: =sum(O4:O7)*0.34+O5*0.41 -> 3400 | P11: =P4*0.34+P5*0.41+P7*0.34 -> 5450 | Q11: =sum(Q4:Q7)*0.34+Q5*0.41 -> 3485 | R11: =sum(R4:R7)*0.34+R5*0.41 -> 3485 | S11: =sum(S4:S7)*0.34+S5*0.41 -> 3485 | T11: =sum(T4:T7)*0.34+T5*0.41 -> 3485 | U11: =sum(U4:U7)*0.34+U5*0.41 -> 3485 | V11: =sum(V4:V7)*0.34+V5*0.41 -> 3485 | W11: =sum(W4:W7)*0.34+W5*0.41 -> 3485 | X11: =sum(X4:X7)*0.34+X5*0.41 -> 3485 | ... BE11: =sum(BE4:BE7)*0.34+BE5*0.41 -> 5666.6667 | BF11: =sum(BF4:BF7)*0.34+BF5*0.52 -> 26633.333 | BG11: =sum(BG4:BG7)*0.34+BG5*0.41 -> 6233.3333 | BH11: =sum(BH4:BH7)*0.34+BH5*0.41 -> 6233.3333 | BI11: =sum(BI4:BI7)*0.34+BI5*0.41 -> 6233.3333 | BJ11: =sum(BJ4:BJ7)*0.34+BJ5*0.41 -> 6233.3333 | BL11: =sum(BL4:BL7)*0.34+BL5*0.41 -> 6233.3333 | BM11: =sum(BM4:BM7)*0.34+BM5*0.41 -> 6233.3333 | BN11: =sum(BN4:BN7)*0.34+BN5*0.41 -> 15233.333 | BO11: =sum(BO4:BO7)*0.34+BO5*0.41 -> 15233.333 | BP11: =sum(BP4:BP7)*0.34+BP5*0.41 -> 14666.667 | BQ11: =sum(BQ4:BQ7)*0.34+BQ5*0.41 -> 15233.333 | BR11: =sum(BR4:BR7)*0.34+BR5*0.41 -> 15233.333 | BS11: =sum(BS4:BS7)*0.34+BS5*0.41 -> 15233.333 | ... BW11: =sum(BW4:BW7)*0.34+BW5*0.41 -> 13733.333
A12: 401k Contribution | O12: =O4*0.04 -> 400 | P12: =P4*0.04 -> 400 | Q12: =Q4*0.03 -> 307.5 | R12: =R4*0.03 -> 307.5 | S12: =S4*0.03 -> 307.5 | T12: =T4*0.03 -> 307.5 | U12: =U4*0.03 -> 307.5 | V12: =V4*0.03 -> 307.5 | W12: =W4*0.03 -> 307.5 | X12: =X4*0.03 -> 307.5 | Y12: =Y4*0.03 -> 307.5 | Z12: =Z4*0 -> 0 | AA12: =AA4*0 -> 0 | AB12: 0 | AC12: =AC4*0.025 -> 333.33333 | AD12: =AD4*0.004 -> 53.333333 | AE12: =AE4*0.004 -> 53.333333 | AF12: =AF4*0 -> 0 | AG12: =AG4*0 -> 0 | AH12: =AH4*0 -> 0 | AI12: =AI4*0.025 -> 333.33333 | AJ12: =AJ4*0.025 -> 333.33333 | AK12: =AK4*0 -> 0 | AL12: =AL4*0 -> 0 | AM12: =AM4*0 -> 0 | AN12: =AN4*0 -> 0 | AO12: =AO4*0 -> 0 | AP12: =AP4*0 -> 0 | AQ12: =AQ4*0 -> 0 | AR12: =AR4*0 -> 0 | ... BJ12: =BJ4*0 -> 0 | BL12: =BL4*0 -> 0 | BM12: =BM4*0 -> 0 | BN12: =BN4*0 -> 0 | BO12: =BO4*0 -> 0 | BP12: =BP4*0 -> 0 | BQ12: =BQ4*0 -> 0 | BR12: =BR4*0 -> 0 | BS12: =BS4*0 -> 0 | ... BW12: =BW4*0 -> 0
A13: Net Take Home | C13: =C10-C11+C5 -> 6200 | D13: =D10-D11+D5 -> 11580 | E13: =E10-E11+E5 -> 6600 | F13: =F10-F11+F5 -> 6600 | G13: =G10-G11+G5 -> 6600 | H13: =H10-H11+H5 -> 6600 | I13: =I10-I11+I5 -> 14900 | J13: =J10-J11+J5 -> 14900 | ... L13: =L10-L11+L5 -> 6600 | M13: =M10-M11 -> 7128 | N13: =N10-N11 -> 6930 | O13: =O4+O7+O5-O11-O12+O8 -> 7200 | P13: =P10-P11-P12 -> 11873 | Q13: =Q10-Q11-Q12 -> 6876.5 | R13: =R10-R11-R12 -> 6657.5 | S13: =S10-S11-S12 -> 9857.5 | T13: =T10-T11-T12 -> 6457.5 | U13: =U10-U11-U12 -> 6457.5 | V13: =V10-V11-V12 -> 6757.5 | W13: =W10-W11-W12 -> 6457.5 | ... BJ13: =BJ10-BJ11-BJ12 -> 12100 | BL13: =BL10-BL11-BL12 -> 12100 | BM13: =BM10-BM11-BM12 -> 12100 | BN13: =BN10-BN11-BN12 -> 15100 | BO13: =BO10-BO11-BO12 -> 15100 | BP13: =BP10-BP11-BP12 -> 14000 | BQ13: =BQ10-BQ11-BQ12 -> 15100 | BR13: =BR10-BR11-BR12 -> 15100 | BS13: =BS10-BS11-BS12 -> 15100 | ... BW13: =BW10-BW11-BW12 -> 14600
A15: Expenses (60%)
A16: Fixed Costs (40%)
A17: Home | B17: Rent | C17: 1450 | D17: 1450 | E17: 1450 | F17: 1450 | G17: 1450 | H17: =1450+350 -> 1800 | I17: =1853+569 -> 2422 | J17: 0 | K17: 1000 | L17: =3383-1500 -> 1883 | M17: =1954 -> 1954 | N17: 1900 | O17: 1900 | P17: 1900 | Q17: 1900 | R17: 1921 | S17: 1921 | T17: =1921 -> 1921 | U17: 120 | V17: =120+700 -> 820 | W17: =sum(120+700) -> 820 | X17: =sum(336,1740) -> 2076 | Y17: =sum(1740) -> 1740 | Z17: 1571.7 | AA17: =sum(1740) -> 1740 | AB17: =sum(1740) -> 1740 | AC17: =sum(1740) -> 1740 | AD17: =sum(1740) -> 1740 | AE17: =sum(1740) -> 1740 | AF17: =sum(1740) -> 1740 | AG17: =sum(1740) -> 1740 | AH17: =sum(4000,1700) -> 5700 | AI17: =sum(2000) -> 2000 | AJ17: =sum(2700) -> 2700 | AK17: =sum(2700) -> 2700 | AL17: =sum(2700) -> 2700 | AM17: =sum(2700) -> 2700 | AN17: =sum(2700) -> 2700 | AO17: =sum(2700) -> 2700 | AP17: =sum(2700) -> 2700 | AQ17: =sum(2700) -> 2700 | ... AT17: =sum(2700) -> 2700 | AU17: =sum(2800) -> 2800 | AV17: =sum(2800) -> 2800 | AW17: =sum(2800) -> 2800 | AX17: =sum(2800) -> 2800 | AY17: =sum(2800) -> 2800 | AZ17: =sum(2800) -> 2800 | BA17: =-sum(2800) -> -2800 | BB17: =-sum(2800) -> -2800 | BC17: =-sum(2800) -> -2800 | BD17: =-sum(2800) -> -2800 | BE17: =-sum(2800) -> -2800 | BF17: =-sum(2800) -> -2800 | BG17: =-sum(2800) -> -2800 | BH17: =-sum(2800) -> -2800 | ... BJ17: =-sum(2800) -> -2800 | BL17: =-sum(2800) -> -2800 | BM17: =-sum(2800) -> -2800 | BN17: =-sum(2800) -> -2800 | BO17: =-sum(2800) -> -2800 | BP17: =-sum(2800) -> -2800 | BQ17: =-sum(2800) -> -2800 | BR17: =-sum(2800) -> -2800 | BS17: =-sum(2800) -> -2800 | ... BW17: =-sum(2800) -> -2800
B18: Renters Insurance | C18: 9 | D18: 9 | E18: 9 | F18: 9 | G18: 9 | H18: 9 | I18: 9 | J18: =18.42/2 -> 9.21 | K18: =18.42/2 -> 9.21 | L18: =18.42/2 -> 9.21 | M18: 11 | N18: =18.42/2 -> 9.21 | O18: =18.42/2 -> 9.21 | P18: =18.42/2 -> 9.21 | Q18: =18.42/2 -> 9.21 | R18: =18.42/2 -> 9.21 | S18: =18.42/2 -> 9.21 | T18: =18.42/2 -> 9.21 | U18: 0 | V18: 0 | W18: 0 | X18: 0 | Y18: 0 | Z18: 0 | AA18: 9 | AB18: 9 | AC18: 0 | AD18: 0 | AE18: 0 | AF18: 0 | AG18: 0 | AH18: 0 | AI18: 0 | AJ18: 0 | AK18: 0 | AL18: 0 | AM18: 0 | AN18: 0 | AO18: 0 | AP18: 0 | AQ18: 0 | AR18: 0 | AS18: 0 | AT18: 0 | AU18: 0 | AV18: 0 | AW18: 0 | AX18: 0 | AY18: 0 | AZ18: 0 | BA18: 0 | BB18: 0 | BC18: 0 | BD18: 0 | BE18: 0 | BF18: 0 | BG18: 0 | BH18: 0 | BI18: 0 | BJ18: 0 | BL18: 0 | BM18: 0 | BN18: 0 | BO18: 0 | BP18: 0 | BQ18: 0 | BR18: 0 | BS18: 0 | BT18: 0 | BU18: 0 | BV18: 0 | BW18: 0
B19: Utilities | I19: 100 | J19: 35 | K19: 90 | L19: =90 -> 90 | M19: 20 | N19: 90 | O19: 90 | P19: 90 | Q19: 90 | R19: 90 | S19: 90 | T19: 90 | U19: 0 | V19: 0 | W19: 0 | X19: 0 | Y19: 90 | Z19: 90 | AA19: 90 | AB19: 90 | AC19: 90 | AD19: 90 | AE19: 90 | AF19: 90 | AG19: 90 | AH19: 90 | AI19: 90 | AJ19: 90 | AK19: 90 | AL19: 90 | AM19: 90 | AN19: 90 | AO19: 90 | AP19: 90 | AQ19: 90 | AR19: 90 | AS19: 90 | AT19: 90 | AU19: 90 | AV19: 90 | AW19: 90 | AX19: 90 | AY19: 90 | AZ19: 90 | BA19: -90 | BB19: -90 | BC19: -90 | BD19: -90 | BE19: -90 | BF19: -90 | BG19: -90 | BH19: -90 | BI19: -90 | BJ19: -90 | BL19: -90 | BM19: -90 | BN19: -90 | BO19: -90 | BP19: -90 | BQ19: -90 | BR19: -90 | BS19: -90 | BT19: -90 | BU19: -90 | BV19: -90 | BW19: -90
B20: Wifi | C20: =62.95/2 -> 31.475 | D20: =62.95/2 -> 31.475 | E20: =62.95/2 -> 31.475 | F20: =62.95/2 -> 31.475 | G20: =62.95/2 -> 31.475 | H20: =62.95/2 -> 31.475 | I20: =62.95/2 -> 31.475 | J20: =62.95/2 -> 31.475 | ... T20: =62.95/2 -> 31.475 | U20: 0 | V20: 0 | W20: 0 | X20: 0 | Y20: =62.95/2 -> 31.475 | Z20: =91/2 -> 45.5 | AA20: =62.95/2 -> 31.475 | AB20: =62.95/2 -> 31.475 | AC20: =62.95/2 -> 31.475 | AD20: =62.95/2 -> 31.475 | AE20: =62.95/2 -> 31.475 | AF20: =62.95/2 -> 31.475 | AG20: =62.95/2 -> 31.475 | AH20: =0 -> 0 | AI20: =100/2 -> 50 | AJ20: =100/2 -> 50 | AK20: =100/2 -> 50 | AL20: =100/2 -> 50 | AM20: =100/2 -> 50 | AN20: =100/2 -> 50 | AO20: =100/2 -> 50 | AP20: =100/2 -> 50 | ... AZ20: =100/2 -> 50 | BA20: =-100/2 -> -50 | BB20: =-100/2 -> -50 | BC20: =-100/2 -> -50 | BD20: =-100/2 -> -50 | BE20: =-100/2 -> -50 | BF20: =-100/2 -> -50 | BG20: =-100/2 -> -50 | BH20: =-100/2 -> -50 | ... BJ20: =-100/2 -> -50 | BL20: =-100/2 -> -50 | BM20: =-100/2 -> -50 | BN20: =-100/2 -> -50 | BO20: =-100/2 -> -50 | BP20: =-100/2 -> -50 | BQ20: =-100/2 -> -50 | BR20: =-100/2 -> -50 | BS20: =-100/2 -> -50 | ... BW20: =-100/2 -> -50
B21: Groceries | I21: 400 | J21: =75*4 -> 300 | K21: =50*4 -> 200 | L21: =55*4 -> 220 | M21: =55*4 -> 220 | N21: =55*4 -> 220 | O21: =55*4 -> 220 | P21: =60*4 -> 240 | Q21: =200+150+250 -> 600 | R21: =195+200+150 -> 545 | S21: =100*4 -> 400 | T21: =60*4 -> 240 | U21: =60*4 -> 240 | V21: =60*4 -> 240 | W21: =60*4 -> 240 | X21: =60*4 -> 240 | Y21: =60*4 -> 240 | Z21: =60*4 -> 240 | AA21: =60*4 -> 240 | ... AJ21: =60*4 -> 240 | AK21: =100*4 -> 400 | AL21: =100*4 -> 400 | AM21: =100*4 -> 400 | AN21: =100*4 -> 400 | AO21: =100*4 -> 400 | AP21: =100*4 -> 400 | AQ21: =100*4 -> 400 | AR21: =100*4 -> 400 | ... AZ21: =100*4 -> 400 | BA21: =-100*4 -> -400 | BB21: =-100*4 -> -400 | BC21: =-100*4 -> -400 | BD21: =-100*4 -> -400 | BE21: =-100*4 -> -400 | BF21: =-100*4 -> -400 | BG21: =-100*4 -> -400 | BH21: =-100*4 -> -400 | ... BJ21: =-100*4 -> -400 | BL21: =-100*4 -> -400 | BM21: =-100*4 -> -400 | BN21: =-100*4 -> -400 | BO21: =-100*4 -> -400 | BP21: =-100*4 -> -400 | BQ21: =-100*4 -> -400 | BR21: =-100*4 -> -400 | BS21: =-100*4 -> -400 | ... BW21: =-100*4 -> -400
A22: Phone | B22: Phone Bill | E22: 100 | F22: 128.79 | G22: 120 | H22: =120+500 -> 620 | I22: 120.64 | J22: 120.64 | K22: 120.64 | L22: 150 | M22: 120.64 | N22: 120.64 | O22: 120 | P22: 120 | Q22: 120 | R22: 120 | S22: 120 | T22: 120 | U22: 120 | V22: 120 | W22: 120 | X22: 120 | Y22: 150 | Z22: 185.09 | AA22: 185.09 | AB22: 185.09 | AC22: 185.09 | AD22: 185.09 | AE22: 185.09 | AF22: 185.09 | AG22: 185.09 | AH22: 185.09 | AI22: 185.09 | AJ22: 185.09 | AK22: 0 | AL22: 0 | AM22: 0 | AN22: 0 | AO22: 0 | AP22: 0 | AQ22: 0 | AR22: 0 | AS22: 0 | AT22: 0 | AU22: 0 | AV22: 0 | AW22: 150 | AX22: 150 | AY22: 150 | AZ22: 150 | BA22: -150 | BB22: -150 | BC22: -150 | BD22: -150 | BE22: -150 | BF22: -150 | BG22: -150 | BH22: -150 | BI22: -150 | BJ22: -150 | BL22: -150 | BM22: -150 | BN22: -150 | BO22: -150 | BP22: -150 | BQ22: -150 | BR22: -150 | BS22: -150 | BT22: -150 | BU22: -150 | BV22: -150 | BW22: -150
A23: Car | B23: Car | N23: 0 | O23: 0 | P23: 0 | Q23: 0 | R23: 0 | S23: 0 | T23: 200 | U23: 0 | V23: =sum(116,60,300,300) -> 776 | W23: =sum(343,60,75) -> 478 | X23: =sum(343,180,150) -> 673 | Y23: =sum(343,180,100) -> 623 | Z23: =sum(343,180,100) -> 623 | AA23: =sum(343,180,100) -> 623 | AB23: =sum(343,180,100) -> 623 | AC23: =sum(343,180,100) -> 623 | AD23: =sum(343,180,100) -> 623 | AE23: =sum(343,180,100) -> 623 | AF23: =sum(343,180,100) -> 623 | ... AH23: =sum(343,180,100) -> 623 | AI23: 400 | AJ23: 0 | AK23: 0 | AL23: 175 | AM23: 0 | AN23: 0 | AO23: 0 | AP23: 0 | AQ23: 0 | AR23: 0 | AS23: 0 | AT23: 0 | AU23: 0 | AV23: 0 | AW23: 0 | AX23: 0 | AY23: 0 | AZ23: 0 | BA23: 0 | BB23: 0 | BC23: 0 | BD23: 0 | BE23: 0 | BF23: 0 | BG23: 0 | BH23: 0 | BI23: 0 | BJ23: 0 | BL23: 0 | BM23: 0 | BN23: 0 | BO23: 0 | BP23: 0 | BQ23: 0 | BR23: 0 | BS23: 0 | BT23: 0 | BU23: 0 | BV23: 0 | BW23: 0
A24: Transportation | B24: Ridesharing | J24: =170*4-20 -> 660 | K24: =22*7*4 -> 616 | L24: =22*7*4 -> 616 | M24: =20*4*4 -> 320 | N24: =20*4*4 -> 320 | O24: =15*7*4 -> 420 | P24: =15*30 -> 450 | Q24: =15*5 -> 75 | R24: =10*4 -> 40 | S24: =10*4 -> 40 | T24: =10*20 -> 200 | U24: =10*10 -> 100 | V24: 0 | W24: 0 | X24: 25 | Y24: 25 | Z24: 25 | AA24: 25 | AB24: 25 | AC24: 25 | AD24: 25 | AE24: 25 | AF24: 25 | AG24: 25 | AH24: 100 | AI24: 200 | AJ24: 100 | AK24: 100 | AL24: 100 | AM24: 100 | AN24: 100 | AO24: 100 | AP24: 100 | AQ24: 100 | AR24: 100 | AS24: 100 | AT24: 100 | AU24: 100 | AV24: 100 | AW24: 100 | AX24: 100 | AY24: 100 | AZ24: 100 | BA24: -100 | BB24: -100 | BC24: -100 | BD24: -100 | BE24: -200 | BF24: -200 | BG24: -200 | BH24: -200 | BI24: -200 | BJ24: -200 | BL24: -200 | BM24: -200 | BN24: -200 | BO24: -200 | BP24: -200 | BQ24: -200 | BR24: -200 | BS24: -200 | BT24: -200 | BU24: -200 | BV24: -200 | BW24: -200
B25: Metro | C25: 200 | D25: 200 | E25: 100 | F25: 200 | G25: 200 | H25: 200 | I25: =8*4*4+20*4 -> 208 | J25: =8*7*4 -> 224 | K25: =8*4*4 -> 128 | L25: =8*7*4 -> 224 | M25: =8*4*4 -> 128 | N25: =8*5*4 -> 160 | O25: =8*7*4 -> 224 | P25: =8*5*4 -> 160 | Q25: =40 -> 40 | R25: =0 -> 0 | S25: =0 -> 0 | T25: 0 | U25: 0 | V25: 0 | W25: 0 | X25: 0 | Y25: 0 | Z25: 0 | AA25: 0 | AB25: 0 | AC25: 0 | AD25: 0 | AE25: 0 | AF25: 0 | AG25: 0 | AH25: 50 | AI25: 50 | AJ25: 50 | AK25: 50 | AL25: 50 | AM25: 25 | AN25: 25 | AO25: 25 | AP25: 50 | AQ25: 50 | AR25: 50 | AS25: 50 | AT25: 50 | AU25: 50 | AV25: 50 | AW25: 50 | AX25: 50 | AY25: 50 | AZ25: 50 | BA25: -50 | BB25: -50 | BC25: -50 | BD25: -50 | BE25: -50 | BF25: -50 | BG25: -50 | BH25: -50 | BI25: -50 | BJ25: -50 | BL25: -50 | BM25: -50 | BN25: -50 | BO25: -50 | BP25: -50 | BQ25: -50 | BR25: -50 | BS25: -50 | BT25: -50 | BU25: -50 | BV25: -50 | BW25: -50
P26: =sum(P17:P25)/P13 -> 0.25273183 | Q26: =sum(Q17:Q25)/Q13 -> 0.41673598 | R26: =sum(R17:R25)/R13 -> 0.4140721 | S26: =sum(S17:S25)/S13 -> 0.26494395 | T26: =sum(T17:T25)/T13 -> 0.43541386 | U26: =sum(U17:U25)/U13 -> 0.089818041 | V26: =sum(V17:V25)/V13 -> 0.28945616 | W26: =sum(W17:W25)/W13 -> 0.25675571 | ... AZ26: =sum(AZ17:AZ25)/AZ13 -> 0.13212341
A27: Variable Costs (20%)
A28: Guilt Free | B28: Safe to Spend - Weekdays | C28: 1150 | D28: 1000 | E28: 1000 | F28: 1120 | G28: 1000 | H28: 500 | I28: =160*4 -> 640 | J28: =125*4 -> 500 | K28: =25*7*4 -> 700 | L28: =50*7*4 -> 1400 | M28: =25*7*4 -> 700 | N28: 1500 | O28: =30*5*4 -> 600 | P28: =30*20 -> 600 | Q28: =20*10 -> 200 | R28: =10*20 -> 200 | S28: =5*20 -> 100 | T28: =20*20 -> 400 | U28: =15*20 -> 300 | V28: =15*20 -> 300 | W28: =15*20 -> 300 | X28: =15*20 -> 300 | Y28: =50*20 -> 1000 | Z28: =45*20 -> 900 | AA28: =25*20 -> 500 | AB28: =25*20 -> 500 | AC28: =45*20 -> 900 | AD28: =25*20 -> 500 | AE28: =25*20 -> 500 | AF28: =25*20 -> 500 | AG28: =25*20 -> 500 | AH28: =25*20 -> 500 | AI28: =45*20 -> 900 | AJ28: =45*20 -> 900 | AK28: =45*20 -> 900 | AL28: =75*20 -> 1500 | AM28: =75*20 -> 1500 | AN28: =75*20 -> 1500 | AO28: =75*20 -> 1500 | AP28: =150*20 -> 3000 | AQ28: =75*20 -> 1500 | AR28: =75*20 -> 1500 | AS28: =75*20 -> 1500 | AT28: =75*20 -> 1500 | AU28: =75*20 -> 1500 | AV28: =75*20 -> 1500 | AW28: =75*20 -> 1500 | AX28: =75*20 -> 1500 | ... AZ28: =75*20 -> 1500 | BA28: =-75*20 -> -1500 | BB28: =-75*20 -> -1500 | BC28: =-75*20 -> -1500 | BD28: =-75*20 -> -1500 | BE28: =-75*20 -> -1500 | BF28: =-75*20 -> -1500 | BG28: =-75*20 -> -1500 | BH28: =-75*20 -> -1500 | ... BJ28: =-75*20 -> -1500 | BL28: =-75*20 -> -1500 | BM28: =-75*20 -> -1500 | BN28: =-75*20 -> -1500 | BO28: =-75*20 -> -1500 | BP28: =-75*20 -> -1500 | BQ28: =-75*20 -> -1500 | BR28: =-75*20 -> -1500 | BS28: =-75*20 -> -1500 | ... BW28: =-75*20 -> -1500
B29: Safe to Spend - Weekends | I29: =100*4 -> 400 | J29: =200*4 -> 800 | K29: =50*2*2*4 -> 800 | L29: =50*2*2*4 -> 800 | M29: =40*2*4 -> 320 | N29: =50*2*4 -> 400 | O29: =50*2*4 -> 400 | P29: =100*4 -> 400 | Q29: =45*2 -> 90 | R29: =20*8 -> 160 | S29: =30*8 -> 240 | T29: =45*8 -> 360 | U29: =20*8 -> 160 | V29: =45*8 -> 360 | W29: =40*8 -> 320 | X29: =40*8 -> 320 | Y29: =100*8 -> 800 | Z29: =100*8 -> 800 | AA29: =100*8 -> 800 | AB29: =100*8+300 -> 1100 | AC29: =100*8 -> 800 | AD29: =75*8 -> 600 | AE29: =75*8 -> 600 | AF29: =75*8 -> 600 | AG29: =75*8 -> 600 | AH29: =75*8 -> 600 | AI29: =100*10 -> 1000 | AJ29: =100*8 -> 800 | AK29: =100*8 -> 800 | AL29: =100*8 -> 800 | AM29: =100*8 -> 800 | AN29: =100*8 -> 800 | AO29: =100*8 -> 800 | AP29: =150*8 -> 1200 | AQ29: =100*8 -> 800 | AR29: =100*8 -> 800 | AS29: =100*8 -> 800 | AT29: =100*8 -> 800 | AU29: =100*8 -> 800 | AV29: =100*8 -> 800 | AW29: =100*8 -> 800 | AX29: =100*8 -> 800 | ... AZ29: =100*8 -> 800 | BA29: =-100*8 -> -800 | BB29: =-100*8 -> -800 | BC29: =-100*8 -> -800 | BD29: =-100*8 -> -800 | BE29: =-100*8 -> -800 | BF29: =-100*8 -> -800 | BG29: =-100*8 -> -800 | BH29: =-100*8 -> -800 | ... BJ29: =-100*8 -> -800 | BL29: =-100*8 -> -800 | BM29: =-100*8 -> -800 | BN29: =-100*8 -> -800 | BO29: =-100*8 -> -800 | BP29: =-100*8 -> -800 | BQ29: =-100*8 -> -800 | BR29: =-100*8 -> -800 | BS29: =-100*8 -> -800 | ... BW29: =-100*8 -> -800
B30: Entertainment | C30: 0 | D30: 0 | E30: 0 | F30: 0 | G30: 0 | H30: 0 | I30: 0 | J30: 0 | K30: 0 | L30: 0 | M30: 0 | N30: 200 | O30: 400 | P30: 0 | Q30: 0 | R30: 0 | S30: 0 | T30: 0 | U30: 0 | V30: 0 | W30: 0 | X30: 0 | Y30: 0 | Z30: 0 | AA30: 0 | AB30: 0 | AC30: 0 | AD30: 0 | AE30: 0 | AF30: 0 | AG30: 0 | AH30: 0 | AI30: 0 | AJ30: 0 | AK30: 0 | AL30: 0 | AM30: 0 | AN30: 0 | AO30: 0 | AP30: 0 | AQ30: 0 | AR30: 0 | AS30: 0 | AT30: 0 | AU30: 0 | AV30: 0 | AW30: 200 | AX30: 200 | AY30: 200 | AZ30: 200 | BA30: -200 | BB30: -200 | BC30: -200 | BD30: -200 | BE30: -200 | BF30: -200 | BG30: -200 | BH30: -200 | BI30: -200 | BJ30: -200 | BL30: -200 | BM30: -200 | BN30: -200 | BO30: -200 | BP30: -200 | BQ30: -200 | BR30: -200 | BS30: -200 | BT30: -200 | BU30: -200 | BV30: -200 | BW30: -200
B31: Memberships | C31: 10 | D31: 10 | E31: 10 | F31: 10 | G31: =10+5+20 -> 35 | H31: =10+5+20 -> 35 | I31: =10+20+60 -> 90 | J31: =10+20+30+15 -> 75 | K31: =10+5+20+30 -> 65 | L31: =10+5+20+60 -> 95 | M31: =10+5+20+60 -> 95 | N31: =10+5+20+60 -> 95 | O31: =10+5+20+60 -> 95 | P31: =10+5+20+60+4+4 -> 103 | Q31: =10+5+20+60+35.68 -> 130.68 | R31: =10+5+20+60 -> 95 | S31: =10+13+20+60 -> 103 | T31: =10+13+20+60 -> 103 | U31: =10+13+20+60 -> 103 | V31: =sum(10,13,20,60,4,15,20) -> 142 | W31: =sum(10,13,20,60,4,15,70) -> 192 | X31: =sum(10,13,20,60,4,15,0) -> 122 | Y31: =sum(10,13,20,60,4,15,0) -> 122 | Z31: =sum(10,13,60,4,15,0) -> 102 | AA31: =sum(10,13,60,4,15,0) -> 102 | AB31: =sum(10,13,60,4,15,0) -> 102 | AC31: =sum(10,13,60,4,15,0) -> 102 | AD31: =sum(10,13,60,4,15,0) -> 102 | AE31: =sum(10,13,60,4,15,0) -> 102 | AF31: =sum(10,13,60,4,15,0) -> 102 | AG31: =sum(10,13,60,4,15,0) -> 102 | ... AZ31: =sum(10,13,60,4,15,0) -> 102 | BA31: =-sum(10,13,60,4,15,0) -> -102 | BB31: =-sum(10,13,60,4,15,0) -> -102 | BC31: =-sum(10,13,60,4,15,0) -> -102 | BD31: =-sum(10,13,60,4,15,0) -> -102 | BE31: =-sum(10,13,60,4,15,0) -> -102 | BF31: =-sum(10,13,60,4,15,0) -> -102 | BG31: =-sum(10,13,60,4,15,0) -> -102 | BH31: =-sum(10,13,60,4,15,0) -> -102 | ... BJ31: =-sum(10,13,60,4,15,0) -> -102 | BL31: =-sum(10,13,60,4,15,0) -> -102 | BM31: =-sum(10,13,60,4,15,0) -> -102 | BN31: =-sum(10,13,60,4,15,0) -> -102 | BO31: =-sum(10,13,60,4,15,0) -> -102 | BP31: =-sum(10,13,60,4,15,0) -> -102 | BQ31: =-sum(10,13,60,4,15,0) -> -102 | BR31: =-sum(10,13,60,4,15,0) -> -102 | BS31: =-sum(10,13,60,4,15,0) -> -102 | ... BW31: =-sum(10,13,60,4,15,0) -> -102
B32: Travel | C32: 0 | D32: 0 | E32: 500 | F32: 500 | G32: 0 | H32: 0 | I32: 0 | J32: 500 | K32: 450 | L32: 300 | M32: 200 | N32: 100 | O32: 0 | P32: =250+179 -> 429 | Q32: 0 | R32: =260*2 -> 520 | S32: 0 | T32: =sum(500/2,185,25,84,257) -> 801 | U32: =sum(270,250) -> 520 | V32: =sum(300,600,240) -> 1140 | W32: =375+74 -> 449 | X32: 0 | Y32: 0 | Z32: =sum(548.5,400,55.1,92.1,169.66,100) -> 1365.36 | AA32: ='Travel Expenses - Tulum'!C32-Z32 -> 2256.425 | AB32: 90 | AC32: 1200 | AD32: 0 | AE32: 500 | AF32: 0 | AG32: 0 | AH32: 0 | AI32: 0 | AJ32: 0 | AK32: 0 | AL32: =1500+600 -> 2100 | AM32: 0 | AN32: 0 | AO32: 0 | AP32: 0 | AQ32: 0 | AR32: 0 | AS32: 0 | AT32: 0 | AU32: 0 | AV32: 0 | AW32: 0 | AX32: 0 | AY32: 0 | AZ32: =sum(650,375,300) -> 1325 | BA32: 0 | BB32: 0 | BC32: =-1700 -> -1700 | BD32: =-sum(3000,4396) -> -7396 | BE32: 0 | BF32: 300 | BG32: 0 | BH32: 0 | BI32: 0 | BJ32: -10000 | BL32: 0 | BM32: 0 | BN32: 0 | BO32: 0 | BP32: 0 | BQ32: 0 | BR32: 0 | BS32: 0 | BT32: 0 | BU32: 0 | BV32: 0 | BW32: 0
A33: Home | B33: Home Goods | I33: 600 | J33: 0 | K33: 0 | L33: 0 | M33: 0 | N33: 0 | O33: 0 | P33: =43+83 -> 126 | Q33: =90+266+80 -> 436 | R33: 0 | S33: 0 | T33: 0 | U33: 0 | V33: 0 | W33: 0 | X33: 1000 | Y33: 0 | Z33: =sum(250,100,250) -> 600 | AA33: 0 | AB33: 0 | AC33: 0 | AD33: 0 | AE33: 0 | AF33: 0 | AG33: 0 | AH33: 2000 | AI33: 0 | AJ33: 0 | AK33: 0 | AL33: 25 | AM33: 0 | AN33: 0 | AO33: 0 | AP33: 0 | AQ33: 0 | AR33: 0 | AS33: 0 | AT33: 0 | AU33: 0 | AV33: 0 | AW33: 50 | AX33: 50 | AY33: 50 | AZ33: 50 | BA33: -50 | BB33: -50 | BC33: -50 | BD33: 0 | BE33: 0 | BF33: -50 | BG33: =sum(-50,-500) -> -550 | BH33: -50 | BI33: -50 | BJ33: -50 | BL33: -50 | BM33: -50 | BN33: -50 | BO33: -50 | BP33: -50 | BQ33: -50 | BR33: -50 | BS33: -50 | BT33: -50 | BU33: -50 | BV33: -50 | BW33: -50
B34: Books | I34: 10 | J34: 0 | K34: =12*2 -> 24 | L34: 0 | M34: 0 | N34: =12*1 -> 12 | O34: =12*1 -> 12 | P34: =13 -> 13 | Q34: 0 | R34: =12*1 -> 12 | S34: =12*1 -> 12 | T34: =12*1 -> 12 | U34: =12*1 -> 12 | V34: =12*1 -> 12 | W34: =12*1 -> 12 | X34: =12*1 -> 12 | Y34: =12*1 -> 12 | ... AJ34: =12*1 -> 12 | AK34: 0 | AL34: 0 | AM34: =12*1 -> 12 | AN34: =12*1 -> 12 | AO34: =12*1 -> 12 | AP34: =12*1 -> 12 | AQ34: =12*1 -> 12 | AR34: =12*1 -> 12 | AS34: 50 | AT34: =12*1 -> 12 | AU34: =12*1 -> 12 | AV34: =12*1 -> 12 | AW34: =12*1 -> 12 | AX34: =12*1 -> 12 | AY34: =12*1 -> 12 | AZ34: =12*1 -> 12 | BA34: =-20*1 -> -20 | BB34: =-20*1 -> -20 | BC34: =-20*1 -> -20 | BD34: =-20*1 -> -20 | BE34: =-20*1 -> -20 | BF34: =-20*1 -> -20 | BG34: =-20*1 -> -20 | BH34: =-20*1 -> -20 | ... BJ34: =-20*1 -> -20 | BL34: =-20*1 -> -20 | BM34: =-20*1 -> -20 | BN34: =-20*1 -> -20 | BO34: =-20*1 -> -20 | BP34: =-20*1 -> -20 | BQ34: =-20*1 -> -20 | BR34: =-20*1 -> -20 | BS34: =-20*1 -> -20 | ... BW34: =-20*1 -> -20
B35: Clothing | I35: 100 | J35: 60 | K35: 250 | L35: 0 | M35: 50 | N35: 0 | O35: 100 | P35: 0 | Q35: 0 | R35: 0 | S35: 0 | T35: 300 | U35: 100 | V35: 100 | W35: 100 | X35: 100 | Y35: 100 | Z35: 100 | AA35: 100 | AB35: 100 | AC35: 100 | AD35: 100 | AE35: 100 | AF35: 100 | AG35: 100 | AH35: 100 | AI35: 100 | AJ35: 100 | AK35: 100 | AL35: 300 | AM35: 300 | AN35: 300 | AO35: 300 | AP35: 300 | AQ35: 300 | AR35: 300 | AS35: 300 | AT35: 300 | AU35: 300 | AV35: 300 | AW35: 300 | AX35: 300 | AY35: 300 | AZ35: 300 | BA35: -500 | BB35: -500 | BC35: -500 | BD35: -500 | BE35: -500 | BF35: -200 | BG35: -500 | BH35: -500 | BI35: =sum(-10000,-2000) -> -12000 | BJ35: =sum(-500,-1200,-800) -> -2500 | BL35: =sum(-500,-1200,-800) -> -2500 | BM35: =sum(-500,-1200,-800) -> -2500 | BN35: =sum(-500,-1200,-800) -> -2500 | BO35: =sum(-500,-1200,-800) -> -2500 | BP35: =sum(-500,-1200,-800) -> -2500 | BQ35: =sum(-500,-1200,-800) -> -2500 | BR35: =sum(-500,-1200) -> -1700 | BS35: =sum(-500,-1200) -> -1700 | BT35: =sum(-500,-1200) -> -1700 | BU35: =sum(-500,-1200) -> -1700 | BV35: =sum(-500,-1200) -> -1700 | BW35: =sum(-500,-1200) -> -1700
A36: Health | B36: Dental | C36: 0 | D36: 0 | E36: 0 | F36: 0 | G36: 0 | H36: 0 | I36: 25 | J36: 0 | K36: 0 | L36: 0 | M36: 0 | N36: 0 | O36: 0 | P36: 0 | Q36: 0 | R36: 0 | S36: 0 | T36: 0 | U36: 0 | V36: 0 | W36: 0 | X36: 0 | Y36: 0 | Z36: 0 | AA36: 0 | AB36: 0 | AC36: 0 | AD36: 0 | AE36: 0 | AF36: 0 | AG36: 0 | AH36: 0 | AI36: 0 | AJ36: 0 | AK36: 0 | AL36: 0 | AM36: 0 | AN36: 0 | AO36: 0 | AP36: 0 | AQ36: 0 | AR36: 0 | AS36: 0 | AT36: 0 | AU36: 0 | AV36: 0 | AW36: 0 | AX36: 0 | AY36: 0 | AZ36: 0 | BA36: 0 | BB36: 0 | BC36: 0 | BD36: 0 | BE36: 0 | BF36: 0 | BG36: 0 | BH36: 0 | BI36: 0 | BJ36: 0 | BL36: 0 | BM36: 0 | BN36: 0 | BO36: 0 | BP36: 0 | BQ36: 0 | BR36: 0 | BS36: 0 | BT36: 0 | BU36: 0 | BV36: 0 | BW36: 0
B37: Healthcare | J37: 0 | K37: 0 | L37: 0 | M37: 0 | N37: 0 | O37: 0 | P37: 0 | Q37: 0 | R37: 0 | S37: 0 | T37: 0 | U37: 0 | V37: =490 -> 490 | W37: 0 | X37: 0 | Y37: 0 | Z37: 0 | AA37: 0 | AB37: 0 | AC37: 0 | AD37: 0 | AE37: 0 | AF37: 0 | AG37: 0 | AH37: 0 | AI37: 0 | AJ37: 0 | AK37: 250 | AL37: 0 | AM37: 0 | AN37: 0 | AO37: 0 | AP37: 0 | AQ37: 0 | AR37: 0 | AS37: 0 | AT37: 0 | AU37: 0 | AV37: 0 | AW37: 0 | AX37: 0 | AY37: 0 | AZ37: 0 | BA37: 0 | BB37: 0 | BC37: 0 | BD37: 0 | BE37: 0 | BF37: 0 | BG37: 0 | BH37: 0 | BI37: 0 | BJ37: 0 | BL37: 0 | BM37: 0 | BN37: 0 | BO37: 0 | BP37: 0 | BQ37: 0 | BR37: 0 | BS37: 0 | BT37: 0 | BU37: 0 | BV37: 0 | BW37: 0
B38: Self-Care | I38: 100 | J38: =60+20+350 -> 430 | K38: 50 | L38: 60 | M38: 60 | N38: 95 | O38: 100 | P38: 100 | Q38: 60 | R38: 0 | S38: 0 | T38: 100 | U38: 50 | V38: 100 | W38: 100 | X38: 100 | Y38: 100 | Z38: 100 | AA38: 100 | AB38: 100 | AC38: 100 | AD38: 100 | AE38: 100 | AF38: 100 | AG38: 100 | AH38: 100 | AI38: 100 | AJ38: 100 | AK38: 100 | AL38: 100 | AM38: 100 | AN38: 100 | AO38: 100 | AP38: 100 | AQ38: 100 | AR38: 100 | AS38: 100 | AT38: 100 | AU38: 100 | AV38: 100 | AW38: 100 | AX38: 100 | AY38: 100 | AZ38: 100 | BA38: -100 | BB38: -100 | BC38: -100 | BD38: -100 | BE38: -100 | BF38: -100 | BG38: -100 | BH38: -100 | BI38: -100 | BJ38: -100 | BL38: -100 | BM38: -100 | BN38: -100 | BO38: -100 | BP38: -100 | BQ38: -100 | BR38: -100 | BS38: -100 | BT38: -100 | BU38: -100 | BV38: -100 | BW38: -100
B39: Gym | C39: 0 | D39: 0 | E39: 0 | F39: 0 | G39: 0 | H39: 0 | I39: 0 | J39: 0 | K39: 0 | L39: 0 | M39: 0 | N39: 0 | O39: 0 | P39: 0 | Q39: 0 | R39: 0 | S39: 0 | T39: 0 | U39: 0 | V39: 0 | W39: 0 | X39: 0 | Y39: 0 | Z39: 0 | AA39: 0 | AB39: 0 | AC39: 0 | AD39: 0 | AE39: 0 | AF39: 0 | AG39: 0 | AH39: 100 | AI39: 300 | AJ39: 100 | AK39: 175 | AL39: 175 | AM39: 175 | AN39: 175 | AO39: 175 | AP39: 175 | AQ39: 175 | AR39: 175 | AS39: 175 | AT39: 175 | AU39: 175 | AV39: 175 | AW39: 175 | AX39: 175 | AY39: 175 | AZ39: 175 | BA39: -175 | BB39: -175 | BC39: -175 | BD39: -175 | BE39: =sum(-175,-1200) -> -1375 | BF39: =sum(-175) -> -175 | BG39: =sum(-175,-185) -> -360 | BH39: =sum(-175,-800) -> -975 | BI39: =sum(-175,-800) -> -975 | BJ39: =sum(-175) -> -175 | BL39: =sum(-175) -> -175 | BM39: =sum(-175,-800) -> -975 | BN39: =sum(-175,-800) -> -975 | BO39: =sum(-175,-800) -> -975 | BP39: =sum(-175,-800) -> -975 | BQ39: =sum(-175,-800) -> -975 | BR39: =sum(-175,-800) -> -975 | BS39: =sum(-175,-800) -> -975 | BT39: =sum(-175,-800) -> -975 | ... BV39: =sum(-175,-800) -> -975 | BW39: =sum(-175) -> -175
A40: Misc | B40: Dog Stuff | E40: 50 | F40: 50 | G40: 50 | H40: 50 | I40: 100 | J40: =30+40 -> 70 | K40: 0 | L40: 50 | M40: 50 | N40: 20 | O40: 0 | P40: 50 | Q40: 30 | R40: =15+35 -> 50 | S40: 10 | T40: 40 | U40: 30 | V40: =sum(30,100) -> 130 | W40: 30 | X40: 30 | Y40: 30 | Z40: 10 | AA40: 10 | AB40: 10 | AC40: 10 | AD40: 10 | AE40: 10 | AF40: 10 | AG40: 10 | AH40: 10 | AI40: 10 | AJ40: 10 | AK40: 10 | AL40: 10 | AM40: 10 | AN40: 10 | AO40: 10 | AP40: 10 | AQ40: 10 | AR40: 10 | AS40: 0 | AT40: 10 | AU40: 10 | AV40: 10 | AW40: 30 | AX40: 30 | AY40: 30 | AZ40: 30 | BA40: -30 | BB40: -30 | BC40: -30 | BD40: =sum(-30,-50) -> -80 | BE40: =sum(-30,-50) -> -80 | BF40: =sum(-30,-50) -> -80 | BG40: =sum(-30,-50) -> -80 | BH40: =sum(-30,-50) -> -80 | BI40: =sum(-30,-50) -> -80 | BJ40: =sum(-30,-50) -> -80 | BL40: =sum(-30,-50) -> -80 | BM40: =sum(-30,-50) -> -80 | BN40: =sum(-30,-50) -> -80 | BO40: =sum(-30,-50) -> -80 | BP40: =sum(-30,-50) -> -80 | BQ40: =sum(-30,-50) -> -80 | BR40: =sum(-30,-50) -> -80 | BS40: =sum(-30,-50) -> -80 | ... BW40: =sum(-30,-50) -> -80
B41: Contractor Services | K41: 0 | L41: 0 | M41: 0 | N41: 250 | O41: 0 | P41: 200 | Q41: 0 | R41: 0 | S41: =0 -> 0 | T41: =840+450 -> 1290 | U41: 0 | V41: 0 | W41: 0 | X41: 0 | Y41: 0 | Z41: 0 | AA41: 0 | AB41: 0 | AC41: 0 | AD41: 0 | AE41: 0 | AF41: 0 | AG41: 0 | AH41: 0 | AI41: 0 | AJ41: 0 | AK41: 0 | AL41: 0 | AM41: 0 | AN41: 0 | AO41: 0 | AP41: 0 | AQ41: 0 | AR41: 0 | AS41: 0 | AT41: 0 | AU41: 0 | AV41: 0 | AW41: 0 | AX41: 0 | AY41: 0 | AZ41: 0 | BA41: 0 | BB41: 0 | BC41: 0 | BD41: 0 | BE41: 0 | BF41: 0 | BG41: 0 | BH41: 0 | BI41: 0 | BJ41: 0 | BL41: 0 | BM41: 0 | BN41: 0 | BO41: 0 | BP41: 0 | BQ41: 0 | BR41: 0 | BS41: 0 | BT41: 0 | BU41: 0 | BV41: 0 | BW41: 0
B42: Tech | X42: =272+375 -> 647 | Y42: 0 | Z42: 0 | AA42: 0 | AB42: 0 | AC42: 0 | AD42: 0 | AE42: 0 | AF42: 0 | AG42: 0 | AH42: 0 | AI42: 0 | AJ42: 0 | AK42: 0 | AL42: 0 | AM42: 0 | AN42: 0 | AO42: 0 | AP42: 0 | AQ42: 0 | AR42: 0 | AS42: 0 | AT42: 0 | AU42: 0 | AV42: 0 | AW42: 0 | AX42: 0 | AY42: 0 | AZ42: 0 | BA42: 0 | BB42: 0 | BC42: 0 | BD42: 0 | BE42: 0 | BF42: 0 | BG42: 0 | BH42: 0 | BI42: 0 | BJ42: 0 | BL42: 0 | BM42: 0 | BN42: 0 | BO42: 0 | BP42: 0 | BQ42: 0 | BR42: 0 | BS42: 0 | BT42: 0 | BU42: 0 | BV42: 0 | BW42: 0
B43: Misc. | T43: 0 | U43: 0 | V43: 0 | W43: 0 | X43: =sum(700/2,50,500) -> 900 | Y43: 0 | Z43: 0 | AA43: 0 | AB43: 0 | AC43: 0 | AD43: 0 | AE43: 0 | AF43: 0 | AG43: 0 | AH43: 0 | AI43: 0 | AJ43: 0 | AK43: 0 | AL43: 1500 | AM43: 0 | AN43: 0 | AO43: 0 | AP43: 0 | AQ43: 0 | AR43: 0 | AS43: 0 | AT43: 0 | AU43: 0 | AV43: 0 | AW43: 0 | AX43: 500 | AY43: 0 | AZ43: 0 | BA43: 0 | BB43: 0 | BC43: 0 | BD43: 0 | BE43: 0 | BF43: 0 | BG43: 0 | BH43: 0 | BI43: 0 | BJ43: 0 | BL43: 0 | BM43: 0 | BN43: 0 | BO43: 0 | BP43: 0 | BQ43: 0 | BR43: 0 | BS43: 0 | BT43: 0 | BU43: 0 | BV43: 0 | BW43: 0
P44: =sum(P17:P41)/P13 -> 0.42297126 | Q44: =sum(Q28:Q41)/Q13 -> 0.13766887 | R44: =sum(R28:R41)/R13 -> 0.15576418 | S44: =sum(S28:S41)/S13 -> 0.047172204 | T44: =sum(T28:T43)/T13 -> 0.5274487 | U44: =sum(U28:U43)/U13 -> 0.19744483 | V44: =sum(V28:V43)/V13 -> 0.41050684 | W44: =sum(W28:W43)/W13 -> 0.23275261 | X44: =sum(X28:X43)/X13 -> 0.54680604 | Y44: =sum(Y28:Y43)/Y13 -> 0.17947336 | Z44: =sum(Z28:Z43)/Z13 -> 0.45333636 | AA44: =sum(AA28:AA43)/AA13 -> 0.44095739 | ... AZ44: =sum(AZ28:AZ43)/AZ13 -> 0.16675136
A45: Total Expenses | C45: =sum(C17:C40) -> 2850.475 | D45: =sum(D17:D40) -> 2700.475 | E45: =sum(E17:E40) -> 3250.475 | F45: =sum(F17:F40) -> 3499.265 | G45: =sum(G17:G40) -> 2895.475 | H45: =sum(H23:H40) -> 785 | I45: =sum(I23:I40) -> 2273 | J45: =sum(J23:J40) -> 3319 | K45: =sum(K23:K40) -> 3083 | L45: =sum(L23:L40) -> 3545 | M45: =sum(M23:M40) -> 1923 | N45: =sum(N23:N41) -> 3152 | O45: =sum(O23:O41) -> 2351 | P45: =sum(P17:P41) -> 5021.9377 | Q45: =sum(Q17:Q41) -> 3812.7817 | R45: =sum(R17:R41) -> 3794.0991 | S45: =sum(S17:S41) -> 3076.9499 | T45: =sum(T17:T43) -> 6218.1204 | U45: =sum(U17:U43) -> 1855.0898 | V45: =sum(V17:V43) -> 4730.2895 | W45: =sum(W17:W43) -> 3161.2568 | X45: =sum(X17:X43) -> 6665.4853 | Y45: =sum(Y17:Y25,Y28:Y43) -> 5063.475 | Z45: =sum(Z17:Z25,Z28:Z43) -> 6769.65 | AA45: =sum(AA17:AA25,AA28:AA43) -> 6823.99 | AB45: =sum(AB17:AB25,AB28:AB43) -> 4957.565 | AC45: =sum(AC17:AC25,AC28:AC43) -> 6158.565 | AD45: =sum(AD17:AD25,AD28:AD43) -> 4358.565 | AE45: =sum(AE17:AE25,AE28:AE43) -> 4858.565 | AF45: =sum(AF17:AF25,AF28:AF43) -> 4358.565 | ... BJ45: =sum(BJ17:BJ25,BJ28:BJ43) -> -19267 | BL45: =sum(BL17:BL25,BL28:BL43) -> -9267 | BM45: =sum(BM17:BM25,BM28:BM43) -> -10067 | BN45: =sum(BN17:BN25,BN28:BN43) -> -10067 | BO45: =sum(BO17:BO25,BO28:BO43) -> -10067 | BP45: =sum(BP17:BP25,BP28:BP43) -> -10067 | BQ45: =sum(BQ17:BQ25,BQ28:BQ43) -> -10067 | BR45: =sum(BR17:BR25,BR28:BR43) -> -9267 | BS45: =sum(BS17:BS25,BS28:BS43) -> -9267 | ... BW45: =sum(BW17:BW25,BW28:BW43) -> -8467
A47: Financial Health (40%)
A48: Debt Consolidation (10%)
B49: Debt Repayment (10%) | C49: 2500 | D49: 4500 | E49: 2800 | F49: 2800 | G49: 2000 | H49: 3093 | I49: 1600 | J49: ='PAYMENT SCHEDULE'!C13+'PAYMENT SCHEDULE'!C29 -> 3200 | K49: =LIABILITIES!E26 -> 1000 | L49: =LIABILITIES!E26 -> 1000 | M49: ='PAYMENT SCHEDULE'!C33 | N49: =N13*0.25 -> 1732.5 | O49: =O13*0.35 -> 2520 | P49: 5956 | Q49: 2008 | R49: =R13*0.4 -> 2663 | S49: 5600 | T49: =T13*0.25 -> 1614.375 | U49: =U13*0.4 -> 2583 | V49: =3397 -> 3397 | W49: =W13*0.3 -> 1937.25 | X49: =X$13*0.11 -> 710.325 | Y49: =Y$13*0.1 -> 1205.75 | Z49: =Z$13*0.1 -> 880 | AA49: =AA$13*0.33 -> 2904 | AB49: =AB$13*0.2 -> 1760 | AC49: =AC$13*0.2 -> 1833.3333 | AD49: =AD$13*0.25 -> 2186.6667 | AE49: =AE$13*0.7 -> 13822.667 | AF49: =AF$13*0.25 -> 2525 | AG49: =AG$13*0.15 -> 1680 | AH49: =AH$13*0.15 -> 3870 | AI49: =AI$13*0.18 -> 1524 | AJ49: =AJ$13*0.18 -> 1524 | AK49: =AK$13*0.18 -> 3379.5 | AL49: =AL$13*0.05 -> 577.5 | AM49: =AM$13*0.1 -> 1155 | AN49: =AN$13*0.4 -> 8620 | AO49: =AO$13*0.1 -> 1255 | AP49: =17000 -> 17000 | AQ49: =AQ$13*0.1 -> 1155 | AR49: =AR$13*0.3 -> 3465 | AS49: =AS$13*0.3 -> 3465 | AT49: =AT$13*0.5 -> 8150.555 | AU49: =AU$13*0.2 -> 5550 | AV49: =AV$13*0.1 -> 1155 | AW49: =AW$13*0.1+2530 -> 3685 | AX49: =AX$13*0.1+2000 -> 3489.4 | AY49: =AY$13*0.1 -> 1435 | AZ49: 16000 | BA49: -15000 | BB49: -2400 | BC49: -5000 | BD49: -2400 | BE49: -2400 | BF49: -5000 | BG49: =-4500 -> -4500 | BH49: =sum(-2500,-10000) -> -12500 | BI49: =sum(-95000,-95000) -> -190000 | BJ49: =sum(0) -> 0 | BL49: 0 | BM49: 0 | BN49: 0 | BO49: 0 | BP49: 0 | BQ49: 0 | BR49: 0 | BS49: 0 | BT49: 0 | BU49: 0 | BV49: 0 | BW49: 0
A50: Savings (19%)
B51: Long-Term High-Yield Savings (10%) | I51: 0 | J51: 0 | K51: =K13*0 -> 0 | L51: =L13*0 -> 0 | M51: 0 | N51: 25 | O51: 25 | P51: 20 | Q51: 25 | R51: 0 | S51: 0 | T51: 0 | U51: 0 | V51: 0 | W51: 0 | X51: =$X$13*0.03 -> 193.725 | Y51: =$X$13*0.03 -> 193.725 | Z51: =$X$13*0.1 -> 645.75 | AA51: =$X$13*0.03 -> 193.725 | AB51: =$X$13*0.03 -> 193.725 | AC51: =$X$13*0.03 -> 193.725 | AD51: =$X$13*0 -> 0 | AE51: =$X$13*0 -> 0 | AF51: =$X$13*0 -> 0 | AG51: =$X$13*0 -> 0 | AH51: =$X$13*0 -> 0 | AI51: =$X$13*0.03 -> 193.725 | AJ51: =$X$13*0.03 -> 193.725 | AK51: =$X$13*0.032 -> 206.64 | AL51: =$X$13*0.032 -> 206.64 | AM51: =$X$13*0.032 -> 206.64 | AN51: =$X$13*0.05 -> 322.875 | AO51: =$X$13*0.05 -> 322.875 | AP51: =$X$13*0.05 -> 322.875 | AQ51: =$X$13*0.05 -> 322.875 | AR51: =$X$13*0.05 -> 322.875 | AS51: =$X$13*0 -> 0 | AT51: =$X$13*0.05 -> 322.875 | AU51: =$X$13*0.05 -> 322.875 | AV51: =$X$13*0.05 -> 322.875 | AW51: 0 | AX51: 0 | AY51: 0 | AZ51: 0 | BA51: 0 | BB51: 0 | BC51: 0 | BD51: 0 | BE51: 0 | BF51: 0 | BG51: 0 | BH51: 0 | BI51: -300 | BJ51: -300 | BL51: -300 | BM51: -300 | BN51: -300 | BO51: -300 | BP51: -300 | BQ51: -300 | BR51: -300 | BS51: -300 | BT51: -300 | BU51: -300 | BV51: -300 | BW51: -300
B52: Short-Term Liquid Traditional Savings (10%) | R52: 0 | S52: 500 | T52: =T13*0.02 -> 129.15 | U52: =U13*0.0387 -> 249.90525 | V52: 200 | W52: 200 | X52: =$X$13*0.04 -> 258.3 | Y52: =$X$13*0.04 -> 258.3 | Z52: =$X$13*0.1 -> 645.75 | AA52: =$X$13*0.047 -> 303.5025 | AB52: =$X$13*0.04 -> 258.3 | AC52: =$X$13*0.04 -> 258.3 | AD52: =$X$13*0.05 -> 322.875 | AE52: =$X$13*0.063 -> 406.8225 | AF52: =$X$13*0.2 -> 1291.5 | AG52: =$X$13*0.2 -> 1291.5 | AH52: =$X$13*0 -> 0 | AI52: =$X$13*0.04 -> 258.3 | AJ52: =$X$13*0.04 -> 258.3 | AK52: =$X$13*0.04 -> 258.3 | AL52: =$X$13*0.04 -> 258.3 | AM52: =$X$13*0.04 -> 258.3 | AN52: =$X$13*0.05 -> 322.875 | AO52: =$X$13*0.05 -> 322.875 | AP52: =$X$13*0.05 -> 322.875 | AQ52: =$X$13*0.05 -> 322.875 | AR52: =$X$13*0.05 -> 322.875 | AS52: =$X$13*0.05 -> 322.875 | AT52: =$X$13*0.05 -> 322.875 | AU52: =$X$13*0.05 -> 322.875 | ... AW52: =$X$13*0.05 -> 322.875 | AX52: =$X$13*0 -> 0 | AY52: =$X$13*0 -> 0 | AZ52: =$X$13*0.05 -> 322.875 | BA52: 0 | BB52: 0 | BC52: -100 | BD52: -100 | BE52: -100 | BF52: -100 | BG52: -100 | BH52: -100 | BI52: -10000 | BJ52: -100 | BL52: -100 | BM52: -100 | BN52: -100 | BO52: -100 | BP52: -100 | BQ52: -100 | BR52: -100 | BS52: -100 | BT52: -100 | BU52: -100 | BV52: -100 | BW52: -100
A53: Investment (10%)
B54: EVM Capital (1%) | K54: 0 | L54: =150+345 -> 495 | M54: 0 | N54: 0 | O54: =O13*0 -> 0 | P54: 78 | Q54: 0 | R54: 0 | S54: 50 | T54: =$Q13*0 -> 0 | U54: =$Q13*0 -> 0 | V54: =$Q13*0 -> 0 | W54: =$Q13*0 -> 0 | X54: =$X$13*0.01 -> 64.575 | Y54: =$X$13*0.01 -> 64.575 | Z54: =$X$13*0.01 -> 64.575 | AA54: =$X$13*0.01 -> 64.575 | AB54: =$X$13*0 -> 0 | AC54: =$X$13*0 -> 0 | AD54: =$X$13*0 -> 0 | AE54: =$X$13*0 -> 0 | AF54: =$X$13*0 -> 0 | AG54: =sum(2500,1200) -> 3700 | AH54: =sum(2500,500,5000) -> 8000 | AI54: =2000 -> 2000 | AJ54: =$X$13*0 -> 0 | AK54: =$X$13*0 -> 0 | AL54: =7000 -> 7000 | AM54: 3600 | AN54: 3500 | AO54: =$X$13*0 -> 0 | AP54: =6000 -> 6000 | AQ54: =$X$13*0 -> 0 | AR54: =$X$13*1 -> 6457.5 | AS54: =$X$13*0 -> 0 | AT54: =$X$13*0 -> 0 | AU54: 10000 | AV54: 0 | AW54: =$X$13*0 -> 0 | AX54: 1000 | AY54: 900 | AZ54: 900 | BA54: =-sum(3509,1490,500) -> -5499 | BB54: =-800 -> -800 | BC54: =sum(-800,-1200) -> -2000 | BD54: =sum(-800) -> -800 | BE54: =sum(-6200,-800) -> -7000 | BF54: =sum(-400,-7400,-25000) -> -32800 | BG54: =sum(-800,-5000) -> -5800 | BH54: =sum(-400,-400,-12000) -> -12800 | BI54: 0 | BJ54: 0 | BL54: 0 | BM54: 0 | BN54: 0 | BO54: 0 | BP54: 0 | BQ54: 0 | BR54: 0 | BS54: 0 | BT54: 0 | BU54: 0 | BV54: 0 | BW54: 0
B55: Common Stock (5%) | J55: 0 | K55: 0 | L55: 0 | M55: =M13*0 -> 0 | N55: 0 | O55: =O10*0 -> 0 | P55: 0 | Q55: =175+100 -> 275 | R55: =R13*0.0063 -> 41.94225 | S55: 300 | T55: =T13*0.02 -> 129.15 | U55: 120 | V55: 100 | W55: =sum(100,-790) -> -690 | X55: =$X$13*0.02 -> 129.15 | Y55: =$X$13*0.02 -> 129.15 | Z55: =$X$13*0.05 -> 322.875 | AA55: =$X$13*0.02 -> 129.15 | AB55: =$X$13*0.02 -> 129.15 | AC55: =$X$13*0.02 -> 129.15 | AD55: =$X$13*0.02 -> 129.15 | AE55: =$X$13*0.02 -> 129.15 | AF55: =$X$13*0.02 -> 129.15 | AG55: =$X$13*0 -> 0 | AH55: =$X$13*0 -> 0 | AI55: =$X$13*0.02 -> 129.15 | AJ55: =$X$13*0.02 -> 129.15 | AK55: =$X$13*0.02 -> 129.15 | AL55: =$X$13*0.02 -> 129.15 | AM55: =$X$13*0.02 -> 129.15 | AN55: =$X$13*0.02 -> 129.15 | AO55: =$X$13*0.02 -> 129.15 | AP55: =$X$13*0.02 -> 129.15 | ... AR55: =$X$13*0.02 -> 129.15 | AS55: 0 | AT55: =$X$13*0.02 -> 129.15 | AU55: =$X$13*0.02 -> 129.15 | AV55: =$X$13*0.02 -> 129.15 | AW55: =$X$13*0.02 -> 129.15 | AX55: 0 | AY55: 0 | AZ55: =$X$13*0.02 -> 129.15 | BA55: -400 | BB55: -400 | BC55: 0 | BD55: 0 | BE55: 0 | BF55: 0 | BG55: 0 | BH55: 0 | BI55: -400 | BJ55: -400 | BL55: -400 | BM55: -400 | BN55: -400 | BO55: -400 | BP55: -400 | BQ55: -400 | BR55: -400 | BS55: -400 | BT55: -400 | BU55: -400 | BV55: -400 | BW55: -400
B56: Crypto Portfolio (10%) | J56: 0 | K56: 0 | L56: 0 | M56: 0 | N56: 0 | O56: =O13*0 -> 0 | P56: 500 | Q56: =25+100+100+450 -> 675 | R56: =R13*0.065 -> 432.7375 | S56: 225 | T56: =T13*0.02 -> 129.15 | U56: 0 | V56: 200 | W56: 100 | X56: =$X$13*0.06 -> 387.45 | Y56: =$X$13*0.06 -> 387.45 | Z56: =$X$13*0.1 -> 645.75 | AA56: =AA13*0.1 -> 880 | AB56: =$X$13*0.07 -> 452.025 | AC56: =$X$13*0.06 -> 387.45 | AD56: =$X$13*0.08 -> 516.6 | AE56: =$X$13*0.06 -> 387.45 | AF56: =$X$13*0.06 -> 387.45 | AG56: =$X$13*0 -> 0 | AH56: =$X$13*0 -> 0 | AI56: =$X$13*0.078 -> 503.685 | AJ56: =$X$13*0.078 -> 503.685 | AK56: =$X$13*0.078 -> 503.685 | AL56: =$X$13*0.078 -> 503.685 | AM56: =$X$13*0.078 -> 503.685 | AN56: =$X$13*0.078 -> 503.685 | AO56: =$X$13*0.078 -> 503.685 | AP56: =$X$13*0.5 -> 3228.75 | AQ56: =$X$13*0.078 -> 503.685 | AR56: =$X$13*0.078 -> 503.685 | AS56: =$X$13*0.078 -> 503.685 | AT56: =$X$13*0.078 -> 503.685 | AU56: =$X$13*0.078 -> 503.685 | AV56: =$X$13*0.078 -> 503.685 | AW56: =$X$13*0.078 -> 503.685 | AX56: 0 | AY56: 0 | AZ56: =$X$13*0.078 -> 503.685 | BA56: -500 | BB56: -500 | BC56: 0 | BD56: 0 | BE56: 0 | BF56: 0 | BG56: 0 | BH56: 0 | BI56: -5000 | BJ56: -500 | BL56: -500 | BM56: -500 | BN56: -500 | BO56: -500 | BP56: -500 | BQ56: -500 | BR56: -500 | BS56: -500 | BT56: -500 | BU56: -500 | BV56: -500 | BW56: -500
B57: 401K IRA (2.5% Pre-Tax) | M57: =M4*0.03 -> 300 | N57: =N4*0.03 -> 300 | O57: =O12 -> 400 | P57: =P12 -> 400 | Q57: =Q12 -> 307.5 | R57: =R12 -> 307.5 | S57: =S12 -> 307.5 | T57: =T12 -> 307.5 | U57: =U12 -> 307.5 | V57: =V12 -> 307.5 | ... BB57: =BB12 -> 0 | BC57: 0 | BD57: 0 | BE57: 0 | BF57: 0 | BG57: =-0 -> 0 | BH57: =-0 -> 0 | BI57: =-250 -> -250 | BJ57: =-250 -> -250 | BL57: =-250 -> -250 | BM57: =-250 -> -250 | BN57: =-250 -> -250 | BO57: =-250 -> -250 | BP57: =-250 -> -250 | BQ57: =-250 -> -250 | BR57: =-250 -> -250 | BS57: =-250 -> -250 | ... BW57: =-250 -> -250
A58: Philanthropy (1%)
B59: Non-Profit (1%) | I59: 0 | J59: 0 | K59: =K14*0 -> 0 | L59: =L14*0 -> 0 | M59: 0 | N59: 0 | O59: =O13*0.01 -> 72 | P59: 0 | Q59: =70+20+20 -> 110 | R59: 0 | S59: 0 | T59: 125 | U59: 0 | V59: =V13*0.01 -> 67.575 | W59: =W13*0.01 -> 64.575 | X59: =X13*0.02 -> 129.15 | Y59: =Y13*0.02 -> 241.15 | Z59: =Z13*0.02 -> 176 | AA59: =AA13*0 -> 0 | AB59: =AB13*0.02 -> 176 | AC59: =AC13*0.01 -> 91.666667 | AD59: =AD13*0.01 -> 87.466667 | AE59: =AE13*0.01 -> 197.46667 | AF59: =AF13*0 -> 0 | AG59: =AG13*0 -> 0 | AH59: =AH13*0 -> 0 | AI59: =AI13*0.01 -> 84.666667 | AJ59: =AJ13*0.01 -> 84.666667 | AK59: =AK13*0.01 -> 187.75 | AL59: =AL13*0.01 -> 115.5 | AM59: =AM13*0.01 -> 115.5 | AN59: =AN13*0.01 -> 215.5 | AO59: =AO13*0 -> 0 | AP59: =1000 -> 1000 | AQ59: =AQ13*0.01 -> 115.5 | AR59: =AR13*0.01 -> 115.5 | AS59: 400 | AT59: 0 | AU59: =AU13*0.01 -> 277.5 | AV59: =AV13*0.01 -> 115.5 | AW59: =AW13*0.01 -> 115.5 | AX59: =AX13*0.01 -> 148.94 | AY59: =AY13*0 -> 0 | AZ59: =AZ13*0 -> 0 | BA59: =BA13*0 -> 0 | BB59: =-100 -> -100 | BC59: =-100 -> -100 | BD59: =-100 -> -100 | BE59: =-100 -> -100 | BF59: =-50 -> -50 | BG59: =-50 -> -50 | BH59: =-50 -> -50 | BI59: =-100 -> -100 | BJ59: =-100 -> -100 | BL59: =-100 -> -100 | BM59: =-100 -> -100 | BN59: =-100 -> -100 | BO59: =-100 -> -100 | BP59: =-100 -> -100 | BQ59: =-100 -> -100 | BR59: =-100 -> -100 | BS59: =-100 -> -100 | ... BW59: =-100 -> -100
A60: Total Financial Health | C60: =C13-C45-#REF!-C49+'BUDGET 2018 (Archive)'!O35 -> #REF! | D60: =D13-D45-#REF!-D49+'BUDGET 2018 (Archive)'!P35 -> #REF! | E60: =E13-E45-#REF!-E49+'BUDGET 2018 (Archive)'!Q35 -> #REF! | F60: =F13-F45-#REF!-F49+'BUDGET 2018 (Archive)'!R35 -> #REF! | G60: =G13-G45-#REF!-G49+'BUDGET 2018 (Archive)'!S35 -> #REF! | H60: =H13-H45-#REF!-H49+'BUDGET 2018 (Archive)'!T35 -> #REF! | I60: =H60+I13-I45-#REF!-#REF!-I49 -> #REF! | J60: =sum(J49:J59) -> 3200 | K60: =sum(K49:K59) -> 1000 | L60: =sum(L49:L59) -> 1495 | M60: =sum(M49:M56)+M59 -> 0 | N60: =sum(N49:N56)+N59 -> 1757.5 | O60: =sum(O49:O56)+O59 -> 2617 | P60: =sum(P49:P59) -> 6954 | Q60: =sum(Q49:Q56)+Q59 -> 3093 | R60: =sum(R49:R56)+R59 -> 3137.6797 | S60: =sum(S49:S56)+S59 -> 6675 | T60: =sum(T49:T56)+T59 -> 2126.825 | U60: =sum(U49:U56)+U59 -> 2952.9052 | V60: =sum(V49:V56)+V59 -> 3964.575 | W60: =sum(W49:W56)+W59 -> 1611.825 | X60: =sum(X49:X57) -> 2051.025 | Y60: =sum(Y49:Y57) -> 2546.45 | Z60: =sum(Z49:Z57) -> 3204.7 | AA60: =sum(AA49:AA57) -> 4474.9525 | AB60: =sum(AB49:AB57) -> 2793.2 | AC60: =sum(AC49:AC57) -> 3135.2917 | AD60: =sum(AD49:AD57) -> 3208.625 | AE60: =sum(AE49:AE57) -> 14799.423 | ... AO60: =sum(AO49:AO57) -> 2533.585 | AP60: =sum(AP49:AP59) -> 28003.65 | AQ60: =sum(AQ49:AQ57) -> 2433.585 | AR60: =sum(AR49:AR57) -> 11201.085 | AS60: =sum(AS49:AS57) -> 4291.56 | AT60: =sum(AT49:AT57) -> 9429.14 | AU60: =sum(AU49:AU57) -> 16828.585 | AV60: =sum(AV49:AV57) -> 2433.585 | AW60: =sum(AW49:AW57) -> 4640.71 | AX60: =sum(AX49:AX57) -> 4489.4 | ... AZ60: =sum(AZ49:AZ57) -> 17855.71 | BA60: =sum(BA49:BA59) -> -21399 | BB60: =sum(BB49:BB59) -> -4200 | BC60: =sum(BC49:BC59) -> -7200 | BD60: =sum(BD49:BD59) -> -3400 | BE60: =sum(BE49:BE59) -> -9600 | BF60: =sum(BF49:BF59) -> -37950 | BG60: =sum(BG49:BG59) -> -10450 | BH60: =sum(BH49:BH59) -> -25450 | ... BJ60: =sum(BJ49:BJ59) -> -1650 | BL60: =sum(BL49:BL59) -> -1650 | BM60: =sum(BM49:BM59) -> -1650 | BN60: =sum(BN49:BN59) -> -1650 | BO60: =sum(BO49:BO59) -> -1650 | BP60: =sum(BP49:BP59) -> -1650 | BQ60: =sum(BQ49:BQ59) -> -1650 | BR60: =sum(BR49:BR59) -> -1650 | BS60: =sum(BS49:BS59) -> -1650 | ... BW60: =sum(BW49:BW59) -> -1650
A63: Total Remaining | J63: =J13-#REF!-J45-J60 -> #REF! | K63: =K13-#REF!-K45-K60 -> #REF! | L63: =L13-#REF!-L45-L60+K63 -> #REF! | M63: =M13-#REF!-M45-M60+L63 -> #REF! | N63: =N13-N45-N60 -> 2020.5 | O63: =N63+O13-O45-O60 -> 4252.5 | P63: =P13-P45-P60+P57 -> 297.06227 | Q63: =Q13-Q45-Q60+Q57+P63 -> 575.28053 | R63: =R13-R45-R60+R57+Q63 -> 608.50171 | S63: =S13-S45-S60+S57+100 -> 513.05006 | T63: =T13-T45-T60+T57+S63 -> -1066.8954 | U63: =U13-U45-U60+U57+T63 -> 890.10957 | V63: =V13-V45-V60+V57+U63 -> -739.75488 | W63: =W13-W45-W60+W57+V63 -> 1252.1634 | X63: =X13-X45-X60+X57 -> -1951.5103 | Y63: =Y13-Y45-Y60+Y57+X63 -> 2803.5647 | Z63: =Z13-Z45-Z60+Z57+Y63 -> 1629.2147 | AA63: =AA13-AA45-AA60+AA57+Z63 -> -869.72783 | AB63: =AB13-AB45-AB60+AB57+AA63 -> 179.50717 | AC63: =AC13-AC45-AC60+AC57+AB63 -> 385.65051 | AD63: =AD13-AD45-AD60+AD57+AC63 -> 1618.4605 | AE63: =AE13-AE45-AE60+AE57+AD63 -> 1760.473 | AF63: =AF13-AF45-AF60+AF57+AE63 -> 3168.808 | ... AH63: =AH13-AH45-AH60+AH57+AG63 -> 6756.653 | AI63: =AI13-AI45-AI60+AI57+AG63 -> 1457.4597 | AJ63: =AJ13-AJ45-AJ60+AJ57 -> 318.71667 | AK63: =AK13-AK45-AK60+AK57 -> 8470.725 | AL63: =AL13-AL45-AL60+AL57+AK63 -> 1168.45 | AM63: =AM13-AM45-AM60+AM57+AL63 -> 501.675 | AN63: =AN13-AN45-AN60+AN57+AM63 -> 2289.09 | AO63: =AO13-AO45-AO60+AO57+AN63 -> 5941.505 | AP63: =AP13-AP45-AP60+AP57+AO63 -> 2198.855 | AQ63: =AQ13-AQ45-AQ60+AQ57+AP63 -> 4926.27 | AR63: =AR13-AR45-AR60+AR57+AQ63 -> -1113.815 | AS63: =AS13-AS45-AS60+AS57+AR63 -> -272.375 | ... AU63: =AU13-AU45-AU60+AU57+AT63 -> 4643.01 | AV63: =0 -> 0 | AW63: =AW13-AW45-AW60+AW57 -> 0.29 | AX63: =AX13-AX45-AX60+AX57 -> 2995.6 | AY63: =AY13-AY45-AY60+AY57 -> 5106 | AZ63: =AZ13-AZ45-AZ60+AZ57+AY63 -> 6566.29 | BA63: =sum(BA13,BA45,BA60) -> 2484 | BB63: =sum(BB13,BB45,BB60,BA63) -> 2167 | BC63: =sum(BC13,BC45,BC60,BB63) -> -350 | BD63: =sum(BD13,BD45,BD60,BC63) -> -7263 | BE63: =sum(BE13,BE45,BE60,BD63) -> -14280 | BF63: =sum(BF13,BF45,BF60) -> 883 | BG63: =sum(BG13,BG45,BG60,BF63) -> 1581 | BH63: =sum(BH13,BH45,BH60,BG63) -> 3164 | BI63: =sum(BI13,BI45,BI60,BH63) -> 39647 | BJ63: =sum(BJ13,BJ45,BJ60,BI63) -> 30830 | BL63: =sum(BL13,BL45,BL60,BJ63) -> 32013 | BM63: =sum(BM13,BM45,BM60,BL63) -> 32396 | BN63: =sum(BN13,BN45,BN60,BM63) -> 35779 | BO63: =sum(BO13,BO45,BO60,BN63) -> 39162 | BP63: =sum(BP13,BP45,BP60,BO63) -> 41445 | BQ63: =sum(BQ13,BQ45,BQ60,BP63) -> 44828 | BR63: =sum(BR13,BR45,BR60,BQ63) -> 49011 | BS63: =sum(BS13,BS45,BS60,BR63) -> 53194 | BT63: =sum(BT13,BT45,BT60,BS63) -> 56877 | ... BW63: =sum(BW13,BW45,BW60,BV63) -> 68726

Sheet GOAL
A1: Categories | C1: Jan | D1: Feb | E1: Mar | F1: Apr | G1: May | H1: Jun | I1: Jul '19 | J1: Aug '19 | K1: Sept '19 | L1: Oct '19 | M1: Nov '19 | N1: Dec '19 | O1: Jan '20 | P1: Feb '20 | Q1: Mar '20 | R1: Apr '20 | S1: May '20 | T1: Jun '20 | U1: Jul '20 | V1: Aug '20 | W1: Sep '20 | X1: Oct '20 | Y1: Nov '20 | Z1: Dec '20 | AA1: Jan '21 | AB1: Feb'21 | AC1: Mar '21 | AD1: Apr '21 | AE1: May '21 | AF1: Jun '21 | AG1: Jul '21 | AH1: Aug '21 | AI1: Sept '21 | AJ1: Oct '21 | AK1: Nov '21 | AL1: Dec '21 | AM1: Jan '22 | AN1: Feb '22 | AO1: Mar '22 | AP1: Apr '22 | AQ1: May '22 | AR1: Jun '22 | AS1: July '22 | AT1: Aug '22 | AU1: Sept '22 | AV1: Oct '22 | AW1: Nov '22 | AX1: Dec '22 | AY1: Jan '23 | AZ1: Feb '23 | BA1: Mar '23 | BB1: Apr '23 | BC1: May '23 | BD1: Jun '23 | BE1: Jul '23 | BF1: Jul '23 | BG1: Aug '23 | BH1: Sept '23 | BI1: Oct '23 | BJ1: Nov '23 | BK1: Dec '23
A2: Income
A3: Salary
B4: Salary (Pre-Tax of 34%) | C4: 10000 | D4: 10000 | E4: 10000 | F4: 10000 | G4: 10000 | H4: 10000 | I4: 10000 | J4: =120000/12 -> 10000 | K4: =120000/12 -> 10000 | L4: =120000/12 -> 10000 | M4: =120000/12 -> 10000 | N4: =120000/12 -> 10000 | O4: =120000/12 -> 10000 | P4: =120000/12 -> 10000 | Q4: =123000/12 -> 10250 | R4: =123000/12 -> 10250 | S4: =123000/12 -> 10250 | T4: =123000/12 -> 10250 | U4: =123000/12 -> 10250 | V4: =123000/12 -> 10250 | W4: =123000/12 -> 10250 | X4: =123000/12 -> 10250 | Y4: =123000/12 -> 10250 | Z4: =160000/12 -> 13333.333 | AA4: =160000/12 -> 13333.333 | AB4: =160000/12 -> 13333.333 | AC4: =160000/12 -> 13333.333 | AD4: =160000/12 -> 13333.333 | AE4: =160000/12 -> 13333.333 | AF4: =160000/12 -> 13333.333 | AG4: =160000/12 -> 13333.333 | ... AJ4: =160000/12 -> 13333.333 | AK4: =165000/12 -> 13750 | AL4: =210000/12 -> 17500 | AM4: =210000/12 -> 17500 | AN4: =210000/12 -> 17500 | AO4: =210000/12 -> 17500 | AP4: =210000/12 -> 17500 | AQ4: =210000/12 -> 17500 | AR4: =210000/12 -> 17500 | AS4: =210000/12 -> 17500 | ... AZ4: =210000/12 -> 17500 | BA4: =200000/12 -> 16666.667 | BB4: =200000/12 -> 16666.667 | BC4: =200000/12 -> 16666.667 | BD4: =200000/12 -> 16666.667 | BE4: =250000/12 -> 20833.333 | BF4: =250000/12 -> 20833.333 | BG4: =sum(1000000/12) -> 83333.333 | BH4: =sum(1000000/12) -> 83333.333 | BI4: =sum(1000000/12) -> 83333.333 | BJ4: =sum(1000000/12) -> 83333.333 | BK4: =sum(1000000/12) -> 83333.333
B5: Freelance (Taxed at 41%) | C5: 0 | D5: 3000 | E5: 0 | F5: 0 | G5: 0 | H5: 0 | I5: 5000 | J5: 5000 | K5: 0 | L5: 0 | M5: 800 | N5: =500 -> 500 | O5: 0 | P5: =5000 -> 5000 | Q5: 0 | R5: 0 | S5: 0 | T5: 0 | U5: 0 | V5: 0 | W5: 0 | X5: 0 | Y5: 0 | Z5: 0 | AA5: 0 | AB5: 0 | AC5: 0 | AD5: 0 | AE5: 0 | AF5: 0 | AG5: 0 | AH5: 0 | AI5: 0 | AJ5: 0 | AK5: 0 | AL5: 0 | AM5: 0 | AN5: 0 | AO5: 0 | AP5: 0 | AQ5: 0 | AR5: 0 | AS5: 0 | AT5: 0 | AU5: 0 | AV5: 0 | AW5: 0 | AX5: 0 | AY5: 0 | AZ5: 0 | BA5: 0 | BB5: 0 | BC5: 0 | BD5: 0 | BF5: 0 | BG5: 0 | BH5: 0 | BI5: 0 | BJ5: 0 | BK5: 0
A6: Freelance
B7: Secondary Income (Taxed @ 34%) | C7: 0 | D7: 0 | E7: 0 | F7: 0 | G7: 0 | H7: 0 | I7: 0 | J7: 0 | K7: 0 | L7: 0 | M7: 0 | N7: 0 | O7: 0 | P7: 0 | Q7: 0 | R7: 0 | S7: 0 | T7: =S7+S7*0.15 -> 0 | U7: =T7+T7*0.15 -> 0 | V7: =U7+U7*0.15 -> 0 | W7: =V7+V7*0.15 -> 0 | X7: 0 | Y7: 0 | Z7: =Y7+Y7*0.1 -> 0 | AA7: =Z7+Z7*0.1 -> 0 | AB7: =AA7+AA7*0.1 -> 0 | AC7: =AB7+AB7*0.1 -> 0 | AD7: =AC7+AC7*0.1 -> 0 | AE7: =AD7+AD7*0.1 -> 0 | AF7: =AE7+AE7*0.1 -> 0 | AG7: =AF7+AF7*0.1 -> 0 | AH7: =AG7+AG7*0.1 -> 0 | AI7: =AG7+AG7*0.1 -> 0 | AJ7: =AH7+AH7*0.1 -> 0 | AK7: =AJ7+AJ7*0.1 -> 0 | AL7: =AK7+AK7*0.1 -> 0 | AM7: =AL7+AL7*0.1 -> 0 | AN7: =AM7+AM7*0.1 -> 0 | AO7: =AN7+AN7*0.1 -> 0 | AP7: =AO7+AO7*0.1 -> 0 | AQ7: =AP7+AP7*0.1 -> 0 | AR7: =AQ7+AQ7*0.1 -> 0 | ... AT7: =AS7+AS7*0.1 -> 0 | AU7: 0 | AV7: 0 | AW7: 0 | AX7: 0 | AY7: 0 | AZ7: 0 | BA7: 0 | BB7: 0 | BC7: 0 | BD7: 0 | BE7: =sum(50000/12) -> 4166.6667 | BF7: =sum(50000/12) -> 4166.6667 | BG7: =sum(50000/12) -> 4166.6667 | BH7: =sum(50000/12) -> 4166.6667 | BI7: =sum(50000/12) -> 4166.6667 | BJ7: =sum(50000/12) -> 4166.6667 | BK7: =sum(50000/12) -> 4166.6667
B8: Non-taxed Income | O8: =1000 -> 1000 | P8: =2723 -> 2723 | Q8: 419 | R8: =200 -> 200 | S8: =900+2500 -> 3400 | T8: 0 | U8: 0 | V8: 300 | W8: 0 | X8: 0 | Y8: 5600 | Z8: 0 | AA8: 0 | AB8: 0 | AC8: 700 | AD8: 0 | AE8: 11000 | AF8: 1300 | AG8: =sum(1200,1200) -> 2400 | AH8: =sum(7000,10000) -> 17000 | AI8: 0 | AJ8: 0 | AK8: =2000+7700 -> 9700 | AL8: 0 | AM8: 0 | AN8: 10000 | AO8: 1000 | AP8: 21000 | AQ8: 0 | AR8: 0 | AS8: 0 | AT8: =sum(4751.11) -> 4751.11 | AU8: =36000*0.45 -> 16200 | AV8: 0 | AW8: 0 | AX8: =SUM(1500,1844) -> 3344 | AY8: =sum(1000,1800) -> 2800 | AZ8: 16000 | BA8: 20000 | BB8: 0 | BC8: 0 | BD8: 300000 | BE8: 0 | BF8: 0 | BG8: =sum(100000) -> 100000 | BH8: 0 | BI8: 0 | BJ8: 0 | BK8: 0
A10: Total Income | C10: =sum(C4:C7) -> 10000 | D10: =sum(D4:D7) -> 13000 | E10: =sum(E4:E7) -> 10000 | F10: =sum(F4:F7) -> 10000 | G10: =sum(G4:G7) -> 10000 | H10: =sum(H4:H7) -> 10000 | I10: =sum(I4:I7) -> 15000 | J10: =sum(J4:J7) -> 15000 | ... O10: =sum(O4:O7) -> 10000 | P10: =sum(P4:P8) -> 17723 | Q10: =sum(Q4:Q8) -> 10669 | R10: =sum(R4:R8) -> 10450 | S10: =sum(S4:S8) -> 13650 | T10: =sum(T4:T8) -> 10250 | U10: =sum(U4:U8) -> 10250 | V10: =sum(V4:V8) -> 10550 | W10: =sum(W4:W8) -> 10250 | ... BK10: =sum(BK4:BK8) -> 87500
A11: Tax + Withholding | C11: =C10*0.38 -> 3800 | D11: =D10*0.34 -> 4420 | E11: =E10*0.34 -> 3400 | F11: =F10*0.34 -> 3400 | G11: =G10*0.34 -> 3400 | H11: =H10*0.34 -> 3400 | I11: =I10*0.34 -> 5100 | J11: =J10*0.34 -> 5100 | K11: =K10*0.34 -> 3400 | L11: =L10*0.34 -> 3400 | M11: =sum(M4:M7)*0.34 -> 3672 | N11: =sum(N4:N7)*0.34 -> 3570 | O11: =sum(O4:O7)*0.34+O5*0.41 -> 3400 | P11: =P4*0.34+P5*0.41+P7*0.34 -> 5450 | Q11: =sum(Q4:Q7)*0.34+Q5*0.41 -> 3485 | R11: =sum(R4:R7)*0.34+R5*0.41 -> 3485 | S11: =sum(S4:S7)*0.34+S5*0.41 -> 3485 | T11: =sum(T4:T7)*0.34+T5*0.41 -> 3485 | U11: =sum(U4:U7)*0.34+U5*0.41 -> 3485 | V11: =sum(V4:V7)*0.34+V5*0.41 -> 3485 | W11: =sum(W4:W7)*0.34+W5*0.41 -> 3485 | X11: =sum(X4:X7)*0.34+X5*0.41 -> 3485 | ... BK11: =sum(BK4:BK7)*0.34+BK5*0.41 -> 29750
A12: 401k Contribution | O12: =O4*0.04 -> 400 | P12: =P4*0.04 -> 400 | Q12: =Q4*0.03 -> 307.5 | R12: =R4*0.03 -> 307.5 | S12: =S4*0.03 -> 307.5 | T12: =T4*0.03 -> 307.5 | U12: =U4*0.03 -> 307.5 | V12: =V4*0.03 -> 307.5 | W12: =W4*0.03 -> 307.5 | X12: =X4*0.03 -> 307.5 | Y12: =Y4*0.03 -> 307.5 | Z12: =Z4*0 -> 0 | AA12: =AA4*0 -> 0 | AB12: 0 | AC12: =AC4*0.025 -> 333.33333 | AD12: =AD4*0.004 -> 53.333333 | AE12: =AE4*0.004 -> 53.333333 | AF12: =AF4*0 -> 0 | AG12: =AG4*0 -> 0 | AH12: =AH4*0 -> 0 | AI12: =AI4*0.025 -> 333.33333 | AJ12: =AJ4*0.025 -> 333.33333 | AK12: =AK4*0 -> 0 | AL12: =AL4*0 -> 0 | AM12: =AM4*0 -> 0 | AN12: =AN4*0 -> 0 | AO12: =AO4*0 -> 0 | AP12: =AP4*0 -> 0 | AQ12: =AQ4*0 -> 0 | AR12: =AR4*0 -> 0 | ... BK12: =BK4*0 -> 0
A13: Net Take Home | C13: =C10-C11+C5 -> 6200 | D13: =D10-D11+D5 -> 11580 | E13: =E10-E11+E5 -> 6600 | F13: =F10-F11+F5 -> 6600 | G13: =G10-G11+G5 -> 6600 | H13: =H10-H11+H5 -> 6600 | I13: =I10-I11+I5 -> 14900 | J13: =J10-J11+J5 -> 14900 | ... L13: =L10-L11+L5 -> 6600 | M13: =M10-M11 -> 7128 | N13: =N10-N11 -> 6930 | O13: =O4+O7+O5-O11-O12+O8 -> 7200 | P13: =P10-P11-P12 -> 11873 | Q13: =Q10-Q11-Q12 -> 6876.5 | R13: =R10-R11-R12 -> 6657.5 | S13: =S10-S11-S12 -> 9857.5 | T13: =T10-T11-T12 -> 6457.5 | U13: =U10-U11-U12 -> 6457.5 | V13: =V10-V11-V12 -> 6757.5 | W13: =W10-W11-W12 -> 6457.5 | ... BK13: =BK10-BK11-BK12 -> 57750
A15: Expenses (60%)
A16: Fixed Costs (40%)
A17: Home | B17: Rent | C17: 1450 | D17: 1450 | E17: 1450 | F17: 1450 | G17: 1450 | H17: =1450+350 -> 1800 | I17: =1853+569 -> 2422 | J17: 0 | K17: 1000 | L17: =3383-1500 -> 1883 | M17: =1954 -> 1954 | N17: 1900 | O17: 1900 | P17: 1900 | Q17: 1900 | R17: 1921 | S17: 1921 | T17: =1921 -> 1921 | U17: 120 | V17: =120+700 -> 820 | W17: =sum(120+700) -> 820 | X17: =sum(336,1740) -> 2076 | Y17: =sum(1740) -> 1740 | Z17: 1571.7 | AA17: =sum(1740) -> 1740 | AB17: =sum(1740) -> 1740 | AC17: =sum(1740) -> 1740 | AD17: =sum(1740) -> 1740 | AE17: =sum(1740) -> 1740 | AF17: =sum(1740) -> 1740 | AG17: =sum(1740) -> 1740 | AH17: =sum(4000,1700) -> 5700 | AI17: =sum(2000) -> 2000 | AJ17: =sum(2700) -> 2700 | AK17: =sum(2700) -> 2700 | AL17: =sum(2700) -> 2700 | AM17: =sum(2700) -> 2700 | AN17: =sum(2700) -> 2700 | AO17: =sum(2700) -> 2700 | AP17: =sum(2700) -> 2700 | AQ17: =sum(2700) -> 2700 | ... AT17: =sum(2700) -> 2700 | AU17: =sum(2800) -> 2800 | AV17: =sum(2800) -> 2800 | AW17: =sum(2800) -> 2800 | AX17: =sum(2800) -> 2800 | AY17: =sum(2800) -> 2800 | AZ17: =sum(2800) -> 2800 | BA17: =sum(2800) -> 2800 | BB17: =sum(2800) -> 2800 | ... BK17: =sum(2800) -> 2800
B18: Renters Insurance | C18: 9 | D18: 9 | E18: 9 | F18: 9 | G18: 9 | H18: 9 | I18: 9 | J18: =18.42/2 -> 9.21 | K18: =18.42/2 -> 9.21 | L18: =18.42/2 -> 9.21 | M18: 11 | N18: =18.42/2 -> 9.21 | O18: =18.42/2 -> 9.21 | P18: =18.42/2 -> 9.21 | Q18: =18.42/2 -> 9.21 | R18: =18.42/2 -> 9.21 | S18: =18.42/2 -> 9.21 | T18: =18.42/2 -> 9.21 | U18: 0 | V18: 0 | W18: 0 | X18: 0 | Y18: 0 | Z18: 0 | AA18: 9 | AB18: 9 | AC18: 0 | AD18: 0 | AE18: 0 | AF18: 0 | AG18: 0 | AH18: 0 | AI18: 0 | AJ18: 0 | AK18: 0 | AL18: 0 | AM18: 0 | AN18: 0 | AO18: 0 | AP18: 0 | AQ18: 0 | AR18: 0 | AS18: 0 | AT18: 0 | AU18: 0 | AV18: 0 | AW18: 0 | AX18: 0 | AY18: 0 | AZ18: 0 | BA18: 0 | BB18: 0 | BC18: 0 | BD18: 0 | BE18: 0 | BF18: 0 | BG18: 0 | BH18: 0 | BI18: 0 | BJ18: 0 | BK18: 0
B19: Utilities | I19: 100 | J19: 35 | K19: 90 | L19: =90 -> 90 | M19: 20 | N19: 90 | O19: 90 | P19: 90 | Q19: 90 | R19: 90 | S19: 90 | T19: 90 | U19: 0 | V19: 0 | W19: 0 | X19: 0 | Y19: 90 | Z19: 90 | AA19: 90 | AB19: 90 | AC19: 90 | AD19: 90 | AE19: 90 | AF19: 90 | AG19: 90 | AH19: 90 | AI19: 90 | AJ19: 90 | AK19: 90 | AL19: 90 | AM19: 90 | AN19: 90 | AO19: 90 | AP19: 90 | AQ19: 90 | AR19: 90 | AS19: 90 | AT19: 90 | AU19: 90 | AV19: 90 | AW19: 90 | AX19: 90 | AY19: 90 | AZ19: 90 | BA19: 90 | BB19: 90 | BC19: 90 | BD19: 90 | BE19: 90 | BF19: 90 | BG19: 90 | BH19: 90 | BI19: 90 | BJ19: 90 | BK19: 90
B20: Wifi | C20: =62.95/2 -> 31.475 | D20: =62.95/2 -> 31.475 | E20: =62.95/2 -> 31.475 | F20: =62.95/2 -> 31.475 | G20: =62.95/2 -> 31.475 | H20: =62.95/2 -> 31.475 | I20: =62.95/2 -> 31.475 | J20: =62.95/2 -> 31.475 | ... T20: =62.95/2 -> 31.475 | U20: 0 | V20: 0 | W20: 0 | X20: 0 | Y20: =62.95/2 -> 31.475 | Z20: =91/2 -> 45.5 | AA20: =62.95/2 -> 31.475 | AB20: =62.95/2 -> 31.475 | AC20: =62.95/2 -> 31.475 | AD20: =62.95/2 -> 31.475 | AE20: =62.95/2 -> 31.475 | AF20: =62.95/2 -> 31.475 | AG20: =62.95/2 -> 31.475 | AH20: =0 -> 0 | AI20: =100/2 -> 50 | AJ20: =100/2 -> 50 | AK20: =100/2 -> 50 | AL20: =100/2 -> 50 | AM20: =100/2 -> 50 | AN20: =100/2 -> 50 | AO20: =100/2 -> 50 | AP20: =100/2 -> 50 | ... BK20: =100/2 -> 50
B21: Groceries | I21: 400 | J21: =75*4 -> 300 | K21: =50*4 -> 200 | L21: =55*4 -> 220 | M21: =55*4 -> 220 | N21: =55*4 -> 220 | O21: =55*4 -> 220 | P21: =60*4 -> 240 | Q21: =200+150+250 -> 600 | R21: =195+200+150 -> 545 | S21: =100*4 -> 400 | T21: =60*4 -> 240 | U21: =60*4 -> 240 | V21: =60*4 -> 240 | W21: =60*4 -> 240 | X21: =60*4 -> 240 | Y21: =60*4 -> 240 | Z21: =60*4 -> 240 | AA21: =60*4 -> 240 | ... AJ21: =60*4 -> 240 | AK21: =100*4 -> 400 | AL21: =100*4 -> 400 | AM21: =100*4 -> 400 | AN21: =100*4 -> 400 | AO21: =100*4 -> 400 | AP21: =100*4 -> 400 | AQ21: =100*4 -> 400 | AR21: =100*4 -> 400 | ... BK21: =100*4 -> 400
A22: Phone | B22: Phone Bill | E22: 100 | F22: 128.79 | G22: 120 | H22: =120+500 -> 620 | I22: 120.64 | J22: 120.64 | K22: 120.64 | L22: 150 | M22: 120.64 | N22: 120.64 | O22: 120 | P22: 120 | Q22: 120 | R22: 120 | S22: 120 | T22: 120 | U22: 120 | V22: 120 | W22: 120 | X22: 120 | Y22: 150 | Z22: 185.09 | AA22: 185.09 | AB22: 185.09 | AC22: 185.09 | AD22: 185.09 | AE22: 185.09 | AF22: 185.09 | AG22: 185.09 | AH22: 185.09 | AI22: 185.09 | AJ22: 185.09 | AK22: 0 | AL22: 0 | AM22: 0 | AN22: 0 | AO22: 0 | AP22: 0 | AQ22: 0 | AR22: 0 | AS22: 0 | AT22: 0 | AU22: 0 | AV22: 0 | AW22: 150 | AX22: 150 | AY22: 150 | AZ22: 150 | BA22: 150 | BB22: 150 | BC22: 150 | BD22: 150 | BE22: 150 | BF22: 150 | BG22: 150 | BH22: 150 | BI22: 150 | BJ22: 150 | BK22: 150
A23: Car | B23: Car | N23: 0 | O23: 0 | P23: 0 | Q23: 0 | R23: 0 | S23: 0 | T23: 200 | U23: 0 | V23: =sum(116,60,300,300) -> 776 | W23: =sum(343,60,75) -> 478 | X23: =sum(343,180,150) -> 673 | Y23: =sum(343,180,100) -> 623 | Z23: =sum(343,180,100) -> 623 | AA23: =sum(343,180,100) -> 623 | AB23: =sum(343,180,100) -> 623 | AC23: =sum(343,180,100) -> 623 | AD23: =sum(343,180,100) -> 623 | AE23: =sum(343,180,100) -> 623 | AF23: =sum(343,180,100) -> 623 | ... AH23: =sum(343,180,100) -> 623 | AI23: 400 | AJ23: 0 | AK23: 0 | AL23: 175 | AM23: 0 | AN23: 0 | AO23: 0 | AP23: 0 | AQ23: 0 | AR23: 0 | AS23: 0 | AT23: 0 | AU23: 0 | AV23: 0 | AW23: 0 | AX23: 0 | AY23: 0 | AZ23: 0 | BA23: 0 | BB23: 0 | BC23: 0 | BD23: 0 | BE23: 0 | BF23: 0 | BG23: 0 | BH23: 0 | BI23: 0 | BJ23: 0 | BK23: 0
A24: Transportation | B24: Ridesharing | J24: =170*4-20 -> 660 | K24: =22*7*4 -> 616 | L24: =22*7*4 -> 616 | M24: =20*4*4 -> 320 | N24: =20*4*4 -> 320 | O24: =15*7*4 -> 420 | P24: =15*30 -> 450 | Q24: =15*5 -> 75 | R24: =10*4 -> 40 | S24: =10*4 -> 40 | T24: =10*20 -> 200 | U24: =10*10 -> 100 | V24: 0 | W24: 0 | X24: 25 | Y24: 25 | Z24: 25 | AA24: 25 | AB24: 25 | AC24: 25 | AD24: 25 | AE24: 25 | AF24: 25 | AG24: 25 | AH24: 100 | AI24: 200 | AJ24: 100 | AK24: 100 | AL24: 100 | AM24: 100 | AN24: 100 | AO24: 100 | AP24: 100 | AQ24: 100 | AR24: 100 | AS24: 100 | AT24: 100 | AU24: 100 | AV24: 100 | AW24: 100 | AX24: 100 | AY24: 100 | AZ24: 100 | BA24: 100 | BB24: 100 | BC24: 100 | BD24: 100 | BE24: 100 | BF24: 100 | BG24: 100 | BH24: 100 | BI24: 100 | BJ24: 100 | BK24: 100
B25: Metro | C25: 200 | D25: 200 | E25: 100 | F25: 200 | G25: 200 | H25: 200 | I25: =8*4*4+20*4 -> 208 | J25: =8*7*4 -> 224 | K25: =8*4*4 -> 128 | L25: =8*7*4 -> 224 | M25: =8*4*4 -> 128 | N25: =8*5*4 -> 160 | O25: =8*7*4 -> 224 | P25: =8*5*4 -> 160 | Q25: =40 -> 40 | R25: =0 -> 0 | S25: =0 -> 0 | T25: 0 | U25: 0 | V25: 0 | W25: 0 | X25: 0 | Y25: 0 | Z25: 0 | AA25: 0 | AB25: 0 | AC25: 0 | AD25: 0 | AE25: 0 | AF25: 0 | AG25: 0 | AH25: 50 | AI25: 50 | AJ25: 50 | AK25: 50 | AL25: 50 | AM25: 25 | AN25: 25 | AO25: 25 | AP25: 50 | AQ25: 50 | AR25: 50 | AS25: 50 | AT25: 50 | AU25: 50 | AV25: 50 | AW25: 50 | AX25: 50 | AY25: 50 | AZ25: 50 | BA25: 50 | BB25: 50 | BC25: 50 | BD25: 50 | BE25: 50 | BF25: 50 | BG25: 50 | BH25: 50 | BI25: 50 | BJ25: 50 | BK25: 50
P26: =sum(P17:P25)/P13 -> 0.25273183 | Q26: =sum(Q17:Q25)/Q13 -> 0.41673598 | R26: =sum(R17:R25)/R13 -> 0.4140721 | S26: =sum(S17:S25)/S13 -> 0.26494395 | T26: =sum(T17:T25)/T13 -> 0.43541386 | U26: =sum(U17:U25)/U13 -> 0.089818041 | V26: =sum(V17:V25)/V13 -> 0.28945616 | W26: =sum(W17:W25)/W13 -> 0.25675571 | ... BK26: =sum(BK17:BK25)/BK13 -> 0.063030303
A27: Variable Costs (20%)
A28: Guilt Free | B28: Safe to Spend - Weekdays | C28: 1150 | D28: 1000 | E28: 1000 | F28: 1120 | G28: 1000 | H28: 500 | I28: =160*4 -> 640 | J28: =125*4 -> 500 | K28: =25*7*4 -> 700 | L28: =50*7*4 -> 1400 | M28: =25*7*4 -> 700 | N28: 1500 | O28: =30*5*4 -> 600 | P28: =30*20 -> 600 | Q28: =20*10 -> 200 | R28: =10*20 -> 200 | S28: =5*20 -> 100 | T28: =20*20 -> 400 | U28: =15*20 -> 300 | V28: =15*20 -> 300 | W28: =15*20 -> 300 | X28: =15*20 -> 300 | Y28: =50*20 -> 1000 | Z28: =45*20 -> 900 | AA28: =25*20 -> 500 | AB28: =25*20 -> 500 | AC28: =45*20 -> 900 | AD28: =25*20 -> 500 | AE28: =25*20 -> 500 | AF28: =25*20 -> 500 | AG28: =25*20 -> 500 | AH28: =25*20 -> 500 | AI28: =45*20 -> 900 | AJ28: =45*20 -> 900 | AK28: =45*20 -> 900 | AL28: =75*20 -> 1500 | AM28: =75*20 -> 1500 | AN28: =75*20 -> 1500 | AO28: =75*20 -> 1500 | AP28: =150*20 -> 3000 | AQ28: =75*20 -> 1500 | AR28: =75*20 -> 1500 | AS28: =75*20 -> 1500 | AT28: =75*20 -> 1500 | AU28: =75*20 -> 1500 | AV28: =75*20 -> 1500 | AW28: =75*20 -> 1500 | AX28: =75*20 -> 1500 | ... BK28: =75*20 -> 1500
B29: Safe to Spend - Weekends | I29: =100*4 -> 400 | J29: =200*4 -> 800 | K29: =50*2*2*4 -> 800 | L29: =50*2*2*4 -> 800 | M29: =40*2*4 -> 320 | N29: =50*2*4 -> 400 | O29: =50*2*4 -> 400 | P29: =100*4 -> 400 | Q29: =45*2 -> 90 | R29: =20*8 -> 160 | S29: =30*8 -> 240 | T29: =45*8 -> 360 | U29: =20*8 -> 160 | V29: =45*8 -> 360 | W29: =40*8 -> 320 | X29: =40*8 -> 320 | Y29: =100*8 -> 800 | Z29: =100*8 -> 800 | AA29: =100*8 -> 800 | AB29: =100*8+300 -> 1100 | AC29: =100*8 -> 800 | AD29: =75*8 -> 600 | AE29: =75*8 -> 600 | AF29: =75*8 -> 600 | AG29: =75*8 -> 600 | AH29: =75*8 -> 600 | AI29: =100*10 -> 1000 | AJ29: =100*8 -> 800 | AK29: =100*8 -> 800 | AL29: =100*8 -> 800 | AM29: =100*8 -> 800 | AN29: =100*8 -> 800 | AO29: =100*8 -> 800 | AP29: =150*8 -> 1200 | AQ29: =100*8 -> 800 | AR29: =100*8 -> 800 | AS29: =100*8 -> 800 | AT29: =100*8 -> 800 | AU29: =100*8 -> 800 | AV29: =100*8 -> 800 | AW29: =100*8 -> 800 | AX29: =100*8 -> 800 | ... BK29: =100*8 -> 800
B30: Entertainment | C30: 0 | D30: 0 | E30: 0 | F30: 0 | G30: 0 | H30: 0 | I30: 0 | J30: 0 | K30: 0 | L30: 0 | M30: 0 | N30: 200 | O30: 400 | P30: 0 | Q30: 0 | R30: 0 | S30: 0 | T30: 0 | U30: 0 | V30: 0 | W30: 0 | X30: 0 | Y30: 0 | Z30: 0 | AA30: 0 | AB30: 0 | AC30: 0 | AD30: 0 | AE30: 0 | AF30: 0 | AG30: 0 | AH30: 0 | AI30: 0 | AJ30: 0 | AK30: 0 | AL30: 0 | AM30: 0 | AN30: 0 | AO30: 0 | AP30: 0 | AQ30: 0 | AR30: 0 | AS30: 0 | AT30: 0 | AU30: 0 | AV30: 0 | AW30: 200 | AX30: 200 | AY30: 200 | AZ30: 200 | BA30: 200 | BB30: 200 | BC30: 200 | BD30: 200 | BE30: 200 | BF30: 200 | BG30: 200 | BH30: 200 | BI30: 200 | BJ30: 200 | BK30: 200
B31: Memberships | C31: 10 | D31: 10 | E31: 10 | F31: 10 | G31: =10+5+20 -> 35 | H31: =10+5+20 -> 35 | I31: =10+20+60 -> 90 | J31: =10+20+30+15 -> 75 | K31: =10+5+20+30 -> 65 | L31: =10+5+20+60 -> 95 | M31: =10+5+20+60 -> 95 | N31: =10+5+20+60 -> 95 | O31: =10+5+20+60 -> 95 | P31: =10+5+20+60+4+4 -> 103 | Q31: =10+5+20+60+35.68 -> 130.68 | R31: =10+5+20+60 -> 95 | S31: =10+13+20+60 -> 103 | T31: =10+13+20+60 -> 103 | U31: =10+13+20+60 -> 103 | V31: =sum(10,13,20,60,4,15,20) -> 142 | W31: =sum(10,13,20,60,4,15,70) -> 192 | X31: =sum(10,13,20,60,4,15,0) -> 122 | Y31: =sum(10,13,20,60,4,15,0) -> 122 | Z31: =sum(10,13,60,4,15,0) -> 102 | AA31: =sum(10,13,60,4,15,0) -> 102 | AB31: =sum(10,13,60,4,15,0) -> 102 | AC31: =sum(10,13,60,4,15,0) -> 102 | AD31: =sum(10,13,60,4,15,0) -> 102 | AE31: =sum(10,13,60,4,15,0) -> 102 | AF31: =sum(10,13,60,4,15,0) -> 102 | AG31: =sum(10,13,60,4,15,0) -> 102 | ... BK31: =sum(10,13,60,4,15,0) -> 102
B32: Travel | C32: 0 | D32: 0 | E32: 500 | F32: 500 | G32: 0 | H32: 0 | I32: 0 | J32: 500 | K32: 450 | L32: 300 | M32: 200 | N32: 100 | O32: 0 | P32: =250+179 -> 429 | Q32: 0 | R32: =260*2 -> 520 | S32: 0 | T32: =sum(500/2,185,25,84,257) -> 801 | U32: =sum(270,250) -> 520 | V32: =sum(300,600,240) -> 1140 | W32: =375+74 -> 449 | X32: 0 | Y32: 0 | Z32: =sum(548.5,400,55.1,92.1,169.66,100) -> 1365.36 | AA32: ='Travel Expenses - Tulum'!C32-Z32 -> 2256.425 | AB32: 90 | AC32: 1200 | AD32: 0 | AE32: 500 | AF32: 0 | AG32: 0 | AH32: 0 | AI32: 0 | AJ32: 0 | AK32: 0 | AL32: =1500+600 -> 2100 | AM32: 0 | AN32: 0 | AO32: 0 | AP32: 0 | AQ32: 0 | AR32: 0 | AS32: 0 | AT32: 0 | AU32: 0 | AV32: 0 | AW32: 0 | AX32: 0 | AY32: 0 | AZ32: =sum(650,375,300) -> 1325 | BA32: 0 | BB32: 0 | BC32: =1700 -> 1700 | BD32: =sum(1850) -> 1850 | BE32: 0 | BF32: 0 | BG32: 0 | BH32: 0 | BI32: 0 | BJ32: 0 | BK32: 0
A33: Home | B33: Home Goods | I33: 600 | J33: 0 | K33: 0 | L33: 0 | M33: 0 | N33: 0 | O33: 0 | P33: =43+83 -> 126 | Q33: =90+266+80 -> 436 | R33: 0 | S33: 0 | T33: 0 | U33: 0 | V33: 0 | W33: 0 | X33: 1000 | Y33: 0 | Z33: =sum(250,100,250) -> 600 | AA33: 0 | AB33: 0 | AC33: 0 | AD33: 0 | AE33: 0 | AF33: 0 | AG33: 0 | AH33: 2000 | AI33: 0 | AJ33: 0 | AK33: 0 | AL33: 25 | AM33: 0 | AN33: 0 | AO33: 0 | AP33: 0 | AQ33: 0 | AR33: 0 | AS33: 0 | AT33: 0 | AU33: 0 | AV33: 0 | AW33: 50 | AX33: 50 | AY33: 50 | AZ33: 50 | BA33: 50 | BB33: 50 | BC33: 1500 | BD33: 50 | BE33: 50 | BF33: 50 | BG33: 50 | BH33: 50 | BI33: 50 | BJ33: 50 | BK33: 50
B34: Books | I34: 10 | J34: 0 | K34: =12*2 -> 24 | L34: 0 | M34: 0 | N34: =12*1 -> 12 | O34: =12*1 -> 12 | P34: =13 -> 13 | Q34: 0 | R34: =12*1 -> 12 | S34: =12*1 -> 12 | T34: =12*1 -> 12 | U34: =12*1 -> 12 | V34: =12*1 -> 12 | W34: =12*1 -> 12 | X34: =12*1 -> 12 | Y34: =12*1 -> 12 | ... AJ34: =12*1 -> 12 | AK34: 0 | AL34: 0 | AM34: =12*1 -> 12 | AN34: =12*1 -> 12 | AO34: =12*1 -> 12 | AP34: =12*1 -> 12 | AQ34: =12*1 -> 12 | AR34: =12*1 -> 12 | AS34: 50 | AT34: =12*1 -> 12 | AU34: =12*1 -> 12 | AV34: =12*1 -> 12 | AW34: =12*1 -> 12 | AX34: =12*1 -> 12 | AY34: =12*1 -> 12 | AZ34: =12*1 -> 12 | BA34: =12*1 -> 12 | ... BK34: =12*1 -> 12
B35: Clothing | I35: 100 | J35: 60 | K35: 250 | L35: 0 | M35: 50 | N35: 0 | O35: 100 | P35: 0 | Q35: 0 | R35: 0 | S35: 0 | T35: 300 | U35: 100 | V35: 100 | W35: 100 | X35: 100 | Y35: 100 | Z35: 100 | AA35: 100 | AB35: 100 | AC35: 100 | AD35: 100 | AE35: 100 | AF35: 100 | AG35: 100 | AH35: 100 | AI35: 100 | AJ35: 100 | AK35: 100 | AL35: 300 | AM35: 300 | AN35: 300 | AO35: 300 | AP35: 300 | AQ35: 300 | AR35: 300 | AS35: 300 | AT35: 300 | AU35: 300 | AV35: 300 | AW35: 300 | AX35: 300 | AY35: 300 | AZ35: 300 | BA35: 300 | BB35: 300 | BC35: =sum(300,2000) -> 2300 | BD35: 300 | BE35: 300 | BF35: 300 | BG35: 300 | BH35: 300 | BI35: 300 | BJ35: 300 | BK35: 300
A36: Health | B36: Dental | C36: 0 | D36: 0 | E36: 0 | F36: 0 | G36: 0 | H36: 0 | I36: 25 | J36: 0 | K36: 0 | L36: 0 | M36: 0 | N36: 0 | O36: 0 | P36: 0 | Q36: 0 | R36: 0 | S36: 0 | T36: 0 | U36: 0 | V36: 0 | W36: 0 | X36: 0 | Y36: 0 | Z36: 0 | AA36: 0 | AB36: 0 | AC36: 0 | AD36: 0 | AE36: 0 | AF36: 0 | AG36: 0 | AH36: 0 | AI36: 0 | AJ36: 0 | AK36: 0 | AL36: 0 | AM36: 0 | AN36: 0 | AO36: 0 | AP36: 0 | AQ36: 0 | AR36: 0 | AS36: 0 | AT36: 0 | AU36: 0 | AV36: 0 | AW36: 0 | AX36: 0 | AY36: 0 | AZ36: 0 | BA36: 0 | BB36: 0 | BC36: 0 | BD36: 0 | BE36: 0 | BF36: 0 | BG36: 0 | BH36: 0 | BI36: 0 | BJ36: 0 | BK36: 0
B37: Healthcare | J37: 0 | K37: 0 | L37: 0 | M37: 0 | N37: 0 | O37: 0 | P37: 0 | Q37: 0 | R37: 0 | S37: 0 | T37: 0 | U37: 0 | V37: =490 -> 490 | W37: 0 | X37: 0 | Y37: 0 | Z37: 0 | AA37: 0 | AB37: 0 | AC37: 0 | AD37: 0 | AE37: 0 | AF37: 0 | AG37: 0 | AH37: 0 | AI37: 0 | AJ37: 0 | AK37: 250 | AL37: 0 | AM37: 0 | AN37: 0 | AO37: 0 | AP37: 0 | AQ37: 0 | AR37: 0 | AS37: 0 | AT37: 0 | AU37: 0 | AV37: 0 | AW37: 0 | AX37: 0 | AY37: 0 | AZ37: 0 | BA37: 0 | BB37: 0 | BC37: 0 | BD37: 0 | BE37: 0 | BF37: 0 | BG37: 0 | BH37: 0 | BI37: 0 | BJ37: 0 | BK37: 0
B38: Self-Care | I38: 100 | J38: =60+20+350 -> 430 | K38: 50 | L38: 60 | M38: 60 | N38: 95 | O38: 100 | P38: 100 | Q38: 60 | R38: 0 | S38: 0 | T38: 100 | U38: 50 | V38: 100 | W38: 100 | X38: 100 | Y38: 100 | Z38: 100 | AA38: 100 | AB38: 100 | AC38: 100 | AD38: 100 | AE38: 100 | AF38: 100 | AG38: 100 | AH38: 100 | AI38: 100 | AJ38: 100 | AK38: 100 | AL38: 100 | AM38: 100 | AN38: 100 | AO38: 100 | AP38: 100 | AQ38: 100 | AR38: 100 | AS38: 100 | AT38: 100 | AU38: 100 | AV38: 100 | AW38: 100 | AX38: 100 | AY38: 100 | AZ38: 100 | BA38: 100 | BB38: 100 | BC38: 100 | BD38: 100 | BE38: 100 | BF38: 100 | BG38: 100 | BH38: 100 | BI38: 100 | BJ38: 100 | BK38: 100
B39: Gym | C39: 0 | D39: 0 | E39: 0 | F39: 0 | G39: 0 | H39: 0 | I39: 0 | J39: 0 | K39: 0 | L39: 0 | M39: 0 | N39: 0 | O39: 0 | P39: 0 | Q39: 0 | R39: 0 | S39: 0 | T39: 0 | U39: 0 | V39: 0 | W39: 0 | X39: 0 | Y39: 0 | Z39: 0 | AA39: 0 | AB39: 0 | AC39: 0 | AD39: 0 | AE39: 0 | AF39: 0 | AG39: 0 | AH39: 100 | AI39: 300 | AJ39: 100 | AK39: 175 | AL39: 175 | AM39: 175 | AN39: 175 | AO39: 175 | AP39: 175 | AQ39: 175 | AR39: 175 | AS39: 175 | AT39: 175 | AU39: 175 | AV39: 175 | AW39: 175 | AX39: 175 | AY39: 175 | AZ39: 175 | BA39: 175 | BB39: 175 | BC39: 175 | BD39: 175 | BE39: 175 | BF39: 175 | BG39: 175 | BH39: 175 | BI39: 175 | BJ39: 175 | BK39: 175
A40: Misc | B40: Dog Stuff | E40: 50 | F40: 50 | G40: 50 | H40: 50 | I40: 100 | J40: =30+40 -> 70 | K40: 0 | L40: 50 | M40: 50 | N40: 20 | O40: 0 | P40: 50 | Q40: 30 | R40: =15+35 -> 50 | S40: 10 | T40: 40 | U40: 30 | V40: =sum(30,100) -> 130 | W40: 30 | X40: 30 | Y40: 30 | Z40: 10 | AA40: 10 | AB40: 10 | AC40: 10 | AD40: 10 | AE40: 10 | AF40: 10 | AG40: 10 | AH40: 10 | AI40: 10 | AJ40: 10 | AK40: 10 | AL40: 10 | AM40: 10 | AN40: 10 | AO40: 10 | AP40: 10 | AQ40: 10 | AR40: 10 | AS40: 0 | AT40: 10 | AU40: 10 | AV40: 10 | AW40: 30 | AX40: 30 | AY40: 30 | AZ40: 30 | BA40: 30 | BB40: 30 | BC40: 30 | BD40: 30 | BE40: 30 | BF40: 30 | BG40: 30 | BH40: 30 | BI40: 30 | BJ40: 30 | BK40: 30
B41: Contractor Services | K41: 0 | L41: 0 | M41: 0 | N41: 250 | O41: 0 | P41: 200 | Q41: 0 | R41: 0 | S41: =0 -> 0 | T41: =840+450 -> 1290 | U41: 0 | V41: 0 | W41: 0 | X41: 0 | Y41: 0 | Z41: 0 | AA41: 0 | AB41: 0 | AC41: 0 | AD41: 0 | AE41: 0 | AF41: 0 | AG41: 0 | AH41: 0 | AI41: 0 | AJ41: 0 | AK41: 0 | AL41: 0 | AM41: 0 | AN41: 0 | AO41: 0 | AP41: 0 | AQ41: 0 | AR41: 0 | AS41: 0 | AT41: 0 | AU41: 0 | AV41: 0 | AW41: 0 | AX41: 0 | AY41: 0 | AZ41: 0 | BA41: 0 | BB41: 0 | BC41: 0 | BD41: 0 | BE41: 0 | BF41: 0 | BG41: 0 | BH41: 0 | BI41: 0 | BJ41: 0 | BK41: 0
B42: Tech | X42: =272+375 -> 647 | Y42: 0 | Z42: 0 | AA42: 0 | AB42: 0 | AC42: 0 | AD42: 0 | AE42: 0 | AF42: 0 | AG42: 0 | AH42: 0 | AI42: 0 | AJ42: 0 | AK42: 0 | AL42: 0 | AM42: 0 | AN42: 0 | AO42: 0 | AP42: 0 | AQ42: 0 | AR42: 0 | AS42: 0 | AT42: 0 | AU42: 0 | AV42: 0 | AW42: 0 | AX42: 0 | AY42: 0 | AZ42: 0 | BA42: 0 | BB42: 0 | BC42: 0 | BD42: 0 | BE42: 0 | BF42: 0 | BG42: 0 | BH42: 0 | BI42: 0 | BJ42: 0 | BK42: 0
B43: Misc. | T43: 0 | U43: 0 | V43: 0 | W43: 0 | X43: =sum(700/2,50,500) -> 900 | Y43: 0 | Z43: 0 | AA43: 0 | AB43: 0 | AC43: 0 | AD43: 0 | AE43: 0 | AF43: 0 | AG43: 0 | AH43: 0 | AI43: 0 | AJ43: 0 | AK43: 0 | AL43: 1500 | AM43: 0 | AN43: 0 | AO43: 0 | AP43: 0 | AQ43: 0 | AR43: 0 | AS43: 0 | AT43: 0 | AU43: 0 | AV43: 0 | AW43: 0 | AX43: 500 | AY43: 0 | AZ43: 0 | BA43: 0 | BB43: 0 | BC43: 0 | BD43: 0 | BE43: 0 | BF43: 0 | BG43: 0 | BH43: 0 | BI43: 0 | BJ43: 0 | BK43: 0
P44: =sum(P17:P41)/P13 -> 0.42297126 | Q44: =sum(Q28:Q41)/Q13 -> 0.13766887 | R44: =sum(R28:R41)/R13 -> 0.15576418 | S44: =sum(S28:S41)/S13 -> 0.047172204 | T44: =sum(T28:T43)/T13 -> 0.5274487 | U44: =sum(U28:U43)/U13 -> 0.19744483 | V44: =sum(V28:V43)/V13 -> 0.41050684 | W44: =sum(W28:W43)/W13 -> 0.23275261 | X44: =sum(X28:X43)/X13 -> 0.54680604 | Y44: =sum(Y28:Y43)/Y13 -> 0.17947336 | Z44: =sum(Z28:Z43)/Z13 -> 0.45333636 | AA44: =sum(AA28:AA43)/AA13 -> 0.44095739 | ... BK44: =sum(BK28:BK43)/BK13 -> 0.056606061
A45: Total Expenses | C45: =sum(C17:C40) -> 2850.475 | D45: =sum(D17:D40) -> 2700.475 | E45: =sum(E17:E40) -> 3250.475 | F45: =sum(F17:F40) -> 3499.265 | G45: =sum(G17:G40) -> 2895.475 | H45: =sum(H23:H40) -> 785 | I45: =sum(I23:I40) -> 2273 | J45: =sum(J23:J40) -> 3319 | K45: =sum(K23:K40) -> 3083 | L45: =sum(L23:L40) -> 3545 | M45: =sum(M23:M40) -> 1923 | N45: =sum(N23:N41) -> 3152 | O45: =sum(O23:O41) -> 2351 | P45: =sum(P17:P41) -> 5021.9377 | Q45: =sum(Q17:Q41) -> 3812.7817 | R45: =sum(R17:R41) -> 3794.0991 | S45: =sum(S17:S41) -> 3076.9499 | T45: =sum(T17:T43) -> 6218.1204 | U45: =sum(U17:U43) -> 1855.0898 | V45: =sum(V17:V43) -> 4730.2895 | W45: =sum(W17:W43) -> 3161.2568 | X45: =sum(X17:X43) -> 6665.4853 | Y45: =sum(Y17:Y25,Y28:Y43) -> 5063.475 | Z45: =sum(Z17:Z25,Z28:Z43) -> 6769.65 | AA45: =sum(AA17:AA25,AA28:AA43) -> 6823.99 | AB45: =sum(AB17:AB25,AB28:AB43) -> 4957.565 | AC45: =sum(AC17:AC25,AC28:AC43) -> 6158.565 | AD45: =sum(AD17:AD25,AD28:AD43) -> 4358.565 | AE45: =sum(AE17:AE25,AE28:AE43) -> 4858.565 | AF45: =sum(AF17:AF25,AF28:AF43) -> 4358.565 | ... BK45: =sum(BK17:BK25,BK28:BK43) -> 6909
A47: Financial Health (40%)
A48: Debt Consolidation (10%)
B49: Charge Card (Weekly Expenses) | X49: =X$13*0.24 -> 1549.8 | Y49: =sum(Y45-Y17) -> 3323.475 | Z49: =sum(Z45-Z17) -> 5197.95 | AA49: =sum(AA45-AA17) -> 5083.99 | AB49: =sum(AB45-AB17) -> 3217.565 | AC49: =sum(AC45-AC17) -> 4418.565 | AD49: =sum(AD45-AD17) -> 2618.565 | AE49: =sum(AE45-AE17) -> 3118.565 | AF49: =sum(AF45-AF17) -> 2618.565 | ... BK49: =sum(BK45-BK17) -> 4109
B50: Debt Repayment (10%) | C50: 2500 | D50: 4500 | E50: 2800 | F50: 2800 | G50: 2000 | H50: 3093 | I50: 1600 | J50: ='PAYMENT SCHEDULE'!C13+'PAYMENT SCHEDULE'!C29 -> 3200 | K50: =LIABILITIES!E26 -> 1000 | L50: =LIABILITIES!E26 -> 1000 | M50: ='PAYMENT SCHEDULE'!C33 | N50: =N13*0.25 -> 1732.5 | O50: =O13*0.35 -> 2520 | P50: 5956 | Q50: 2008 | R50: =R13*0.4 -> 2663 | S50: 5600 | T50: =T13*0.25 -> 1614.375 | U50: =U13*0.4 -> 2583 | V50: =3397 -> 3397 | W50: =W13*0.3 -> 1937.25 | X50: =X$13*0.11 -> 710.325 | Y50: =Y$13*0.1 -> 1205.75 | Z50: =Z$13*0.1 -> 880 | AA50: =AA$13*0.33 -> 2904 | AB50: =AB$13*0.2 -> 1760 | AC50: =AC$13*0.2 -> 1833.3333 | AD50: =AD$13*0.25 -> 2186.6667 | AE50: =AE$13*0.7 -> 13822.667 | AF50: =AF$13*0.25 -> 2525 | AG50: =AG$13*0.15 -> 1680 | AH50: =AH$13*0.15 -> 3870 | AI50: =AI$13*0.18 -> 1524 | AJ50: =AJ$13*0.18 -> 1524 | AK50: =AK$13*0.18 -> 3379.5 | AL50: =AL$13*0.05 -> 577.5 | AM50: =AM$13*0.1 -> 1155 | AN50: =AN$13*0.4 -> 8620 | AO50: =AO$13*0.1 -> 1255 | AP50: =17000 -> 17000 | AQ50: =AQ$13*0.1 -> 1155 | AR50: =AR$13*0.3 -> 3465 | AS50: =AS$13*0.3 -> 3465 | AT50: =AT$13*0.5 -> 8150.555 | AU50: =AU$13*0.2 -> 5550 | AV50: =AV$13*0.1 -> 1155 | AW50: =AW$13*0.1+2530 -> 3685 | AX50: =AX$13*0.1+2000 -> 3489.4 | AY50: =AY$13*0.1 -> 1435 | AZ50: 16000 | BA50: 15000 | BB50: 2400 | BC50: 2400 | BD50: 2400 | BE50: 2400 | BF50: 2400 | BG50: 2400 | BH50: 2400 | BI50: 2400 | BJ50: 2400 | BK50: 2400
A51: Savings (19%)
B52: Long-Term High-Yield Savings (10%) | I52: 0 | J52: 0 | K52: =K13*0 -> 0 | L52: =L13*0 -> 0 | M52: 0 | N52: 25 | O52: 25 | P52: 20 | Q52: 25 | R52: 0 | S52: 0 | T52: 0 | U52: 0 | V52: 0 | W52: 0 | X52: =$X$13*0.03 -> 193.725 | Y52: =$X$13*0.03 -> 193.725 | Z52: =$X$13*0.1 -> 645.75 | AA52: =$X$13*0.03 -> 193.725 | AB52: =$X$13*0.03 -> 193.725 | AC52: =$X$13*0.03 -> 193.725 | AD52: =$X$13*0 -> 0 | AE52: =$X$13*0 -> 0 | AF52: =$X$13*0 -> 0 | AG52: =$X$13*0 -> 0 | AH52: =$X$13*0 -> 0 | AI52: =$X$13*0.03 -> 193.725 | AJ52: =$X$13*0.03 -> 193.725 | AK52: =$X$13*0.032 -> 206.64 | AL52: =$X$13*0.032 -> 206.64 | AM52: =$X$13*0.032 -> 206.64 | AN52: =$X$13*0.05 -> 322.875 | AO52: =$X$13*0.05 -> 322.875 | AP52: =$X$13*0.05 -> 322.875 | AQ52: =$X$13*0.05 -> 322.875 | AR52: =$X$13*0.05 -> 322.875 | AS52: =$X$13*0 -> 0 | AT52: =$X$13*0.05 -> 322.875 | AU52: =$X$13*0.05 -> 322.875 | AV52: =$X$13*0.05 -> 322.875 | AW52: 0 | AX52: 0 | AY52: 0 | AZ52: 0 | BA52: 0 | BB52: 0 | BC52: =$X$13*0.05 -> 322.875 | BD52: 1000 | BE52: 1000 | BF52: 1000 | BG52: 1000 | BH52: 1000 | BI52: 1000 | BJ52: 1000 | BK52: 1000
B53: Short-Term Liquid Traditional Savings (10%) | R53: 0 | S53: 500 | T53: =T13*0.02 -> 129.15 | U53: =U13*0.0387 -> 249.90525 | V53: 200 | W53: 200 | X53: =$X$13*0.04 -> 258.3 | Y53: =$X$13*0.04 -> 258.3 | Z53: =$X$13*0.1 -> 645.75 | AA53: =$X$13*0.047 -> 303.5025 | AB53: =$X$13*0.04 -> 258.3 | AC53: =$X$13*0.04 -> 258.3 | AD53: =$X$13*0.05 -> 322.875 | AE53: =$X$13*0.063 -> 406.8225 | AF53: =$X$13*0.2 -> 1291.5 | AG53: =$X$13*0.2 -> 1291.5 | AH53: =$X$13*0 -> 0 | AI53: =$X$13*0.04 -> 258.3 | AJ53: =$X$13*0.04 -> 258.3 | AK53: =$X$13*0.04 -> 258.3 | AL53: =$X$13*0.04 -> 258.3 | AM53: =$X$13*0.04 -> 258.3 | AN53: =$X$13*0.05 -> 322.875 | AO53: =$X$13*0.05 -> 322.875 | AP53: =$X$13*0.05 -> 322.875 | AQ53: =$X$13*0.05 -> 322.875 | AR53: =$X$13*0.05 -> 322.875 | AS53: =$X$13*0.05 -> 322.875 | AT53: =$X$13*0.05 -> 322.875 | AU53: =$X$13*0.05 -> 322.875 | ... AW53: =$X$13*0.05 -> 322.875 | AX53: =$X$13*0 -> 0 | AY53: =$X$13*0 -> 0 | AZ53: =$X$13*0.05 -> 322.875 | BA53: 0 | BB53: 0 | BC53: 0 | BD53: =$X$13*0.05 -> 322.875 | BE53: =$X$13*0.05 -> 322.875 | BF53: =$X$13*0.05 -> 322.875 | BG53: =$X$13*0.05 -> 322.875 | BH53: =$X$13*0.05 -> 322.875 | BI53: =$X$13*0.05 -> 322.875 | BJ53: =$X$13*0.05 -> 322.875 | BK53: =$X$13*0.05 -> 322.875
A54: Investment (10%)
B55: EVM Fund (1%) | K55: 0 | L55: =150+345 -> 495 | M55: 0 | N55: 0 | O55: =O13*0 -> 0 | P55: 78 | Q55: 0 | R55: 0 | S55: 50 | T55: =$Q13*0 -> 0 | U55: =$Q13*0 -> 0 | V55: =$Q13*0 -> 0 | W55: =$Q13*0 -> 0 | X55: =$X$13*0.01 -> 64.575 | Y55: =$X$13*0.01 -> 64.575 | Z55: =$X$13*0.01 -> 64.575 | AA55: =$X$13*0.01 -> 64.575 | AB55: =$X$13*0 -> 0 | AC55: =$X$13*0 -> 0 | AD55: =$X$13*0 -> 0 | AE55: =$X$13*0 -> 0 | AF55: =$X$13*0 -> 0 | AG55: =sum(2500,1200) -> 3700 | AH55: =sum(2500,500,5000) -> 8000 | AI55: =2000 -> 2000 | AJ55: =$X$13*0 -> 0 | AK55: =$X$13*0 -> 0 | AL55: =7000 -> 7000 | AM55: 3600 | AN55: 3500 | AO55: =$X$13*0 -> 0 | AP55: =6000 -> 6000 | AQ55: =$X$13*0 -> 0 | AR55: =$X$13*1 -> 6457.5 | AS55: =$X$13*0 -> 0 | AT55: =$X$13*0 -> 0 | AU55: 10000 | AV55: 0 | AW55: =$X$13*0 -> 0 | AX55: 1000 | AY55: 900 | AZ55: 900 | BA55: =sum(3509,1490,500) -> 5499 | BB55: 0 | BC55: 0 | BD55: =sum(900) -> 900 | BE55: =sum(900) -> 900 | BF55: =sum(900) -> 900 | BG55: =sum(900) -> 900 | BH55: =sum(900) -> 900 | BI55: =sum(900) -> 900 | BJ55: =sum(900) -> 900 | BK55: 0
